Workbook
Name \a: #REF!
Name \b: #REF!
Name \c: #REF!
Name \d: #REF!
Name \e: #REF!
Name \f: #REF!
Name \g: #REF!
Name \h: #REF!
Name \i: #REF!
Name \j: #REF!
Name \k: #REF!
Name \l: #REF!
Name \m: #REF!
Name \n: #REF!
Name \o: #REF!
Name \p: #REF!
Name \q: #REF!
Name \r: #REF!
Name \s: #REF!
Name \t: #REF!
Name \u: #REF!
Name \v: #REF!
Name \w: #REF!
Name \x: #REF!
Name \Y: #REF!
Name \z: #REF!
Name ______________________________________________________________________________R: #REF!
Name ______________________________________________________________________________rad2: #REF!
Name _____________________________________________________________________________R: #REF!
Name _____________________________________________________________________________rad2: #REF!
Name ____________________________________________________________________________R: #REF!
Name ____________________________________________________________________________rad2: #REF!
Name ___________________________________________________________________________R: #REF!
Name ___________________________________________________________________________rad2: #REF!
Name __________________________________________________________________________R: #REF!
Name __________________________________________________________________________rad2: #REF!
Name _________________________________________________________________________R: #REF!
Name _________________________________________________________________________rad2: #REF!
Name ________________________________________________________________________R: #REF!
Name ________________________________________________________________________rad2: #REF!
Name _______________________________________________________________________R: #REF!
Name _______________________________________________________________________rad2: #REF!
Name ______________________________________________________________________R: #REF!
Name ______________________________________________________________________rad2: #REF!
Name _____________________________________________________________________R: #REF!
Name _____________________________________________________________________rad2: #REF!
Name ____________________________________________________________________R: #REF!
Name ____________________________________________________________________rad2: #REF!
Name ___________________________________________________________________R: #REF!
Name ___________________________________________________________________rad2: #REF!
Name __________________________________________________________________R: #REF!
Name __________________________________________________________________rad2: #REF!
Name _________________________________________________________________R: #REF!
Name _________________________________________________________________rad2: #REF!
Name ________________________________________________________________rad2: #REF!
Name ____________________________________OP9: #REF!
Name ___________________________________OP9: #REF!
Name __________________________________OP9: #REF!
Name ________________________GYE1: #REF!
Name ________________________gye2: #REF!

Sheet FLOW MEDIOS
E3: FLOW DE MEDIOS
E4: CAMPAÑA VAC COSTA 2026
E6: 2026
E7: ENERO | I7: FEBRERO | M7: MARZO | R7: ABRIL | Z7: DETALLE DE INVERSIÓN | AC7: DETALLE DE COMPRA
E8: 5 | F8: 12 | G8: 19 | H8: =G8+7 -> 26 | I8: 2 | J8: =I8+7 -> 9 | K8: =J8+7 -> 16 | L8: =K8+7 -> 23 | M8: 2 | N8: =M8+7 -> 9 | O8: =N8+7 -> 16 | P8: =O8+7 -> 23 | Q8: =P8+7 -> 30 | R8: 6 | S8: =R8+7 -> 13 | T8: =S8+7 -> 20 | U8: =T8+7 -> 27 | V8: =U8+7 -> 34 | X8: TOTAL INVERSIÓN | Z8: MARKETING | AA8: NEGOCIO | AC8: PAUTA PAGADA | AD8: PREPAGO | AE8: COMPROMISOS
D9: LAYER 01 AWARENESS
D10: TELEVISIÓN | X10: =SUM(E11:Q12) -> 45620
D11: PAUTA REGULAR - ECUAVISA | E11: =+'PAUTA TELEVISIÓN OP2'!CT19+'PAUTA TELEVISIÓN OP2'!CT54 -> 10186.23 | I11: =+'PAUTA TELEVISIÓN OP2'!CU19+'PAUTA TELEVISIÓN OP2'!CU54 -> 17413.77 | Z11: =SUM(E11:Q11) -> 27600 | AC11: =SUM(D11:P11) -> 27600
D12: PAUTA REGULAR - TC TELEVISIÓN | E12: =+'PAUTA TELEVISIÓN OP2'!CT75 -> 9247.9967 | I12: =+'PAUTA TELEVISIÓN OP2'!CU75 -> 8772.0033 | Z12: =SUM(E12:Q12) -> 18020 | AC12: =SUM(D12:P12) -> 18020
D13: VÍA PÚBLICA | X13: =SUM(E14:Q17) -> 13000
D14: VALLAS | E14: =+'PAUTA VALLAS'!Q30 -> 8600 | I14: 0 | Z14: =SUM(E14:Q14) -> 8600 | AC14: =SUM(E14:Q14) -> 8600
D15: CIRCUITO VIA LA COSTA | E15: =+'CIRCUITO VIA LA COSTA'!N11 -> 4400 | I15: 0 | Z15: =SUM(E15:Q15) -> 4400 | AC15: =SUM(E15:Q15) -> 4400
D16: PANTALLAS LEDS | E16: 0 | I16: 0 | Z16: =SUM(E16:Q16) -> 0 | AC16: =SUM(E16:Q16) -> 0
D17: VALLAS HIBRIDAS | E17: 0 | I17: 0 | Z17: =SUM(E17:Q17) -> 0 | AC17: =SUM(E17:Q17) -> 0
D18: REVISTAS | X18: 0
D19: REVISTA DINERS | I19: 0 | Z19: =SUM(E19:Q19) -> 0 | AC19: =SUM(E19:Q19) -> 0
D20: DIGITAL | X20: =SUM(E21:Q24) -> 7500
D21: META | E21: =+'PAUTA DIGITAL'!AB14+'PAUTA DIGITAL'!AB15 -> 1140 | I21: =+'PAUTA DIGITAL'!AI14+'PAUTA DIGITAL'!AI15 -> 760 | Z21: =+E21+I21 -> 1900 | AC21: =+Z21 -> 1900
D22: TIK TOK | E22: =+'PAUTA DIGITAL'!AB16+'PAUTA DIGITAL'!AB17 -> 360 | I22: =+'PAUTA DIGITAL'!AI16+'PAUTA DIGITAL'!AI17 -> 240 | Z22: =+E22+I22 -> 600 | AC22: =+Z22 -> 600
D23: YOUTUBE | E23: =+'PAUTA DIGITAL'!AB18+'PAUTA DIGITAL'!AB19+'PAUTA DIGITAL'!AB20+'PAUTA DIGITAL'!AB21 -> 600 | I23: =+'PAUTA DIGITAL'!AI18+'PAUTA DIGITAL'!AI19+'PAUTA DIGITAL'!AI20+'PAUTA DIGITAL'!AI21 -> 400 | Z23: =+E23+I23 -> 1000 | AC23: =+Z23 -> 1000
D24: DV360 | E24: =+'PAUTA DIGITAL'!AB22 -> 2400 | I24: =+'PAUTA DIGITAL'!AI22 -> 1600 | Z24: =+E24+I24 -> 4000 | AD24: =+Z24 -> 4000
D26: SUBTOTAL | E26: =SUM(E11:H12,E14:H16,E21:H24) -> 36934.227 | I26: =SUM(I11:L12,I14:L16,I21:L24) -> 29185.773 | M26: =SUM(M11:Q11,M14:Q16,M21:Q24) -> 0 | R26: =SUM(R11:V11,R14:V16,R21:V24) -> 0 | X26: =SUM(X10:X20) -> 66120 | Z26: =SUM(Z11:Z24) -> 66120 | AA26: =SUM(AA11:AA24) -> 0 | AC26: =SUM(AC11:AC24) -> 62120 | AD26: =SUM(AD11:AD24) -> 4000 | AE26: =SUM(AE11:AE24) -> 0
D28: LAYER 02 CONSIDERACION
D29: DIGITAL | X29: =SUM(E30:Q32) -> 10363.9
D30: META | E30: ='[3]PAUTA DIGITAL'!AB24+'[3]PAUTA DIGITAL'!AB25+'[3]PAUTA DIGITAL'!AB26+'[3]PAUTA DIGITAL'!AB27+'[3]PAUTA DIGITAL'!AB32+'[3]PAUTA DIGITAL'!AB33+'[3]PAUTA DIGITAL'!AB34+'[3]PAUTA DIGITAL'!AB35+'[3]PAUTA DIGITAL'!AB40+'[3]PAUTA DIGITAL'!AB41+'[3]PAUTA DIGITAL'!AB42+'[3]PAUTA DIGITAL'!AB43 -> 1236.141 | I30: ='[3]PAUTA DIGITAL'!AG24+'[3]PAUTA DIGITAL'!AG25+'[3]PAUTA DIGITAL'!AG26+'[3]PAUTA DIGITAL'!AG27+'[3]PAUTA DIGITAL'!AG32+'[3]PAUTA DIGITAL'!AG33+'[3]PAUTA DIGITAL'!AG34+'[3]PAUTA DIGITAL'!AG35+'[3]PAUTA DIGITAL'!AG40+'[3]PAUTA DIGITAL'!AG41+'[3]PAUTA DIGITAL'!AG42+'[3]PAUTA DIGITAL'!AG43 -> 3090.3525 | M30: ='[3]PAUTA DIGITAL'!BI24+'[3]PAUTA DIGITAL'!BI25+'[3]PAUTA DIGITAL'!BI26+'[3]PAUTA DIGITAL'!BI27+'[3]PAUTA DIGITAL'!BI32+'[3]PAUTA DIGITAL'!BI33+'[3]PAUTA DIGITAL'!BI34+'[3]PAUTA DIGITAL'!BI35+'[3]PAUTA DIGITAL'!BI40+'[3]PAUTA DIGITAL'!BI41+'[3]PAUTA DIGITAL'!BI42+'[3]PAUTA DIGITAL'!BI43 -> 1854.2115 | Z30: =+'[4]PAUTA DIGITAL'!L24+'[4]PAUTA DIGITAL'!L25+'[4]PAUTA DIGITAL'!L26+'[4]PAUTA DIGITAL'!L27+'[4]PAUTA DIGITAL'!L34 -> 2230.2663 | AA30: =+'[4]PAUTA DIGITAL'!M34+'[4]PAUTA DIGITAL'!M35+'[4]PAUTA DIGITAL'!M36+'[4]PAUTA DIGITAL'!M37+'[4]PAUTA DIGITAL'!M44+'[4]PAUTA DIGITAL'!M45+'[4]PAUTA DIGITAL'!M46+'[4]PAUTA DIGITAL'!M47 -> 4099.9327 | AC30: =+Z30+AA30 -> 6330.199
D31: YOUTUBE | E31: ='[3]PAUTA DIGITAL'!AB30+'[3]PAUTA DIGITAL'!AB31+'[3]PAUTA DIGITAL'!AB38+'[3]PAUTA DIGITAL'!AB39+'[3]PAUTA DIGITAL'!AB46+'[3]PAUTA DIGITAL'!AB47 -> 189.47907 | I31: ='[3]PAUTA DIGITAL'!AG47+'[3]PAUTA DIGITAL'!AG46+'[3]PAUTA DIGITAL'!AG39+'[3]PAUTA DIGITAL'!AG38+'[3]PAUTA DIGITAL'!AG31+'[3]PAUTA DIGITAL'!AG30 -> 473.69766 | M31: ='[3]PAUTA DIGITAL'!BI47+'[3]PAUTA DIGITAL'!BI46+'[3]PAUTA DIGITAL'!BI38+'[3]PAUTA DIGITAL'!BI39+'[3]PAUTA DIGITAL'!BI30+'[3]PAUTA DIGITAL'!BI31 -> 284.2186 | Z31: =+'[4]PAUTA DIGITAL'!L30+'[4]PAUTA DIGITAL'!L31+'[4]PAUTA DIGITAL'!L32+'[4]PAUTA DIGITAL'!L33 -> 497.15549 | AA31: =+'[4]PAUTA DIGITAL'!M40+'[4]PAUTA DIGITAL'!M41+'[4]PAUTA DIGITAL'!M42+'[4]PAUTA DIGITAL'!M43+'[4]PAUTA DIGITAL'!M50+'[4]PAUTA DIGITAL'!M51+'[4]PAUTA DIGITAL'!M52+'[4]PAUTA DIGITAL'!M53 -> 994.31099 | AC31: =+Z31+AA31 -> 1491.4665
D32: TIKTOK | E32: ='[3]PAUTA DIGITAL'!AB45+'[3]PAUTA DIGITAL'!AB44+'[3]PAUTA DIGITAL'!AB37+'[3]PAUTA DIGITAL'!AB36+'[3]PAUTA DIGITAL'!AB29+'[3]PAUTA DIGITAL'!AB28 -> 647.15992 | I32: ='[3]PAUTA DIGITAL'!AG28+'[3]PAUTA DIGITAL'!AG29+'[3]PAUTA DIGITAL'!AG36+'[3]PAUTA DIGITAL'!AG37+'[3]PAUTA DIGITAL'!AG44+'[3]PAUTA DIGITAL'!AG45 -> 1617.8998 | M32: ='[3]PAUTA DIGITAL'!BI45+'[3]PAUTA DIGITAL'!BI44+'[3]PAUTA DIGITAL'!BI36+'[3]PAUTA DIGITAL'!BI37+'[3]PAUTA DIGITAL'!BI28+'[3]PAUTA DIGITAL'!BI29 -> 970.73987 | Z32: =+'[4]PAUTA DIGITAL'!L28+'[4]PAUTA DIGITAL'!L29 -> 645.73324 | AA32: =+'[4]PAUTA DIGITAL'!M38+'[4]PAUTA DIGITAL'!M39+'[4]PAUTA DIGITAL'!M48+'[4]PAUTA DIGITAL'!M49 -> 1291.4665 | AC32: =+Z32+AA32 -> 1937.1997
D34: SUBTOTAL | E34: =SUM(E30:H33) -> 2072.78 | I34: =SUM(I30:L33) -> 5181.9499 | M34: =SUM(M30:Q33) -> 3109.17 | R34: =SUM(R30:V33) -> 0 | X34: =SUM(X29:X29) -> 10363.9 | Z34: =SUM(Z29:Z32) -> 3373.1551 | AA34: =SUM(AA29:AA32) -> 6385.7101 | AC34: =SUM(AC29:AC32) -> 9758.8652 | AD34: =SUM(AD29:AD32) -> 0 | AE34: =SUM(AE29:AE32) -> 0
D36: LAYER 03 MOVILIZACION
D37: DIGITAL | X37: =SUM(E38:V39) -> 11853
D38: META | I38: =+'[4]PAUTA DIGITAL'!AF63+'[4]PAUTA DIGITAL'!AF65+'[4]PAUTA DIGITAL'!AF67 -> 2151 | M38: =+'[4]PAUTA DIGITAL'!BH63+'[4]PAUTA DIGITAL'!BH65+'[4]PAUTA DIGITAL'!BH67 -> 2151 | R38: =+'[4]PAUTA DIGITAL'!CM63+'[4]PAUTA DIGITAL'!CM65+'[4]PAUTA DIGITAL'!CM67 -> 2151 | AA38: =+I38+M38+R38 -> 6453 | AC38: =+AA38 -> 6453
D39: GOOGLE | I39: =+'[4]PAUTA DIGITAL'!AF64+'[4]PAUTA DIGITAL'!AF66+'[4]PAUTA DIGITAL'!AF68 -> 1800 | M39: =+'[4]PAUTA DIGITAL'!BH64+'[4]PAUTA DIGITAL'!BH66+'[4]PAUTA DIGITAL'!BH68 -> 1800 | R39: =+'[4]PAUTA DIGITAL'!CM64+'[4]PAUTA DIGITAL'!CM66+'[4]PAUTA DIGITAL'!CM68 -> 1800 | AA39: =+I39+M39+R39 -> 5400 | AC39: =+AA39 -> 5400
D41: APP BLU
D42: DIGITAL | X42: =SUM(E43:V43) -> 20.355
D43: META | I43: =+'PAUTA DIGITAL'!AT76+'PAUTA DIGITAL'!AT77+'PAUTA DIGITAL'!AT78+'PAUTA DIGITAL'!AT79 -> 6.785 | M43: =+'PAUTA DIGITAL'!BK76+'PAUTA DIGITAL'!BK77+'PAUTA DIGITAL'!BK78+'PAUTA DIGITAL'!BK79 -> 6.785 | R43: =+'PAUTA DIGITAL'!CP76+'PAUTA DIGITAL'!CP77+'PAUTA DIGITAL'!CP78+'PAUTA DIGITAL'!CP79 -> 6.785 | AA43: =+I43+M43+R43 -> 20.355 | AC43: =+AA43 -> 20.355
D45: DE UNA
D46: DIGITAL | X46: =SUM(E47:V48) -> 795.6095
D47: META | I47: =+'PAUTA DIGITAL'!N81 -> 499.1 | AA47: =+I47+M47+R47 -> 499.1 | AC47: =+AA47 -> 499.1
D48: GOOGLE | I48: =+'PAUTA DIGITAL'!N82 -> 296.5095 | AA48: =+I48+M48+R48 -> 296.5095 | AC48: =+AA48 -> 296.5095
D50: SUBTOTAL | E50: =SUM(E39:H44) -> 0 | I50: =SUM(I38:L48) -> 4753.3945 | M50: =SUM(M43:Q49) -> 6.785 | R50: =SUM(R43:V49) -> 6.785 | X50: =SUM(X37:X46) -> 12668.965 | Z50: =SUM(Z37:Z48) -> 0 | AA50: =SUM(AA37:AA48) -> 12668.965 | AC50: =SUM(AC37:AC48) -> 12668.965 | AD50: =SUM(AD37:AD39) -> 0 | AE50: =SUM(AE37:AE39) -> 0
D52: SUBTOTAL | E52: =E26+E34+E50 -> 39007.007 | I52: =I26+I34+I50 -> 39121.118 | M52: =+M50+M34+M26 -> 3115.955 | R52: =+R50+R34+R26 -> 6.785 | X52: =X26+X34+X50 -> 89152.864 | Z52: =Z34+Z26+Z50 -> 69493.155 | AA52: =AA34+AA26+AA50 -> 19054.675 | AC52: =AC34+AC26+AC50 -> 84547.83 | AD52: =AD34+AD26 -> 4000 | AE52: =AE26+AE34 -> 0
D53: FEE PRIMICIAS | M53: 1760 | R53: 1760 | X53: =+'[4]PAUTA DIGITAL'!N77 -> 4000 | Z53: =+'[4]PAUTA DIGITAL'!L77 -> 3206.4516 | AA53: =+'[4]PAUTA DIGITAL'!M77 -> 793.54841 | AC53: =+Z53+AA53 -> 4000
D54: FEE DIGITAL 20% | E54: =SUM(E21:H24,E29:H32,E39)*20% -> 1314.556 | I54: =SUM(I21:L24,I29:L32,I38:L39,I43)*20% -> 2427.947 | M54: =SUM(M38:Q39,M43)*20% -> 791.557 | R54: =SUM(R38:V39,R43)*20% -> 791.557 | X54: =SUM(E54:V54) -> 5325.617 | Z54: =+'[4]PAUTA DIGITAL'!L76 -> 2294.631 | AA54: =+'[4]PAUTA DIGITAL'!M76 -> 3967.742 | AC54: =+Z54+AA54 -> 6262.373
D55: VALOR TOTAL | E55: =SUM(E52:H54) -> 40321.563 | I55: =SUM(I52:L54) -> 41549.065 | M55: =SUM(M52:Q54) -> 5667.512 | R55: =SUM(R52:V54) -> 2558.342 | X55: =SUM(X52:X54) -> 98478.481 | Z55: =SUM(Z52:Z54) -> 74994.238 | AA55: =SUM(AA52:AA54) -> 23815.965 | AC55: =SUM(AC52:AC54) -> 94810.203 | AD55: =SUM(AD52:AD54) -> 4000 | AE55: =SUM(AE52:AE54) -> 0
D56: *VALORES NO INCLUYEN IVA
X57: 104600
X58: =+X57-X55 -> 6121.5187

Sheet PAUTA DIGITAL
C3: JOB | D3: DCEEA5A10068
C4: MKT | D4: MKT0022145 | E4: MKT0022086
C5: RESPONSABLE MLD | D5: CRISTIAN TAPIA
C6: RESPONSABLE DCE | D6: FERNANDO VILLACIS
C7: CLIENTE: | D7: DINERS CLUB DEL ECUADOR | R7: =ED14+ED15 -> 946.0705
C8: PRODUCTO: | D8: INSTITUCIONAL | R8: =R14+R15 -> 1900
C9: CAMPAÑA: | D9: VAC COSTA 2026
P10: 2285.71 | R10: =R8-R7 -> 953.9295
C12: =D9 -> VAC COSTA 2026 | T12: ENERO | AI12: FEBRERO | BK12: MARZO | CP12: ABRIL | DW12: KPI | DZ12: MONITOREO
C13: ETAPA | D13: SUB ETAPA | E13: MEDIO | F13: FORMATO | G13: MENSAJE | H13: SEGMENTACIÓN | I13: TAMAÑO AUDIENCIA | J13: TIPO DE COMPRA | K13: SHARE | L13: =+E4 -> MKT0022086 | M13: =+D4 -> MKT0022145 | N13: INVERSIÓN | O13: PLATAFORMA | P13: REAL EJECUTADO ENERO | R13: ORIGINAL | S13: Plat. | T13: 16 | U13: 17 | V13: 18 | W13: 19 | X13: 20 | Y13: 21 | Z13: 22 | AA13: 23 | AB13: 24 | AC13: 25 | AD13: 26 | AE13: 27 | AF13: 28 | AG13: 29 | AH13: 30 | AI13: 1 | AJ13: 2 | AK13: 3 | AL13: 4 | AM13: 5 | AN13: 6 | AO13: 7 | AP13: 8 | AQ13: 9 | AR13: 10 | AS13: 11 | AT13: 12 | AU13: 13 | AV13: 14 | AW13: 15 | AX13: 16 | AY13: 17 | AZ13: 18 | BA13: 19 | BB13: 20 | BC13: 21 | BD13: 22 | BE13: 23 | BF13: 24 | BG13: 25 | BH13: 26 | BI13: 27 | BJ13: 28 | BK13: 1 | BL13: 2 | BM13: 3 | BN13: 4 | BO13: 5 | BP13: 6 | BQ13: 7 | BR13: 8 | BS13: 9 | BT13: 10 | BU13: 11 | BV13: 12 | BW13: 13 | BX13: 14 | BY13: 15 | BZ13: 16 | CA13: 17 | CB13: 18 | CC13: 19 | CD13: 20 | CE13: 21 | CF13: 22 | CG13: 23 | CH13: 24 | CI13: 25 | CJ13: 26 | CK13: 27 | CL13: 28 | CM13: 29 | CN13: 30 | CO13: 31 | CP13: 1 | CQ13: 2 | CR13: 3 | CS13: 4 | CT13: 5 | CU13: 6 | CV13: 7 | CW13: 8 | CX13: 9 | CY13: 10 | CZ13: 11 | DA13: 12 | DB13: 13 | DC13: 14 | DD13: 15 | DE13: 16 | DF13: 17 | DG13: 18 | DH13: 19 | DI13: 20 | DJ13: 21 | DK13: 22 | DL13: 23 | DM13: 24 | DN13: 25 | DO13: 26 | DP13: 27 | DQ13: 28 | DR13: 29 | DS13: 30 | DT13: FRECUENCIA MÁXIMA | DU13: ALCANCE ESTIMADO PERSONAS | DV13: ALCANCE ESTIMADO COBERTURA | DW13: Costo | DX13: Objetivo | DZ13: IMPORTE GASTADO | EA13: REMANENTE | EB13: AVANCE PPTO | EC13: FECHA MONITOREO | ED13: REAL CUMPLIDO | EE13: TIPO DE COMPRA | EF13: AVANCE OBJETIVOS | EG13: RESULTADOS | EH13: COSTO POR RESULTADO | EI13: CPV | EJ13: CPC | EK13: CPM | EL13: ALCANCE | EM13: FREC | EN13: CLICS | EO13: THRU´PLAYS | EP13: IMPRESIONES | EQ13: CTR | ER13: VTR | ES13: NOMBRE DE CAMPAÑA | ET13: ESTADO DE LA CAMPAÑA | EU13: BASES | EV13: UTM
C14: LAYER 01 AWARENESS | D14: LANZAMIENTO | E14: META | F14: PROMOTED VIDEO | G14: Video hero posicionamiento con experiencias únicas generación de interés en Alto Valor | H14: BASE SOCIOS DINERS REGION COSTA | I14: 266000 | J14: CPM | K14: =+N14/$N$84 -> 0.039301911 | L14: =+N14 -> 1200 | N14: 1200 | O14: =+N14/1.15 -> 1043.4783 | P14: 206.97 | R14: 1200 | AB14: =+N14*60% -> 720 | AI14: =+N14*40% -> 480 | DU14: =358000*55% -> 196900 | DV14: 0.59 | DW14: 0.05 | DX14: =O14/DW14*1000 -> 20869565 | DZ14: 519.03 | EA14: =+O14-DZ14 -> 524.44826 | EB14: =+DZ14/O14 -> 0.49740375 | EC14: 46073 | ED14: =+DZ14*1.15 -> 596.8845 | EE14: CPM | EF14: =+EG14/DX14 -> 0.075341627 | EG14: =+EP14 -> 1572347 | EH14: =IFERROR((+DZ14/EG14*1000),"") -> 0.33009889 | EI14: =IFERROR(+DZ14/EO14,"") -> 0.036768915 | EJ14: =+IFERROR(+DZ14/EN14,"") -> 0.5123692 | EK14: =IFERROR(+(+DZ14/EP14*1000),"") -> 0.33009889 | EL14: 91085 | EM14: 17.26 | EN14: 1013 | EO14: 14116 | EP14: 1572347 | EQ14: =+IFERROR(+EN14/EP14,"") -> 0.00064425982 | ER14: =IFERROR(+EO14/EP14,"") -> 0.0089776621 | ES14: JOB:DCEEA5A10068_MKT:MKT0022145_MARCA:DC_PLATAFORMA:META_FECHA:25012026_CAMPAÑA:VACCOSTA2026_ETAPA:LAYER01_COMPRA:CPM_COMUNICACION:LANZAMIENTO_FORMATO:VIDEOADREEL_AUDIENCIA:BASESOCIOS | ET14: PAUSADO | EU14: PAUSADO EL 11 FEB PARA MOVER PPTO A YOUTUBE | EV14: https://www.dinersclub.com.ec/blubenefits/?utm_source=META&utm_medium=CPM&utm_campaign=DINERS-VACCOSTA-2026-MKT0022145&utm_id=DINERS-VACCOSTA-2026-MKT0022145&utm_term=DINERS-VACCOSTA-2026-MKT0022145&utm_content=META-VIDEOADREEL
H15: RMK WEB/RMK INTERACCIÓN RRSS REGION COSTA | I15: 155000 | K15: =+N15/$N$84 -> 0.022926115 | L15: =+N15 -> 700 | N15: 700 | O15: =+N15/1.15 -> 608.69565 | P15: 122.63 | R15: 700 | AB15: =+N15*60% -> 420 | AI15: =+N15*40% -> 280 | DW15: 0.05 | DX15: =O15/DW15*1000 -> 12173913 | DZ15: 303.64 | EA15: =+O15-DZ15 -> 305.05565 | EB15: =+DZ15/O15 -> 0.49883714 | EC15: 46073 | ED15: =+DZ15*1.15 -> 349.186 | EE15: CPM | EF15: =+EG15/DX15 -> 0.11220542 | EG15: =+EP15 -> 1365979 | EH15: =IFERROR((+DZ15/EG15*1000),"") -> 0.22228746 | EI15: =IFERROR(+DZ15/EO15,"") -> 0.039098635 | EJ15: =+IFERROR(+DZ15/EN15,"") -> 0.54611511 | EK15: =IFERROR(+(+DZ15/EP15*1000),"") -> 0.22228746 | EL15: 276131 | EM15: 4.95 | EN15: 556 | EO15: 7766 | EP15: 1365979 | EQ15: =+IFERROR(+EN15/EP15,"") -> 0.00040703408 | ER15: =IFERROR(+EO15/EP15,"") -> 0.0056852997 | ES15: JOB:DCEEA5A10068_MKT:MKT0022145_MARCA:DC_PLATAFORMA:META_FECHA:25012026_CAMPAÑA:VACCOSTA2026_ETAPA:LAYER01_COMPRA:CPM_COMUNICACION:LANZAMIENTO_FORMATO:VIDEOADREEL_AUDIENCIA:RMK | ET15: PAUSADO | EV15: https://www.dinersclub.com.ec/blubenefits/?utm_source=META&utm_medium=CPM&utm_campaign=DINERS-VACCOSTA-2026-MKT0022145&utm_id=DINERS-VACCOSTA-2026-MKT0022145&utm_term=DINERS-VACCOSTA-2026-MKT0022145&utm_content=META-VIDEOADREEL | EX15: NUEVO PPTO
E16: TIKTOK | F16: SPARK AD | H16: BASE SOCIOS DINERS REGION COSTA | I16: 114500 | J16: CPM | K16: =+N16/$N$84 -> 0.0098254778 | L16: =+N16 -> 300 | N16: 300 | O16: =+N16/1.05 -> 285.71429 | P16: 71.97 | R16: 900 | AB16: =+N16*60% -> 180 | AI16: =+N16*40% -> 120 | DW16: 0.89 | DX16: =O16/DW16*1000 -> 321027.29 | DZ16: 199.38 | EA16: =+O16-DZ16 -> 86.334286 | EB16: =+DZ16/O16 -> 0.69783 | EC16: 46083 | ED16: =+DZ16*1.15 -> 229.287 | EE16: CPM | EF16: =+EG16/DX16 -> 1.8454226 | EG16: =+EP16 -> 592431 | EH16: =IFERROR((+DZ16/EG16*1000),"") -> 0.33654552 | EI16: =IFERROR(+DZ16/EO16,"") -> 0.043896962 | EJ16: =+IFERROR(+DZ16/EN16,"") -> 0.16939677 | EK16: =IFERROR(+(+DZ16/EP16*1000),"") -> 0.33654552 | EL16: 92344 | EM16: 6.42 | EN16: 1177 | EO16: 4542 | EP16: 592431 | EQ16: =+IFERROR(+EN16/EP16,"") -> 0.0019867293 | ER16: =IFERROR(+EO16/EP16,"") -> 0.0076667156 | ES16: JOB:DCEEA5A10068_MKT:MKT0022145_MARCA:DC_PLATAFORMA:TIKTOK_FECHA:25012026_CAMPAÑA:VACCOSTA2026_ETAPA:LAYER01_COMPRA:CPM_COMUNICACION:LANZAMIENTO_FORMATO:SPARKAD_AUDIENCIA:BASESOCIOS | ET16: EN PAUTA | EU16: Se duplico el 24 de feb, por que se desactivaron todas las campañas de TikTok. | EV16: https://www.dinersclub.com.ec/blubenefits/?utm_source=TIKTOK&utm_medium=CPM&utm_campaign=DINERS-VACCOSTA-2026-MKT0022145&utm_id=DINERS-VACCOSTA-2026-MKT0022145&utm_term=DINERS-VACCOSTA-2026-MKT0022145&utm_content=TIKTOK-SPARKAD | EW16: 177.69 | EX16: =O16-EW16 -> 108.02429
H17: RMK WEB REGION COSTA | I17: =1640645*24.8% -> 406879.96 | K17: =+N17/$N$84 -> 0.0098254778 | L17: =+N17 -> 300 | N17: 300 | O17: =+N17/1.05 -> 285.71429 | P17: 65.73 | R17: 300 | AB17: =+N17*60% -> 180 | AI17: =+N17*40% -> 120 | DW17: 0.89 | DX17: =O17/DW17*1000 -> 321027.29 | DZ17: 208.92 | EA17: =+O17-DZ17 -> 76.794286 | EB17: =+DZ17/O17 -> 0.73122 | EC17: 46079 | ED17: =+DZ17*1.15 -> 240.258 | EE17: CPM | EF17: =+EG17/DX17 -> 2.5169574 | EG17: =+EP17 -> 808012 | EH17: =IFERROR((+DZ17/EG17*1000),"") -> 0.25856052 | EI17: =IFERROR(+DZ17/EO17,"") -> 0.046211015 | EJ17: =+IFERROR(+DZ17/EN17,"") -> 0.12631197 | EK17: =IFERROR(+(+DZ17/EP17*1000),"") -> 0.25856052 | EL17: 210164 | EM17: 3.84 | EN17: 1654 | EO17: 4521 | EP17: 808012 | EQ17: =+IFERROR(+EN17/EP17,"") -> 0.0020469993 | ER17: =IFERROR(+EO17/EP17,"") -> 0.0055952139 | ES17: JOB:DCEEA5A10068_MKT:MKT0022145_MARCA:DC_PLATAFORMA:TIKTOK_FECHA:25012026_CAMPAÑA:VACCOSTA2026_ETAPA:LAYER01_COMPRA:CPM_COMUNICACION:LANZAMIENTO_FORMATO:SPARKAD_AUDIENCIA:RMK | ET17: EN PAUTA | EV17: https://www.dinersclub.com.ec/blubenefits/?utm_source=TIKTOK&utm_medium=CPM&utm_campaign=DINERS-VACCOSTA-2026-MKT0022145&utm_id=DINERS-VACCOSTA-2026-MKT0022145&utm_term=DINERS-VACCOSTA-2026-MKT0022145&utm_content=TIKTOK-SPARKAD | EW17: 155.68 | EX17: =O17-EW17 -> 130.03429
E18: YOUTUBE | F18: INSTREAM | H18: BASE SOCIOS DINERS REGION COSTA | I18: 54000 | J18: CPM | K18: =+N18/$N$84 -> 0.01604828 | L18: =+N18 -> 490 | N18: =700*70% -> 490 | O18: =+N18/1.05 -> 466.66667 | P18: 74.75 | R18: 490 | AB18: =+N18*60% -> 294 | AI18: =+N18*40% -> 196 | DW18: 1 | DX18: =O18/DW18*1000 -> 466666.67 | DZ18: 438.47 | EA18: =+O18-DZ18 -> 28.196667 | EB18: =+DZ18/O18 -> 0.93957857 | EC18: 46079 | ED18: =+DZ18*1.15 -> 504.2405 | EE18: CPM | EF18: =+EG18/DX18 -> 0.99748714 | EG18: =+EP18 -> 465494 | EH18: =IFERROR((+DZ18/EG18*1000),"") -> 0.94194555 | EI18: =IFERROR(+DZ18/EO18,"") -> 0.003857021 | EJ18: =+IFERROR(+DZ18/EN18,"") -> 0.23335285 | EK18: =IFERROR(+(+DZ18/EP18*1000),"") -> 0.94194555 | EN18: 1879 | EO18: 113681 | EP18: 465494 | EQ18: =+IFERROR(+EN18/EP18,"") -> 0.0040365719 | ER18: =IFERROR(+EO18/EP18,"") -> 0.24421582 | ES18: JOB:DCEEA5A10068_MKT:MKT0022145_MARCA:DC_PLATAFORMA:YOUTUBE_FECHA:26012026_CAMPAÑA:VACCOSTA2026_ETAPA:LAYER01_COMPRA:CPM_COMUNICACION:LANZAMIENTO_FORMATO:INSTREAM_AUDIENCIA:BASESOCIOS | ET18: EN PAUTA | EU18: PPTO SE CAMBIO EL 11 FEB | EV18: www.dinersclub.com.ec/blubenefits/?utm_source=YOUTUBE&utm_medium=CPM&utm_campaign=DINERS-VACCOSTA-2026-MKT0022145&utm_id=DINERS-VACCOSTA-2026-MKT0022145&utm_term=DINERS-VACCOSTA-2026-MKT0022145&utm_content=YOUTUBE-INSTREAM
H19: RMK WEB REGION COSTA | I19: - | K19: =+N19/$N$84 -> 0.0068778345 | L19: =+N19 -> 210 | N19: =300*70% -> 210 | O19: =+N19/1.05 -> 200 | P19: 31.97 | R19: 210 | AB19: =+N19*60% -> 126 | AI19: =+N19*40% -> 84 | DW19: 1 | DX19: =O19/DW19*1000 -> 200000 | DZ19: 188.51 | EA19: =+O19-DZ19 -> 11.49 | EB19: =+DZ19/O19 -> 0.94255 | EC19: 46079 | ED19: =+DZ19*1.15 -> 216.7865 | EE19: CPM | EF19: =+EG19/DX19 -> 1.62426 | EG19: =+EP19 -> 324852 | EH19: =IFERROR((+DZ19/EG19*1000),"") -> 0.58029503 | EI19: =IFERROR(+DZ19/EO19,"") -> 0.002215419 | EJ19: =+IFERROR(+DZ19/EN19,"") -> 0.094633534 | EK19: =IFERROR(+(+DZ19/EP19*1000),"") -> 0.58029503 | EN19: 1992 | EO19: 85090 | EP19: 324852 | EQ19: =+IFERROR(+EN19/EP19,"") -> 0.0061320232 | ER19: =IFERROR(+EO19/EP19,"") -> 0.26193467 | ES19: JOB:DCEEA5A10068_MKT:MKT0022145_MARCA:DC_PLATAFORMA:YOUTUBE_FECHA:26012026_CAMPAÑA:VACCOSTA2026_ETAPA:LAYER01_COMPRA:CPM_COMUNICACION:LANZAMIENTO_FORMATO:INSTREAM_AUDIENCIA:RMK | ET19: EN PAUTA | EV19: www.dinersclub.com.ec/blubenefits/?utm_source=YOUTUBE&utm_medium=CPM&utm_campaign=DINERS-VACCOSTA-2026-MKT0022145&utm_id=DINERS-VACCOSTA-2026-MKT0022145&utm_term=DINERS-VACCOSTA-2026-MKT0022145&utm_content=YOUTUBE-INSTREAM
F20: SHORTS | H20: BASE SOCIOS DINERS REGION COSTA | I20: 54000 | J20: CPM | K20: =+N20/$N$84 -> 0.0068778345 | L20: =+N20 -> 210 | N20: =700*30% -> 210 | O20: =+N20/1.05 -> 200 | P20: 30.19 | R20: 210 | AB20: =+N20*60% -> 126 | AI20: =+N20*40% -> 84 | DW20: 1 | DX20: =O20/DW20*1000 -> 200000 | DZ20: 188.01 | EA20: =+O20-DZ20 -> 11.99 | EB20: =+DZ20/O20 -> 0.94005 | EC20: 46079 | ED20: =+DZ20*1.15 -> 216.2115 | EE20: CPM | EF20: =+EG20/DX20 -> 1.052645 | EG20: =+EP20 -> 210529 | EH20: =IFERROR((+DZ20/EG20*1000),"") -> 0.89303611 | EI20: =IFERROR(+DZ20/EO20,"") -> 0.038004851 | EJ20: =+IFERROR(+DZ20/EN20,"") -> 1.0930814 | EK20: =IFERROR(+(+DZ20/EP20*1000),"") -> 0.89303611 | EN20: 172 | EO20: 4947 | EP20: 210529 | EQ20: =+IFERROR(+EN20/EP20,"") -> 0.00081698958 | ER20: =IFERROR(+EO20/EP20,"") -> 0.02349795 | ES20: JOB:DCEEA5A10068_MKT:MKT0022145_MARCA:DC_PLATAFORMA:YOUTUBE_FECHA:26012026_CAMPAÑA:VACCOSTA2026_ETAPA:LAYER01_COMPRA:CPM_COMUNICACION:LANZAMIENTO_FORMATO:SHORTS_AUDIENCIA:BASESOCIOS | ET20: EN PAUTA | EV20: https://www.dinersclub.com.ec/blubenefits/?utm_source=YOUTUBE&utm_medium=CPM&utm_campaign=DINERS-VACCOSTA-2026-MKT0022145&utm_id=DINERS-VACCOSTA-2026-MKT0022145&utm_term=DINERS-VACCOSTA-2026-MKT0022145&utm_content=YOUTUBE-SHORTS
H21: RMK WEB REGION COSTA | I21: - | K21: =+N21/$N$84 -> 0.0029476433 | L21: =+N21 -> 90 | N21: =300*30% -> 90 | O21: =+N21/1.05 -> 85.714286 | P21: 13.57 | R21: 90 | AB21: =+N21*60% -> 54 | AI21: =+N21*40% -> 36 | DW21: 1 | DX21: =O21/DW21*1000 -> 85714.286 | DZ21: 80.04 | EA21: =+O21-DZ21 -> 5.6742857 | EB21: =+DZ21/O21 -> 0.9338 | EC21: 46079 | ED21: =+DZ21*1.15 -> 92.046 | EE21: CPM | EF21: =+EG21/DX21 -> 2.0728633 | EG21: =+EP21 -> 177674 | EH21: =IFERROR((+DZ21/EG21*1000),"") -> 0.45048797 | EI21: =IFERROR(+DZ21/EO21,"") -> 0.014918919 | EJ21: =+IFERROR(+DZ21/EN21,"") -> 0.23267442 | EK21: =IFERROR(+(+DZ21/EP21*1000),"") -> 0.45048797 | EN21: 344 | EO21: 5365 | EP21: 177674 | EQ21: =+IFERROR(+EN21/EP21,"") -> 0.0019361302 | ER21: =IFERROR(+EO21/EP21,"") -> 0.030195752 | ES21: JOB:DCEEA5A10068_MKT:MKT0022145_MARCA:DC_PLATAFORMA:YOUTUBE_FECHA:26012026_CAMPAÑA:VACCOSTA2026_ETAPA:LAYER01_COMPRA:CPM_COMUNICACION:LANZAMIENTO_FORMATO:SHORTS_AUDIENCIA:RMK | ET21: EN PAUTA | EV21: https://www.dinersclub.com.ec/blubenefits/?utm_source=YOUTUBE&utm_medium=CPM&utm_campaign=DINERS-VACCOSTA-2026-MKT0022145&utm_id=DINERS-VACCOSTA-2026-MKT0022145&utm_term=DINERS-VACCOSTA-2026-MKT0022145&utm_content=YOUTUBE-SHORTS
E22: DV360 | F22: INSTREAM CONTEXTUAL NATIVE ADS | H22: INTERESES; VIAJES, AGENCIA DE VIAJES, EXPERIENCIAS, COMPRAS EN EL EXTERIOR, TURISMO, HOTELES APP TARGETING AIRBNB/BOOKING/KAYAC/TRIP ADVISOR/DESPEGAR/LATAM AIRLINES/WAZE/TRIPPY/ECUADOR TRAVEL | I22: - | J22: CPM | K22: =+N22/$N$84 -> 0.13100637 | L22: =+N22 -> 4000 | N22: 4000 | O22: =+N22/1.05 -> 3809.5238 | P22: 800.37 | R22: 4000 | AB22: =+N22*60% -> 2400 | AI22: =+N22*40% -> 1600 | DW22: 1 | DX22: =O22/DW22*1000 -> 3809523.8 | DZ22: 208.68 | EA22: =+O22-DZ22 -> 3600.8438 | EB22: =+DZ22/O22 -> 0.0547785 | EC22: 46072 | ED22: =+DZ22*1.15 -> 239.982 | EE22: CPM | EF22: =+EG22/DX22 -> 1.0399848 | EG22: =+EP22 -> 3961847 | EH22: =IFERROR((+DZ22/EG22*1000),"") -> 0.052672403 | EI22: =IFERROR(+DZ22/EO22,"") | EJ22: =+IFERROR(+DZ22/EN22,"") | EK22: =IFERROR(+(+DZ22/EP22*1000),"") -> 0.052672403 | EP22: 3961847 | EQ22: =+IFERROR(+EN22/EP22,"") -> 0 | ER22: =IFERROR(+EO22/EP22,"") -> 0 | ES22: JOB:DCEEA5A10068_MKT:MKT0022145_MARCA:DC_PLATAFORMA:DV360_FECHA:27012026_CAMPAÑA:VACCOSTA2026_ETAPA:LAYER01_COMPRA:CPM_COMUNICACION:LANZAMIENTO_FORMATO:INSTREAM_AUDIENCIA:INTERESESVIAJES | ET22: FINALIZADO | EU22: SE PAUSÓ EL 20 DE FEB | EV22: https://www.dinersclub.com.ec/blubenefits/?utm_source=DV360&utm_medium=CPM&utm_campaign=DINERS-VACCOSTA-2026-MKT0022145&utm_id=DINERS-VACCOSTA-2026-MKT0022145&utm_term=DINERS-VACCOSTA-2026-MKT0022145&utm_content=DV360
C23: LAYER 01 | L23: =SUM(L14:L22) -> 7500 | M23: =SUM(M14:M22) -> 0 | N23: =SUM(N14:N22) -> 7500 | O23: =SUM(O14:O22) -> 6985.5072 | R23: =SUM(R14:R22) -> 8100
C24: LAYER 02 CONSIDERACIÓN IDENTIFICACIÓN | D24: AEROLINEAS | E24: META | F24: REEL/VIDEO AD | G24: ESPECIALIDADES AEROLINEAS Snackables convisualizaciones de experiencias unicas en vuelos y beneficios ser socio. | H24: BASE SOCIOS DINERS (EXC RMK VISUALIZACIÓN AEROLINEAS) REGION COSTA | I24: 266000 | J24: CPV TRUVIEW 2 SEG | K24: =+N24/$N$84 -> 0.027699111 | L24: =+N24 -> 845.73324 | N24: =745.73324+100 -> 845.73324 | O24: =+N24/1.15 -> 735.42021 | P24: 89.85 | R24: 745.73324 | S24: =R24/1.15 -> 648.46369 | AD24: =+O24*20% -> 147.08404 | AI24: =+O24*50% -> 367.7101 | BK24: =+O24*30% -> 220.62606 | DW24: 0.09 | DX24: =O24/DW24 -> 8171.3357 | DZ24: 609.61 | EA24: =+O24-DZ24 -> 125.81021 | EB24: =+DZ24/O24 -> 0.82892745 | EC24: 46079 | ED24: =+DZ24*1.15 -> 701.0515 | EE24: CPV | EF24: =+EG24/DX24 -> 0.95259824 | EG24: =+EO24 -> 7784 | EH24: =IFERROR((+DZ24/EG24*1000),"") -> 78.315776 | EI24: =IFERROR(+DZ24/EO24,"") -> 0.078315776 | EJ24: =+IFERROR(+DZ24/EN24,"") -> 2.3812891 | EK24: =IFERROR(+(+DZ24/EP24*1000),"") -> 0.97893777 | EL24: 87429 | EM24: 7.12 | EN24: 256 | EO24: 7784 | EP24: 622726 | EQ24: =+IFERROR(+EN24/EP24,"") -> 0.00041109573 | ER24: =IFERROR(+EO24/EP24,"") -> 0.01249988 | ES24: JOB:DCEEA5A10068_MKT:MKT0022145_MARCA:DC_PLATAFORMA:META_FECHA:27012026_CAMPAÑA:VACCOSTA2026_ETAPA:LAYER02_COMPRA:CPV_COMUNICACION:AEROLINEAS_FORMATO:VIDEOADREEL_AUDIENCIA:BASESOCIOS | ET24: EN PAUTA | EU24: se aumento el creativo de tiktok el 11 de feb | EV24: https://www.dinersclub.com.ec/blubenefits/?utm_source=META&utm_medium=CPV&utm_campaign=DINERS-VACCOSTA-2026-MKT0022145&utm_id=DINERS-VACCOSTA-2026-MKT0022145&utm_term=DINERS-VACCOSTA-2026-MKT0022145&utm_content=META-VIDEOADREEL | EW24: *el 27 de feb se cambiaron todos los pptos y se exc base de views de toda la LAYER 02
H25: RMK WEB/RMK INTERACCIÓN RRSS (EXC RMK VISUALIZACIÓN AEROLINEAS) REGION COSTA | I25: 155000 | K25: =+N25/$N$84 -> 0.026810449 | L25: =+N25 -> 818.59986 | N25: =1118.59986-400+100 -> 818.59986 | O25: =+N25/1.15 -> 711.82597 | P25: 87.66 | R25: 718.59986 | S25: =R25/1.15 -> 624.86944 | AD25: =+O25*20% -> 142.36519 | AI25: =+O25*50% -> 355.91298 | BK25: =+O25*30% -> 213.54779 | DW25: 0.09 | DX25: =O25/DW25 -> 7909.1774 | DZ25: 586.15 | EA25: =+O25-DZ25 -> 125.67597 | EB25: =+DZ25/O25 -> 0.82344566 | EC25: 46079 | ED25: =+DZ25*1.15 -> 674.0725 | EE25: CPV | EF25: =+EG25/DX25 -> 2.5366734 | EG25: =+EO25 -> 20063 | EH25: =IFERROR((+DZ25/EG25*1000),"") -> 29.215471 | EI25: =IFERROR(+DZ25/EO25,"") -> 0.029215471 | EJ25: =+IFERROR(+DZ25/EN25,"") -> 1.5630667 | EK25: =IFERROR(+(+DZ25/EP25*1000),"") -> 0.52520048 | EL25: 184390 | EM25: 6.05 | EN25: 375 | EO25: 20063 | EP25: 1116050 | EQ25: =+IFERROR(+EN25/EP25,"") -> 0.00033600645 | ER25: =IFERROR(+EO25/EP25,"") -> 0.017976793 | ES25: JOB:DCEEA5A10068_MKT:MKT0022145_MARCA:DC_PLATAFORMA:META_FECHA:27012026_CAMPAÑA:VACCOSTA2026_ETAPA:LAYER02_COMPRA:CPV_COMUNICACION:AEROLINEAS_FORMATO:VIDEOADREEL_AUDIENCIA:RMK | ET25: EN PAUTA | EV25: https://www.dinersclub.com.ec/blubenefits/?utm_source=META&utm_medium=CPV&utm_campaign=DINERS-VACCOSTA-2026-MKT0022145&utm_id=DINERS-VACCOSTA-2026-MKT0022145&utm_term=DINERS-VACCOSTA-2026-MKT0022145&utm_content=META-VIDEOADREEL
E26: META | F26: DINAMICOS | G26: ESPECIALIDADES AEROLINEAS Snackables convisualizaciones de experiencias unicas en vuelos y beneficios ser socio. | H26: BASE SOCIOS DINERS (EXC RMK VISUALIZACIÓN AEROLINEAS) REGION COSTA | I26: 266000 | J26: CPC | K26: =+N26/$N$84 -> 0.016319899 | L26: =+N26 -> 498.2933 | N26: =398.293296+100 -> 498.2933 | O26: =+N26/1.15 -> 433.29852 | P26: 47.02 | R26: 398.2933 | S26: =R26/1.15 -> 346.342 | AD26: =+O26*20% -> 86.659704 | AI26: =+O26*50% -> 216.64926 | BK26: =+O26*30% -> 129.98956 | DW26: 0.09 | DX26: =O26/DW26 -> 4814.428 | DZ26: 291.04 | EA26: =+O26-DZ26 -> 142.25852 | EB26: =+DZ26/O26 -> 0.67168473 | EC26: 46079 | ED26: =+DZ26*1.15 -> 334.696 | EE26: CPC | EF26: =+EG26/DX26 -> 0.49247803 | EG26: =+EN26 -> 2371 | EH26: =IFERROR((+DZ26/EG26*1000),"") -> 122.74989 | EI26: =IFERROR(+DZ26/EO26,"") | EJ26: =+IFERROR(+DZ26/EN26,"") -> 0.12274989 | EK26: =IFERROR(+(+DZ26/EP26*1000),"") -> 1.2694646 | EL26: 46518 | EM26: 4.93 | EN26: 2371 | EO26: - | EP26: 229262 | EQ26: =+IFERROR(+EN26/EP26,"") -> 0.01034188 | ER26: =IFERROR(+EO26/EP26,"") | ES26: JOB:DCEEA5A10068_MKT:MKT0022145_MARCA:DC_PLATAFORMA:META_FECHA:27012026_CAMPAÑA:VACCOSTA2026_ETAPA:LAYER02_COMPRA:CPC_COMUNICACION:AEROLINEAS_FORMATO:DINAMICOS_AUDIENCIA:BASESOCIOS | ET26: EN PAUTA | EU26: se rechazaron los anuncios, se volvió a activar el 23 de feb | EV26: https://www.dinersclub.com.ec/blubenefits/?utm_source=META&utm_medium=CPC&utm_campaign=DINERS-VACCOSTA-2026-MKT0022145&utm_id=DINERS-VACCOSTA-2026-MKT0022145&utm_term=DINERS-VACCOSTA-2026-MKT0022145&utm_content=META-DINAMICOS
H27: RMK WEB/RMK INTERACCIÓN RRSS (EXC RMK VISUALIZACIÓN AEROLINEAS) REGION COSTA | I27: 155000 | K27: =+N27/$N$84 -> 0.011379212 | L27: =+N27 -> 347.43994 | N27: =247.439944+100 -> 347.43994 | O27: =+N27/1.15 -> 302.12169 | P27: 29.93 | R27: 247.43994 | S27: =R27/1.15 -> 215.16517 | AD27: =+O27*20% -> 60.424338 | AI27: =+O27*50% -> 151.06085 | BK27: =+O27*30% -> 90.636507 | DW27: 0.09 | DX27: =O27/DW27 -> 3356.9077 | DZ27: 180.68 | EA27: =+O27-DZ27 -> 121.44169 | EB27: =+DZ27/O27 -> 0.59803717 | EC27: 46079 | ED27: =+DZ27*1.15 -> 207.782 | EE27: CPC | EF27: =+EG27/DX27 -> 1.0354768 | EG27: =+EN27 -> 3476 | EH27: =IFERROR((+DZ27/EG27*1000),"") -> 51.979287 | EI27: =IFERROR(+DZ27/EO27,"") | EJ27: =+IFERROR(+DZ27/EN27,"") -> 0.051979287 | EK27: =IFERROR(+(+DZ27/EP27*1000),"") -> 0.85862282 | EL27: 76848 | EM27: 2.74 | EN27: 3476 | EO27: - | EP27: 210430 | EQ27: =+IFERROR(+EN27/EP27,"") -> 0.016518557 | ER27: =IFERROR(+EO27/EP27,"") | ES27: JOB:DCEEA5A10068_MKT:MKT0022145_MARCA:DC_PLATAFORMA:META_FECHA:27012026_CAMPAÑA:VACCOSTA2026_ETAPA:LAYER02_COMPRA:CPC_COMUNICACION:AEROLINEAS_FORMATO:DINAMICO_AUDIENCIA:RMK | ET27: EN PAUTA | EV27: https://www.dinersclub.com.ec/blubenefits/?utm_source=META&utm_medium=CPC&utm_campaign=DINERS-VACCOSTA-2026-MKT0022145&utm_id=DINERS-VACCOSTA-2026-MKT0022145&utm_term=DINERS-VACCOSTA-2026-MKT0022145&utm_content=META-DINAMICOS | EX27: NUEVO PPTO
E28: TIKTOK | F28: INFEED | G28: ESPECIALIDADES AEROLINEAS Snackables convisualizaciones de experiencias unicas en vuelos y beneficios ser socio. | H28: BASE SOCIOS DINERS (EXC RMK VISUALIZACIÓN AEROLINEAS) REGION COSTA | I28: 109000 | J28: CPV | K28: =+N28/$N$84 -> 0.014682319 | L28: =+N28 -> 448.2933 | N28: =298.293296+100+50 -> 448.2933 | O28: =+N28/1.05 -> 426.946 | P28: 45.07 | R28: 298.2933 | S28: =R28/1.05 -> 284.08885 | AD28: =+O28*20% -> 85.389199 | AI28: =+O28*50% -> 213.473 | BK28: =+O28*30% -> 128.0838 | DW28: 0.1 | DX28: =O28/DW28 -> 4269.46 | DZ28: 234.2 | EA28: =+O28-DZ28 -> 192.746 | EB28: =+DZ28/O28 -> 0.54854713 | EC28: 46079 | ED28: =+DZ28*1.15 -> 269.33 | EE28: CPV | EF28: =+EG28/DX28 -> 2.3953849 | EG28: =+EO28 -> 10227 | EH28: =IFERROR((+DZ28/EG28*1000),"") -> 22.900166 | EI28: =IFERROR(+DZ28/EO28,"") -> 0.022900166 | EJ28: =+IFERROR(+DZ28/EN28,"") -> 0.2964557 | EK28: =IFERROR(+(+DZ28/EP28*1000),"") -> 0.89919909 | EL28: 66986 | EM28: 3.89 | EN28: 790 | EO28: 10227 | EP28: 260454 | EQ28: =+IFERROR(+EN28/EP28,"") -> 0.0030331652 | ER28: =IFERROR(+EO28/EP28,"") -> 0.039266051 | ES28: JOB:DCEEA5A10068_MKT:MKT0022145_MARCA:DC_PLATAFORMA:TIKTOK_FECHA:27012026_CAMPAÑA:VACCOSTA2026_ETAPA:LAYER02_COMPRA:CPV_COMUNICACION:AEROLINEAS_FORMATO:INFEED_AUDIENCIA:BASESOCIOS | ET28: EN PAUTA | EU28: Se duplico el 24 de feb, por que se desactivaron todas las campañas de TikTok. | EV28: https://www.dinersclub.com.ec/blubenefits/?utm_source=TIKTOK&utm_medium=CPV&utm_campaign=DINERS-VACCOSTA-2026-MKT0022145&utm_id=DINERS-VACCOSTA-2026-MKT0022145&utm_term=DINERS-VACCOSTA-2026-MKT0022145&utm_content=TIKTOK-INFEED | EW28: 150.89 | EX28: =O28-EW28 -> 276.056
H29: RMK WEB/RMK INTERACCIÓN RRSS (EXC RMK VISUALIZACIÓN AEROLINEAS) REGION COSTA | I29: 155000 | K29: =+N29/$N$84 -> 0.01629195 | L29: =+N29 -> 497.43994 | N29: =347.439944+100+50 -> 497.43994 | O29: =+N29/1.05 -> 473.75233 | P29: 53.32 | R29: 347.43994 | S29: =R29/1.05 -> 330.89518 | AD29: =+O29*20% -> 94.750466 | AI29: =+O29*50% -> 236.87616 | BK29: =+O29*30% -> 142.1257 | DW29: 0.1 | DX29: =O29/DW29 -> 4737.5233 | DZ29: 265.07 | EA29: =+O29-DZ29 -> 208.68233 | EB29: =+DZ29/O29 -> 0.55951176 | EC29: 46079 | ED29: =+DZ29*1.15 -> 304.8305 | EE29: CPV | EF29: =+EG29/DX29 -> 4.3134353 | EG29: =+EO29 -> 20435 | EH29: =IFERROR((+DZ29/EG29*1000),"") -> 12.971373 | EI29: =IFERROR(+DZ29/EO29,"") -> 0.012971373 | EJ29: =+IFERROR(+DZ29/EN29,"") -> 0.14758909 | EK29: =IFERROR(+(+DZ29/EP29*1000),"") -> 0.69392414 | EL29: 127921 | EM29: 2.99 | EN29: 1796 | EO29: 20435 | EP29: 381987 | EQ29: =+IFERROR(+EN29/EP29,"") -> 0.0047017307 | ER29: =IFERROR(+EO29/EP29,"") -> 0.053496585 | ES29: JOB:DCEEA5A10068_MKT:MKT0022145_MARCA:DC_PLATAFORMA:TIKTOK_FECHA:27012026_CAMPAÑA:VACCOSTA2026_ETAPA:LAYER02_COMPRA:CPV_COMUNICACION:AEROLINEAS_FORMATO:INFEED_AUDIENCIA:RMK | ET29: EN PAUTA | EV29: https://www.dinersclub.com.ec/blubenefits/?utm_source=TIKTOK&utm_medium=CPV&utm_campaign=DINERS-VACCOSTA-2026-MKT0022145&utm_id=DINERS-VACCOSTA-2026-MKT0022145&utm_term=DINERS-VACCOSTA-2026-MKT0022145&utm_content=TIKTOK-INFEED | EW29: 172.09 | EX29: =O29-EW29 -> 301.66233
E30: YOUTUBE | F30: INSTREAM | G30: ESPECIALIDADES AEROLINEAS Snackables convisualizaciones de experiencias unicas en vuelos y beneficios ser socio. | H30: BASE SOCIOS DINERS (EXC RMK VISUALIZACIÓN AEROLINEAS) REGION COSTA | I30: 54000 | J30: CPV | K30: =+N30/$N$84 -> 0.0035765898 | L30: =+N30 -> 109.20354 | N30: =(198.862197333209*70%)-30 -> 109.20354 | O30: =+N30/1.05 -> 104.00337 | R30: 139.20354 | S30: =R30/1.05 -> 132.5748 | AD30: =+O30*20% -> 20.800674 | AI30: =+O30*50% -> 52.001685 | BK30: =+O30*30% -> 31.201011 | DW30: 1 | DX30: =O30/DW30 -> 104.00337 | EA30: =+O30-DZ30 -> 104.00337 | EB30: =+DZ30/O30 -> 0 | ED30: =+DZ30*1.15 -> 0 | EE30: CPV | EF30: =+EG30/DX30 -> 0 | EG30: =+EP30 -> 0 | EH30: =IFERROR((+DZ30/EG30*1000),"") | EI30: =IFERROR(+DZ30/EO30,"") | EJ30: =+IFERROR(+DZ30/EN30,"") | EK30: =IFERROR(+(+DZ30/EP30*1000),"") | EQ30: =+IFERROR(+EN30/EP30,"") | ER30: =IFERROR(+EO30/EP30,"") | ES30: JOB:DCEEA5A10068_MKT:MKT0022145_MARCA:DC_PLATAFORMA:YOUTUBE_FECHA:27022026_CAMPAÑA:VACCOSTA2026_ETAPA:LAYER02_COMPRA:CPV_COMUNICACION:AEROLINEAS_FORMATO:INSTREAM_AUDIENCIA:BASESOCIOS | ET30: EN PAUTA | EV30: www.dinersclub.com.ec/blubenefits/?utm_source=YOUTUBE&utm_medium=CPV&utm_campaign=DINERS-VACCOSTA-2026-MKT0022145&utm_id=DINERS-VACCOSTA-2026-MKT0022145&utm_term=DINERS-VACCOSTA-2026-MKT0022145&utm_content=YOUTUBE-INSTREAM
H31: RMK WEB/RMK INTERACCIÓN RRSS (EXC RMK VISUALIZACIÓN AEROLINEAS) REGION COSTA | I31: - | K31: =+N31/$N$84 -> 0.0035635471 | L31: =+N31 -> 108.80531 | N31: =(298.293295999814*70%)-100 -> 108.80531 | O31: =+N31/1.05 -> 103.6241 | R31: 208.80531 | S31: =R31/1.05 -> 198.8622 | AD31: =+O31*20% -> 20.72482 | AI31: =+O31*50% -> 51.812051 | BK31: =+O31*30% -> 31.087231 | DW31: 1 | DX31: =O31/DW31 -> 103.6241 | EA31: =+O31-DZ31 -> 103.6241 | EB31: =+DZ31/O31 -> 0 | ED31: =+DZ31*1.15 -> 0 | EE31: CPV | EF31: =+EG31/DX31 -> 0 | EG31: =+EP31 -> 0 | EH31: =IFERROR((+DZ31/EG31*1000),"") | EI31: =IFERROR(+DZ31/EO31,"") | EJ31: =+IFERROR(+DZ31/EN31,"") | EK31: =IFERROR(+(+DZ31/EP31*1000),"") | EQ31: =+IFERROR(+EN31/EP31,"") | ER31: =IFERROR(+EO31/EP31,"") | ES31: JOB:DCEEA5A10068_MKT:MKT0022145_MARCA:DC_PLATAFORMA:YOUTUBE_FECHA:27022026_CAMPAÑA:VACCOSTA2026_ETAPA:LAYER02_COMPRA:CPV_COMUNICACION:AEROLINEAS_FORMATO:INSTREAM_AUDIENCIA:RMK | ET31: EN PAUTA | EV31: www.dinersclub.com.ec/blubenefits/?utm_source=YOUTUBE&utm_medium=CPV&utm_campaign=DINERS-VACCOSTA-2026-MKT0022145&utm_id=DINERS-VACCOSTA-2026-MKT0022145&utm_term=DINERS-VACCOSTA-2026-MKT0022145&utm_content=YOUTUBE-INSTREAM
D32: HOTELES | E32: META | F32: REEL/VIDEO AD | G32: ESPECIALIDADES HOTELES Snackables con EXPERIENCIAS de amenities y beneficios | H32: BASE SOCIOS DINERS (EXC RMK VISUALIZACIÓN HOTELES) REGION COSTA | I32: 266000 | J32: CPV TRUVIEW 2 SEG | K32: =+N32/$N$84 -> 0.027699111 | L32: =+N32 -> 845.73324 | N32: =745.73324+100 -> 845.73324 | O32: =+N32/1.15 -> 735.42021 | P32: 88.02 | R32: 745.73324 | S32: =R32/1.15 -> 648.46369 | AD32: =+O32*20% -> 147.08404 | AI32: =+O32*50% -> 367.7101 | BK32: =+O32*30% -> 220.62606 | DW32: 0.09 | DX32: =O32/DW32 -> 8171.3357 | DZ32: 609.8 | EA32: =+O32-DZ32 -> 125.62021 | EB32: =+DZ32/O32 -> 0.82918581 | EC32: 46079 | ED32: =+DZ32*1.15 -> 701.27 | EE32: CPV | EF32: =+EG32/DX32 -> 0.85077891 | EG32: =+EO32 -> 6952 | EH32: =IFERROR((+DZ32/EG32*1000),"") -> 87.715765 | EI32: =IFERROR(+DZ32/EO32,"") -> 0.087715765 | EJ32: =+IFERROR(+DZ32/EN32,"") -> 2.3453846 | EK32: =IFERROR(+(+DZ32/EP32*1000),"") -> 0.99853936 | EL32: 99605 | EM32: 5.49 | EN32: 260 | EO32: 6952 | EP32: 610692 | EQ32: =+IFERROR(+EN32/EP32,"") -> 0.00042574653 | ER32: =IFERROR(+EO32/EP32,"") -> 0.011383807 | ES32: JOB:DCEEA5A10068_MKT:MKT0022145_MARCA:DC_PLATAFORMA:META_FECHA:27012026_CAMPAÑA:VACCOSTA2026_ETAPA:LAYER02_COMPRA:CPV_COMUNICACION:HOTELES_FORMATO:VIDEOADREEL_AUDIENCIA:BASESOCIOS | ET32: EN PAUTA | EU32: se aumento el creativo de tiktok el 11 de feb | EV32: https://www.dinersclub.com.ec/blubenefits/?utm_source=META&utm_medium=CPV&utm_campaign=DINERS-VACCOSTA-2026-MKT0022145&utm_id=DINERS-VACCOSTA-2026-MKT0022145&utm_term=DINERS-VACCOSTA-2026-MKT0022145&utm_content=META-VIDEOADREEL
H33: RMK WEB/RMK INTERACCIÓN RRSS (EXC RMK VISUALIZACIÓN HOTELES) REGION COSTA | I33: 155000 | K33: =+N33/$N$84 -> 0.026810449 | L33: =+N33 -> 818.59986 | N33: =1118.59986-400+100 -> 818.59986 | O33: =+N33/1.15 -> 711.82597 | P33: 88.7 | R33: 718.59986 | S33: =R33/1.15 -> 624.86944 | AD33: =+O33*20% -> 142.36519 | AI33: =+O33*50% -> 355.91298 | BK33: =+O33*30% -> 213.54779 | DW33: 0.09 | DX33: =O33/DW33 -> 7909.1774 | DZ33: 586.61 | EA33: =+O33-DZ33 -> 125.21597 | EB33: =+DZ33/O33 -> 0.82409188 | EC33: 46079 | ED33: =+DZ33*1.15 -> 674.6015 | EE33: CPV | EF33: =+EG33/DX33 -> 2.5612019 | EG33: =+EO33 -> 20257 | EH33: =IFERROR((+DZ33/EG33*1000),"") -> 28.958385 | EI33: =IFERROR(+DZ33/EO33,"") -> 0.028958385 | EJ33: =+IFERROR(+DZ33/EN33,"") -> 1.3705841 | EK33: =IFERROR(+(+DZ33/EP33*1000),"") -> 0.46927937 | EL33: 233673 | EM33: 4.87 | EN33: 428 | EO33: 20257 | EP33: 1250023 | EQ33: =+IFERROR(+EN33/EP33,"") -> 0.0003423937 | ER33: =IFERROR(+EO33/EP33,"") -> 0.016205302 | ES33: JOB:DCEEA5A10068_MKT:MKT0022145_MARCA:DC_PLATAFORMA:META_FECHA:27012026_CAMPAÑA:VACCOSTA2026_ETAPA:LAYER02_COMPRA:CPV_COMUNICACION:HOTELES_FORMATO:VIDEOADREEL_AUDIENCIA:RMK | ET33: EN PAUTA | EU33: se aumento el creativo de tiktok el 11 de feb | EV33: https://www.dinersclub.com.ec/blubenefits/?utm_source=META&utm_medium=CPV&utm_campaign=DINERS-VACCOSTA-2026-MKT0022145&utm_id=DINERS-VACCOSTA-2026-MKT0022145&utm_term=DINERS-VACCOSTA-2026-MKT0022145&utm_content=META-VIDEOADREEL
E34: META | F34: DINAMICOS | G34: ESPECIALIDADES HOTELES Snackables con EXPERIENCIAS de amenities y beneficios | H34: BASE SOCIOS DINERS (EXC RMK VISUALIZACIÓN HOTELES) REGION COSTA | I34: 266000 | J34: CPC | K34: =+N34/$N$84 -> 0.0035915396 | L34: 120.2 | M34: =+N34-L34 -> -10.54 | N34: =59.66+50 -> 109.66 | O34: =+N34/1.15 -> 95.356522 | R34: 59.66 | S34: =R34/1.15 -> 51.878261 | AD34: =+O34*20% -> 19.071304 | AI34: =+O34*50% -> 47.678261 | BK34: =+O34*30% -> 28.606957 | DW34: 0.09 | DX34: =O34/DW34 -> 1059.5169 | EA34: =+O34-DZ34 -> 95.356522 | EB34: =+DZ34/O34 -> 0 | ED34: =+DZ34*1.15 -> 0 | EE34: CPC | EF34: =+EG34/DX34 -> 0 | EG34: =+EN34 -> 0 | EH34: =IFERROR((+DZ34/EG34*1000),"") | EI34: =IFERROR(+DZ34/EO34,"") | EJ34: =+IFERROR(+DZ34/EN34,"") | EK34: =IFERROR(+(+DZ34/EP34*1000),"") | EQ34: =+IFERROR(+EN34/EP34,"") | ER34: =IFERROR(+EO34/EP34,"") | ES34: JOB:DCEEA5A10068_MKT:MKT0022145_MARCA:DC_PLATAFORMA:META_FECHA:27022026_CAMPAÑA:VACCOSTA2026_ETAPA:LAYER02_COMPRA:CPC_COMUNICACION:HOTELES_FORMATO:DINAMICOS_AUDIENCIA:BASESOCIOS | ET34: EN PAUTA | EV34: https://www.dinersclub.com.ec/blubenefits/?utm_source=META&utm_medium=CPC&utm_campaign=DINERS-VACCOSTA-2026-MKT0022145&utm_id=DINERS-VACCOSTA-2026-MKT0022145&utm_term=DINERS-VACCOSTA-2026-MKT0022145&utm_content=META-DINAMICOS
H35: RMK WEB/RMK INTERACCIÓN RRSS (EXC RMK VISUALIZACIÓN HOTELES) REGION COSTA | I35: 155000 | K35: =+N35/$N$84 -> 0.0045685197 | M35: =+N35 -> 139.49 | N35: =89.49+50 -> 139.49 | O35: =+N35/1.15 -> 121.29565 | R35: 89.49 | S35: =R35/1.15 -> 77.817391 | AD35: =+O35*20% -> 24.25913 | AI35: =+O35*50% -> 60.647826 | BK35: =+O35*30% -> 36.388696 | DW35: 0.09 | DX35: =O35/DW35 -> 1347.7295 | EA35: =+O35-DZ35 -> 121.29565 | EB35: =+DZ35/O35 -> 0 | ED35: =+DZ35*1.15 -> 0 | EE35: CPC | EF35: =+EG35/DX35 -> 0 | EG35: =+EN35 -> 0 | EH35: =IFERROR((+DZ35/EG35*1000),"") | EI35: =IFERROR(+DZ35/EO35,"") | EJ35: =+IFERROR(+DZ35/EN35,"") | EK35: =IFERROR(+(+DZ35/EP35*1000),"") | EQ35: =+IFERROR(+EN35/EP35,"") | ER35: =IFERROR(+EO35/EP35,"") | ES35: JOB:DCEEA5A10068_MKT:MKT0022145_MARCA:DC_PLATAFORMA:META_FECHA:27022026_CAMPAÑA:VACCOSTA2026_ETAPA:LAYER02_COMPRA:CPC_COMUNICACION:HOTELES_FORMATO:DINAMICOS_AUDIENCIA:RMK | ET35: EN PAUTA | EV35: https://www.dinersclub.com.ec/blubenefits/?utm_source=META&utm_medium=CPC&utm_campaign=DINERS-VACCOSTA-2026-MKT0022145&utm_id=DINERS-VACCOSTA-2026-MKT0022145&utm_term=DINERS-VACCOSTA-2026-MKT0022145&utm_content=META-DINAMICOS | EX35: NUEVO PPTO
E36: TIKTOK | F36: INFEED | G36: ESPECIALIDADES HOTELES Snackables con EXPERIENCIAS de amenities y beneficios | H36: BASE SOCIOS DINERS (EXC RMK VISUALIZACIÓN HOTELES) REGION COSTA | I36: 109000 | J36: CPV | K36: =+N36/$N$84 -> 0.017957479 | M36: =+N36 -> 548.2933 | N36: =398.293296+100+50 -> 548.2933 | O36: =+N36/1.05 -> 522.18409 | P36: 45.16 | R36: 398.2933 | S36: =R36/1.05 -> 379.32695 | AD36: =+O36*20% -> 104.43682 | AI36: =+O36*50% -> 261.09205 | BK36: =+O36*30% -> 156.65523 | DW36: 0.1 | DX36: =O36/DW36 -> 5221.8409 | DZ36: 285.93 | EA36: =+O36-DZ36 -> 236.25409 | EB36: =+DZ36/O36 -> 0.54756551 | EC36: 46079 | ED36: =+DZ36*1.15 -> 328.8195 | EE36: CPV | EF36: =+EG36/DX36 -> 2.0668956 | EG36: =+EO36 -> 10793 | EH36: =IFERROR((+DZ36/EG36*1000),"") -> 26.492171 | EI36: =IFERROR(+DZ36/EO36,"") -> 0.026492171 | EJ36: =+IFERROR(+DZ36/EN36,"") -> 0.34120525 | EK36: =IFERROR(+(+DZ36/EP36*1000),"") -> 0.97776243 | EL36: 65409 | EM36: 4.47 | EN36: 838 | EO36: 10793 | EP36: 292433 | EQ36: =+IFERROR(+EN36/EP36,"") -> 0.0028656137 | ER36: =IFERROR(+EO36/EP36,"") -> 0.036907599 | ES36: JOB:DCEEA5A10068_MKT:MKT0022145_MARCA:DC_PLATAFORMA:TIKTOK_FECHA:27012026_CAMPAÑA:VACCOSTA2026_ETAPA:LAYER02_COMPRA:CPV_COMUNICACION:HOTELES_FORMATO:INFEED_AUDIENCIA:BASESOCIOS | ET36: EN PAUTA | EU36: Se duplico el 24 de feb, por que se desactivaron todas las campañas de TikTok. | EV36: https://www.dinersclub.com.ec/blubenefits/?utm_source=TIKTOK&utm_medium=CPV&utm_campaign=DINERS-VACCOSTA-2026-MKT0022145&utm_id=DINERS-VACCOSTA-2026-MKT0022145&utm_term=DINERS-VACCOSTA-2026-MKT0022145&utm_content=TIKTOK-INFEED | EW36: 150.18 | EX36: =O36-EW36 -> 372.00409
H37: RMK WEB/RMK INTERACCIÓN RRSS (EXC RMK VISUALIZACIÓN HOTELES) REGION COSTA | I37: 155000 | K37: =+N37/$N$84 -> 0.01629195 | M37: =+N37 -> 497.43994 | N37: =347.439944+100+50 -> 497.43994 | O37: =+N37/1.05 -> 473.75233 | P37: 52.71 | R37: 347.43994 | S37: =R37/1.05 -> 330.89518 | AD37: =+O37*20% -> 94.750466 | AI37: =+O37*50% -> 236.87616 | BK37: =+O37*30% -> 142.1257 | DW37: 0.1 | DX37: =O37/DW37 -> 4737.5233 | DZ37: 264.97 | EA37: =+O37-DZ37 -> 208.78233 | EB37: =+DZ37/O37 -> 0.55930068 | EC37: 46079 | ED37: =+DZ37*1.15 -> 304.7155 | EE37: CPV | EF37: =+EG37/DX37 -> 4.5162839 | EG37: =+EO37 -> 21396 | EH37: =IFERROR((+DZ37/EG37*1000),"") -> 12.38409 | EI37: =IFERROR(+DZ37/EO37,"") -> 0.01238409 | EJ37: =+IFERROR(+DZ37/EN37,"") -> 0.13800521 | EK37: =IFERROR(+(+DZ37/EP37*1000),"") -> 0.66577217 | EL37: 117703 | EM37: 3.38 | EN37: 1920 | EO37: 21396 | EP37: 397989 | EQ37: =+IFERROR(+EN37/EP37,"") -> 0.0048242539 | ER37: =IFERROR(+EO37/EP37,"") -> 0.05376028 | ES37: JOB:DCEEA5A10068_MKT:MKT0022145_MARCA:DC_PLATAFORMA:TIKTOK_FECHA:27012026_CAMPAÑA:VACCOSTA2026_ETAPA:LAYER02_COMPRA:CPV_COMUNICACION:HOTELES_FORMATO:INFEED_AUDIENCIA:RMK | ET37: EN PAUTA | EV37: https://www.dinersclub.com.ec/blubenefits/?utm_source=TIKTOK&utm_medium=CPV&utm_campaign=DINERS-VACCOSTA-2026-MKT0022145&utm_id=DINERS-VACCOSTA-2026-MKT0022145&utm_term=DINERS-VACCOSTA-2026-MKT0022145&utm_content=TIKTOK-INFEED | EW37: 171.53 | EX37: =O37-EW37 -> 302.22233
E38: YOUTUBE | F38: INSTREAM | G38: ESPECIALIDADES HOTELES Snackables con EXPERIENCIAS de amenities y beneficios | H38: BASE SOCIOS DINERS (EXC RMK VISUALIZACIÓN HOTELES) REGION COSTA | I38: 54000 | J38: CPV | K38: =+N38/$N$84 -> 0.0045293257 | M38: =+N38 -> 138.2933 | N38: =298.293296-160-30+30 -> 138.2933 | O38: =+N38/1.05 -> 131.7079 | R38: 298.2933 | S38: =R38/1.05 -> 284.08885 | AD38: =+O38*20% -> 26.34158 | AI38: =+O38*50% -> 65.85395 | BK38: =+O38*30% -> 39.51237 | DW38: 1 | DX38: =O38/DW38 -> 131.7079 | EA38: =+O38-DZ38 -> 131.7079 | EB38: =+DZ38/O38 -> 0 | ED38: =+DZ38*1.15 -> 0 | EE38: CPV | EF38: =+EG38/DX38 -> 0 | EG38: =+EO38 -> 0 | EH38: =IFERROR((+DZ38/EG38*1000),"") | EI38: =IFERROR(+DZ38/EO38,"") | EJ38: =+IFERROR(+DZ38/EN38,"") | EK38: =IFERROR(+(+DZ38/EP38*1000),"") | EQ38: =+IFERROR(+EN38/EP38,"") | ER38: =IFERROR(+EO38/EP38,"") | ES38: JOB:DCEEA5A10068_MKT:MKT0022145_MARCA:DC_PLATAFORMA:YOUTUBE_FECHA:02032026_CAMPAÑA:VACCOSTA2026_ETAPA:LAYER02_COMPRA:CPV_COMUNICACION:HOTELES_FORMATO:INSTREAM_AUDIENCIA:BASESOCIOS | ET38: PENDIENTE APROBACION | EV38: www.dinersclub.com.ec/blubenefits/?utm_source=YOUTUBE&utm_medium=CPV&utm_campaign=DINERS-VACCOSTA-2026-MKT0022145&utm_id=DINERS-VACCOSTA-2026-MKT0022145&utm_term=DINERS-VACCOSTA-2026-MKT0022145&utm_content=YOUTUBE-INSTREAM
H39: RMK WEB/RMK INTERACCIÓN RRSS (EXC RMK VISUALIZACIÓN HOTELES) REGION COSTA | I39: - | K39: =+N39/$N$84 -> 0.0064664726 | M39: =+N39 -> 197.43994 | N39: =247.439944-100+50 -> 197.43994 | O39: =+N39/1.05 -> 188.03804 | R39: 247.43994 | S39: =R39/1.05 -> 235.65709 | AD39: =+O39*20% -> 37.607608 | AI39: =+O39*50% -> 94.019021 | BK39: =+O39*30% -> 56.411413 | DW39: 1 | DX39: =O39/DW39 -> 188.03804 | EA39: =+O39-DZ39 -> 188.03804 | EB39: =+DZ39/O39 -> 0 | ED39: =+DZ39*1.15 -> 0 | EE39: CPV | EF39: =+EG39/DX39 -> 0 | EG39: =+EO39 -> 0 | EH39: =IFERROR((+DZ39/EG39*1000),"") | EI39: =IFERROR(+DZ39/EO39,"") | EJ39: =+IFERROR(+DZ39/EN39,"") | EK39: =IFERROR(+(+DZ39/EP39*1000),"") | EQ39: =+IFERROR(+EN39/EP39,"") | ER39: =IFERROR(+EO39/EP39,"") | ES39: JOB:DCEEA5A10068_MKT:MKT0022145_MARCA:DC_PLATAFORMA:YOUTUBE_FECHA:02032026_CAMPAÑA:VACCOSTA2026_ETAPA:LAYER02_COMPRA:CPV_COMUNICACION:HOTELES_FORMATO:INSTREAM_AUDIENCIA:RMK | ET39: PENDIENTE APROBACION | EV39: www.dinersclub.com.ec/blubenefits/?utm_source=YOUTUBE&utm_medium=CPV&utm_campaign=DINERS-VACCOSTA-2026-MKT0022145&utm_id=DINERS-VACCOSTA-2026-MKT0022145&utm_term=DINERS-VACCOSTA-2026-MKT0022145&utm_content=YOUTUBE-INSTREAM
D40: AGENCIAS DE VIAJE | E40: META | F40: REEL/VIDEO AD | G40: ESPECIALIDADES AGENCIAS DE VIAJES Seguridad de tener todo | H40: BASE SOCIOS DINERS (EXC RMK VISUALIZACIÓN VIAJES) REGION COSTA | I40: 266000 | J40: CPV TRUVIEW 2 SEG | K40: =+N40/$N$84 -> 0.025192641 | M40: =+N40 -> 769.20354 | N40: =(198.862197333209*70%)+300+150+50+30+100 -> 769.20354 | O40: =+N40/1.15 -> 668.87264 | P40: 87.13 | R40: 669.20354 | S40: =R40/1.15 -> 581.91612 | AD40: =+O40*20% -> 133.77453 | AI40: =+O40*50% -> 334.43632 | BK40: =+O40*30% -> 200.66179 | DW40: 0.09 | DX40: =O40/DW40 -> 7431.9182 | DZ40: 571.88 | EA40: =+O40-DZ40 -> 96.992642 | EB40: =+DZ40/O40 -> 0.85499087 | EC40: 46079 | ED40: =+DZ40*1.15 -> 657.662 | EE40: CPV | EF40: =+EG40/DX40 -> 69.306871 | EG40: =+EP40 -> 515083 | EH40: =IFERROR((+DZ40/EG40*1000),"") -> 1.1102677 | EI40: =IFERROR(+DZ40/EO40,"") -> 0.076546647 | EJ40: =+IFERROR(+DZ40/EN40,"") -> 2.125948 | EK40: =IFERROR(+(+DZ40/EP40*1000),"") -> 1.1102677 | EL40: 99756 | EM40: 5.16 | EN40: 269 | EO40: 7471 | EP40: 515083 | EQ40: =+IFERROR(+EN40/EP40,"") -> 0.00052224593 | ER40: =IFERROR(+EO40/EP40,"") -> 0.014504459 | ES40: JOB:DCEEA5A10068_MKT:MKT0022145_MARCA:DC_PLATAFORMA:META_FECHA:27012026_CAMPAÑA:VACCOSTA2026_ETAPA:LAYER02_COMPRA:CPV_COMUNICACION:VIAJES_FORMATO:VIDEOADREEL_AUDIENCIA:BASESOCIOS | ET40: EN PAUTA | EU40: se aumento el creativo de tiktok el 11 de feb | EV40: https://www.dinersclub.com.ec/blubenefits/?utm_source=META&utm_medium=CPV&utm_campaign=DINERS-VACCOSTA-2026-MKT0022145&utm_id=DINERS-VACCOSTA-2026-MKT0022145&utm_term=DINERS-VACCOSTA-2026-MKT0022145&utm_content=META-VIDEOADREEL | FD40: CAMBIO DE PIEZAS DE LOS VIDEOAD/REELS DE TODAS LAS CATEGORÍAS
H41: RMK WEB/RMK INTERACCIÓN RRSS (EXC RMK VISUALIZACIÓN VIAJES) REGION COSTA | I41: 155000 | K41: =+N41/$N$84 -> 0.02419705 | M41: =+N41 -> 738.80531 | N41: =(298.293295999814*70%)+300+100+30+100 -> 738.80531 | O41: =+N41/1.15 -> 642.4394 | P41: 88.31 | R41: 638.80531 | S41: =R41/1.15 -> 555.48288 | AD41: =+O41*20% -> 128.48788 | AI41: =+O41*50% -> 321.2197 | BK41: =+O41*30% -> 192.73182 | DW41: 0.09 | DX41: =O41/DW41 -> 7138.2155 | DZ41: 547.39 | EA41: =+O41-DZ41 -> 95.049398 | EB41: =+DZ41/O41 -> 0.85204924 | EC41: 46079 | ED41: =+DZ41*1.15 -> 629.4985 | EE41: CPV | EF41: =+EG41/DX41 -> 156.56112 | EG41: =+EP41 -> 1117567 | EH41: =IFERROR((+DZ41/EG41*1000),"") -> 0.48980509 | EI41: =IFERROR(+DZ41/EO41,"") -> 0.029789932 | EJ41: =+IFERROR(+DZ41/EN41,"") -> 1.3286165 | EK41: =IFERROR(+(+DZ41/EP41*1000),"") -> 0.48980509 | EL41: 254008 | EM41: 4.4 | EN41: 412 | EO41: 18375 | EP41: 1117567 | EQ41: =+IFERROR(+EN41/EP41,"") -> 0.00036865799 | ER41: =IFERROR(+EO41/EP41,"") -> 0.016441967 | ES41: JOB:DCEEA5A10068_MKT:MKT0022145_MARCA:DC_PLATAFORMA:META_FECHA:27012026_CAMPAÑA:VACCOSTA2026_ETAPA:LAYER02_COMPRA:CPV_COMUNICACION:VIAJES_FORMATO:VIDEOADREEL_AUDIENCIA:RMK | ET41: EN PAUTA | EU41: se aumento el creativo de tiktok el 11 de feb | EV41: https://www.dinersclub.com.ec/blubenefits/?utm_source=META&utm_medium=CPV&utm_campaign=DINERS-VACCOSTA-2026-MKT0022145&utm_id=DINERS-VACCOSTA-2026-MKT0022145&utm_term=DINERS-VACCOSTA-2026-MKT0022145&utm_content=META-VIDEOADREEL
E42: META | F42: DINAMICOS | G42: ESPECIALIDADES AGENCIAS DE VIAJES Seguridad de tener todo | H42: BASE SOCIOS DINERS (EXC RMK VISUALIZACIÓN VIAJES) REGION COSTA | I42: 266000 | J42: CPC | K42: =+N42/$N$84 -> 0.0035914957 | M42: =+N42 -> 109.65866 | N42: =(198.862197333209*30%)+50 -> 109.65866 | O42: =+N42/1.15 -> 95.355356 | R42: 59.658659 | S42: =R42/1.15 -> 51.877095 | AD42: =+O42*20% -> 19.071071 | AI42: =+O42*50% -> 47.677678 | BK42: =+O42*30% -> 28.606607 | DW42: 0.09 | DX42: =O42/DW42 -> 1059.504 | EA42: =+O42-DZ42 -> 95.355356 | EB42: =+DZ42/O42 -> 0 | ED42: =+DZ42*1.15 -> 0 | EE42: CPC | EF42: =+EG42/DX42 -> 0 | EG42: =+EP42 -> 0 | EH42: =IFERROR((+DZ42/EG42*1000),"") | EI42: =IFERROR(+DZ42/EO42,"") | EJ42: =+IFERROR(+DZ42/EN42,"") | EK42: =IFERROR(+(+DZ42/EP42*1000),"") | EQ42: =+IFERROR(+EN42/EP42,"") | ER42: =IFERROR(+EO42/EP42,"") | ES42: JOB:DCEEA5A10068_MKT:MKT0022145_MARCA:DC_PLATAFORMA:META_FECHA:27022026_CAMPAÑA:VACCOSTA2026_ETAPA:LAYER02_COMPRA:CPC_COMUNICACION:VIAJES_FORMATO:DINAMICOS_AUDIENCIA:BASESOCIOS | ET42: EN PAUTA | EV42: https://www.dinersclub.com.ec/blubenefits/?utm_source=META&utm_medium=CPV&utm_campaign=DINERS-VACCOSTA-2026-MKT0022145&utm_id=DINERS-VACCOSTA-2026-MKT0022145&utm_term=DINERS-VACCOSTA-2026-MKT0022145&utm_content=META-DINAMICOS
H43: RMK WEB/RMK INTERACCIÓN RRSS (EXC RMK VISUALIZACIÓN VIAJES) REGION COSTA | I43: 155000 | K43: =+N43/$N$84 -> 0.0045684538 | M43: =+N43 -> 139.48799 | N43: =(298.293295999814*30%)+50 -> 139.48799 | O43: =+N43/1.15 -> 121.2939 | R43: 89.487989 | S43: =R43/1.15 -> 77.815642 | AD43: =+O43*20% -> 24.258781 | AI43: =+O43*50% -> 60.646952 | BK43: =+O43*30% -> 36.388171 | DW43: 0.09 | DX43: =O43/DW43 -> 1347.71 | EA43: =+O43-DZ43 -> 121.2939 | EB43: =+DZ43/O43 -> 0 | ED43: =+DZ43*1.15 -> 0 | EE43: CPC | EF43: =+EG43/DX43 -> 0 | EG43: =+EP43 -> 0 | EH43: =IFERROR((+DZ43/EG43*1000),"") | EI43: =IFERROR(+DZ43/EO43,"") | EJ43: =+IFERROR(+DZ43/EN43,"") | EK43: =IFERROR(+(+DZ43/EP43*1000),"") | EQ43: =+IFERROR(+EN43/EP43,"") | ER43: =IFERROR(+EO43/EP43,"") | ES43: JOB:DCEEA5A10068_MKT:MKT0022145_MARCA:DC_PLATAFORMA:META_FECHA:27022026_CAMPAÑA:VACCOSTA2026_ETAPA:LAYER02_COMPRA:CPC_COMUNICACION:VIAJES_FORMATO:DINAMICOS_AUDIENCIA:RMK | ET43: EN PAUTA | EV43: https://www.dinersclub.com.ec/blubenefits/?utm_source=META&utm_medium=CPV&utm_campaign=DINERS-VACCOSTA-2026-MKT0022145&utm_id=DINERS-VACCOSTA-2026-MKT0022145&utm_term=DINERS-VACCOSTA-2026-MKT0022145&utm_content=META-DINAMICOS | EX43: NUEVO PPTO
E44: TIKTOK | F44: INFEED | G44: ESPECIALIDADES AGENCIAS DE VIAJES Seguridad de tener todo | H44: BASE SOCIOS DINERS (EXC RMK VISUALIZACIÓN VIAJES) REGION COSTA | I44: 109000 | J44: CPV | K44: =+N44/$N$84 -> 0.021803824 | M44: =+N44 -> 665.73324 | N44: =745.73324-300-30+100+100+50 -> 665.73324 | O44: =+N44/1.05 -> 634.03166 | P44: 44.3 | R44: 415.73324 | S44: =R44/1.05 -> 395.93642 | AD44: =+O44*20% -> 126.80633 | AI44: =+O44*50% -> 317.01583 | BK44: =+O44*30% -> 190.2095 | DW44: 0.1 | DX44: =O44/DW44 -> 6340.3166 | DZ44: 293.57 | EA44: =+O44-DZ44 -> 340.46166 | EB44: =+DZ44/O44 -> 0.46302104 | EC44: 46079 | ED44: =+DZ44*1.15 -> 337.6055 | EE44: CPV | EF44: =+EG44/DX44 -> 42.567117 | EG44: =+EP44 -> 269889 | EH44: =IFERROR((+DZ44/EG44*1000),"") -> 1.0877435 | EI44: =IFERROR(+DZ44/EO44,"") -> 0.031685915 | EJ44: =+IFERROR(+DZ44/EN44,"") -> 0.3536988 | EK44: =IFERROR(+(+DZ44/EP44*1000),"") -> 1.0877435 | EL44: 70473 | EM44: 3.83 | EN44: 830 | EO44: 9265 | EP44: 269889 | EQ44: =+IFERROR(+EN44/EP44,"") -> 0.0030753384 | ER44: =IFERROR(+EO44/EP44,"") -> 0.034328928 | ES44: JOB:DCEEA5A10068_MKT:MKT0022145_MARCA:DC_PLATAFORMA:TIKTOK_FECHA:27012026_CAMPAÑA:VACCOSTA2026_ETAPA:LAYER02_COMPRA:CPV_COMUNICACION:VIAJES_FORMATO:INFEED_AUDIENCIA:BASESOCIOS | ET44: EN PAUTA | EU44: Se duplico el 24 de feb, por que se desactivaron todas las campañas de TikTok. | EV44: https://www.dinersclub.com.ec/blubenefits/?utm_source=TIKTOK&utm_medium=CPV&utm_campaign=DINERS-VACCOSTA-2026-MKT0022145&utm_id=DINERS-VACCOSTA-2026-MKT0022145&utm_term=DINERS-VACCOSTA-2026-MKT0022145&utm_content=TIKTOK-INFEED | EW44: 150.22 | EX44: =O44-EW44 -> 483.81166
H45: RMK WEB/RMK INTERACCIÓN RRSS (EXC RMK VISUALIZACIÓN VIAJES) REGION COSTA | I45: 155000 | K45: =+N45/$N$84 -> 0.018950067 | M45: =+N45 -> 578.59986 | N45: =(1118.59986-400)-300-30+40+100+50 -> 578.59986 | O45: =+N45/1.05 -> 551.04749 | P45: 53.77 | R45: 388.59986 | S45: =R45/1.05 -> 370.0951 | AD45: =+O45*20% -> 110.2095 | AI45: =+O45*50% -> 275.52374 | BK45: =+O45*30% -> 165.31425 | DW45: 0.1 | DX45: =O45/DW45 -> 5510.4749 | DZ45: 288.05 | EA45: =+O45-DZ45 -> 262.99749 | EB45: =+DZ45/O45 -> 0.52273172 | EC45: 46079 | ED45: =+DZ45*1.15 -> 331.2575 | EE45: CPV | EF45: =+EG45/DX45 -> 68.297562 | EG45: =+EP45 -> 376352 | EH45: =IFERROR((+DZ45/EG45*1000),"") -> 0.76537391 | EI45: =IFERROR(+DZ45/EO45,"") -> 0.014526703 | EJ45: =+IFERROR(+DZ45/EN45,"") -> 0.14182669 | EK45: =IFERROR(+(+DZ45/EP45*1000),"") -> 0.76537391 | EL45: 128517 | EM45: 2.93 | EN45: 2031 | EO45: 19829 | EP45: 376352 | EQ45: =+IFERROR(+EN45/EP45,"") -> 0.0053965437 | ER45: =IFERROR(+EO45/EP45,"") -> 0.052687378 | ES45: JOB:DCEEA5A10068_MKT:MKT0022145_MARCA:DC_PLATAFORMA:TIKTOK_FECHA:27012026_CAMPAÑA:VACCOSTA2026_ETAPA:LAYER02_COMPRA:CPV_COMUNICACION:VIAJES_FORMATO:INFEED_AUDIENCIA:RMK | ET45: EN PAUTA | EV45: https://www.dinersclub.com.ec/blubenefits/?utm_source=TIKTOK&utm_medium=CPV&utm_campaign=DINERS-VACCOSTA-2026-MKT0022145&utm_id=DINERS-VACCOSTA-2026-MKT0022145&utm_term=DINERS-VACCOSTA-2026-MKT0022145&utm_content=TIKTOK-INFEED | EW45: 171.34 | EX45: =O45-EW45 -> 379.70749
E46: YOUTUBE | F46: INSTREAM | G46: ESPECIALIDADES AGENCIAS DE VIAJES Seguridad de tener todo | H46: BASE SOCIOS DINERS (EXC RMK VISUALIZACIÓN VIAJES) REGION COSTA | I46: 54000 | J46: CPV | K46: =+N46/$N$84 -> 0.0047887183 | M46: =+N46 -> 146.2133 | N46: =(398.293296-150)-140+30+7.92 -> 146.2133 | O46: =+N46/1.05 -> 139.25076 | R46: 248.2933 | S46: =R46/1.05 -> 236.46981 | AD46: =+O46*20% -> 27.850152 | AI46: =+O46*50% -> 69.625379 | BK46: =+O46*30% -> 41.775227 | DW46: 1 | DX46: =O46/DW46 -> 139.25076 | EA46: =+O46-DZ46 -> 139.25076 | EB46: =+DZ46/O46 -> 0 | ED46: =+DZ46*1.15 -> 0 | EE46: CPV | EF46: =+EG46/DX46 -> 0 | EG46: =+EP46 -> 0 | EH46: =IFERROR((+DZ46/EG46*1000),"") | EI46: =IFERROR(+DZ46/EO46,"") | EJ46: =+IFERROR(+DZ46/EN46,"") | EK46: =IFERROR(+(+DZ46/EP46*1000),"") | EQ46: =+IFERROR(+EN46/EP46,"") | ER46: =IFERROR(+EO46/EP46,"") | ES46: JOB:DCEEA5A10068_MKT:MKT0022145_MARCA:DC_PLATAFORMA:YOUTUBE_FECHA:02032026_CAMPAÑA:VACCOSTA2026_ETAPA:LAYER02_COMPRA:CPV_COMUNICACION:VIAJES_FORMATO:INSTREAM_AUDIENCIA:BASESOCIOS | ET46: PENDIENTE APROBACION | EV46: www.dinersclub.com.ec/blubenefits/?utm_source=YOUTUBE&utm_medium=CPV&utm_campaign=DINERS-VACCOSTA-2026-MKT0022145&utm_id=DINERS-VACCOSTA-2026-MKT0022145&utm_term=DINERS-VACCOSTA-2026-MKT0022145&utm_content=YOUTUBE-INSTREAM
H47: RMK WEB/RMK INTERACCIÓN RRSS (EXC RMK VISUALIZACIÓN VIAJES) REGION COSTA | I47: - | K47: =+N47/$N$84 -> 0.0081040522 | M47: =+N47 -> 247.43994 | N47: =247.439944-150+100+50 -> 247.43994 | O47: =+N47/1.05 -> 235.65709 | R47: 97.439944 | S47: =R47/1.05 -> 92.799947 | AD47: =+O47*20% -> 47.131418 | AI47: =+O47*50% -> 117.82854 | BK47: =+O47*30% -> 70.697127 | DW47: 1 | DX47: =O47/DW47 -> 235.65709 | EA47: =+O47-DZ47 -> 235.65709 | EB47: =+DZ47/O47 -> 0 | ED47: =+DZ47*1.15 -> 0 | EE47: CPV | EF47: =+EG47/DX47 -> 0 | EG47: =+EP47 -> 0 | EH47: =IFERROR((+DZ47/EG47*1000),"") | EI47: =IFERROR(+DZ47/EO47,"") | EJ47: =+IFERROR(+DZ47/EN47,"") | EK47: =IFERROR(+(+DZ47/EP47*1000),"") | EQ47: =+IFERROR(+EN47/EP47,"") | ER47: =IFERROR(+EO47/EP47,"") | ES47: JOB:DCEEA5A10068_MKT:MKT0022145_MARCA:DC_PLATAFORMA:YOUTUBE_FECHA:02032026_CAMPAÑA:VACCOSTA2026_ETAPA:LAYER02_COMPRA:CPV_COMUNICACION:VIAJES_FORMATO:INSTREAM_AUDIENCIA:RMK | ET47: PENDIENTE APROBACION | EV47: www.dinersclub.com.ec/blubenefits/?utm_source=YOUTUBE&utm_medium=CPV&utm_campaign=DINERS-VACCOSTA-2026-MKT0022145&utm_id=DINERS-VACCOSTA-2026-MKT0022145&utm_term=DINERS-VACCOSTA-2026-MKT0022145&utm_content=YOUTUBE-INSTREAM
C48: LAYER 02 | L48: =SUM(L24:L47) -> 5458.3415 | M48: =SUM(M24:M47) -> 4905.5583 | N48: =SUM(N24:N47) -> 10363.9 | O48: =SUM(O24:O47) -> 9358.5212 | R48: 9758.8686
C49: LAYER 03 AEROLINEAS | D49: ESTABLECIMIENTO 1: AIR EUROPA | E49: META | F49: VIDEO AD /REEL/ESTÁTICO | G49: AEROLINEAS | H49: RMK COMPORTAMIENTO DE VISUALIZACION LAYER 02 | I49: POR DEFINIR | J49: CPC | K49: =+N49/$N$84 -> 0.016450142 | M49: =+N49 -> 502.27 | N49: 502.27 | O49: =N49/1.15 -> 436.75652 | R49: 502.27 | AZ49: =+N49/3 -> 167.42333 | BK49: =+N49/3 -> 167.42333 | CP49: =+N49/3 -> 167.42333 | DW49: 0.05 | DX49: =O49/DW49 -> 8735.1304 | DZ49: 35.62 | EA49: =+O49-DZ49 -> 401.13652 | EB49: =+DZ49/O49 -> 0.081555737 | EC49: 46076 | ED49: =+DZ49*1.15 -> 40.963 | EE49: CPC | EF49: =+EG49/DX49 -> 0.0968503 | EG49: =+EN49 -> 846 | EH49: =IFERROR((+DZ49/EG49*1000),"") -> 42.104019 | EI49: =IFERROR(+DZ49/EO49,"") -> 0.0051841071 | EJ49: =+IFERROR(+DZ49/EN49,"") -> 0.042104019 | EK49: =IFERROR(+(+DZ49/EP49*1000),"") -> 1.2644209 | EL49: 11222 | EM49: 2.51 | EN49: 846 | EO49: 6871 | EP49: 28171 | EQ49: =+IFERROR(+EN49/EP49,"") -> 0.030030883 | ER49: =IFERROR(+EO49/EP49,"") -> 0.2439033 | ES49: JOB:DCEEA5A10068_MKT:MKT0022145_MARCA:DC_PLATAFORMA:META_FECHA:18022026_CAMPAÑA:VACCOSTA2026_ETAPA:LAYER03_COMPRA:CPC_COMUNICACION:AEROLINEAS_ESTABLECIMIENTO:AIREUROPA_FORMATO:VIDEOAD/REEL/ESTATICO_AUDIENCIA:VIEWSAEROLINEAS | ET49: EN PAUTA
E50: GOOGLE | F50: DEMAND GEN | H50: BASE SOCIOS DINERS REGION COSTA | I50: POR DEFINIR | J50: CPC | K50: =+N50/$N$84 -> 0.013411777 | M50: =+N50 -> 409.5 | N50: 409.5 | O50: =N50/1.05 -> 390 | R50: 409.5 | AU50: =+N50/3 -> 136.5 | BK50: =+N50/3 -> 136.5 | CP50: =+N50/3 -> 136.5 | DW50: 0.09 | DX50: =O50/DW50 -> 4333.3333 | DZ50: 50.95 | EA50: =+O50-DZ50 -> 339.05 | EB50: =+DZ50/O50 -> 0.13064103 | EC50: 46076 | ED50: =+DZ50*1.15 -> 58.5925 | EE50: CPC | EF50: =+EG50/DX50 -> 0.22130769 | EG50: =+EN50 -> 959 | EH50: =IFERROR((+DZ50/EG50*1000),"") -> 53.128259 | EI50: =IFERROR(+DZ50/EO50,"") | EJ50: =+IFERROR(+DZ50/EN50,"") -> 0.053128259 | EK50: =IFERROR(+(+DZ50/EP50*1000),"") -> 1.0656321 | EN50: 959 | EP50: 47812 | EQ50: =+IFERROR(+EN50/EP50,"") -> 0.020057726 | ER50: =IFERROR(+EO50/EP50,"") -> 0 | ET50: EN PAUTA
D51: ESTABLECIMIENTO 2: AVIANCA | E51: META | F51: VIDEO AD /REEL/ESTÁTICO | H51: RMK COMPORTAMIENTO DE VISUALIZACION LAYER 02 | I51: POR DEFINIR | J51: CPC | K51: =+N51/$N$84 -> 0.016450142 | M51: =+N51 -> 502.27 | N51: 502.27 | O51: =N51/1.15 -> 436.75652 | R51: 502.27 | AZ51: =+N51/3 -> 167.42333 | BK51: =+N51/3 -> 167.42333 | CP51: =+N51/3 -> 167.42333 | DW51: 0.05 | DX51: =O51/DW51 -> 8735.1304 | DZ51: 35.63 | EA51: =+O51-DZ51 -> 401.12652 | EB51: =+DZ51/O51 -> 0.081578633 | EC51: 46076 | ED51: =+DZ51*1.15 -> 40.9745 | EE51: CPC | EF51: =+EG51/DX51 -> 0.095133096 | EG51: =+EN51 -> 831 | EH51: =IFERROR((+DZ51/EG51*1000),"") -> 42.876053 | EI51: =IFERROR(+DZ51/EO51,"") -> 0.0048416904 | EJ51: =+IFERROR(+DZ51/EN51,"") -> 0.042876053 | EK51: =IFERROR(+(+DZ51/EP51*1000),"") -> 1.3421984 | EL51: 9689 | EM51: 2.74 | EN51: 831 | EO51: 7359 | EP51: 26546 | EQ51: =+IFERROR(+EN51/EP51,"") -> 0.031304151 | ER51: =IFERROR(+EO51/EP51,"") -> 0.27721691 | ES51: JOB:DCEEA5A10068_MKT:MKT0022145_MARCA:DC_PLATAFORMA:META_FECHA:18022026_CAMPAÑA:VACCOSTA2026_ETAPA:LAYER03_COMPRA:CPC_COMUNICACION:AEROLINEAS_ESTABLECIMIENTO:AVIANCA_FORMATO:VIDEOAD/REEL/ESTATICO_AUDIENCIA:VIEWSAEROLINEAS | ET51: EN PAUTA
E52: GOOGLE | F52: DEMAND GEN | H52: BASE SOCIOS DINERS REGION COSTA | I52: POR DEFINIR | J52: CPC | K52: =+N52/$N$84 -> 0.013411777 | M52: =+N52 -> 409.5 | N52: 409.5 | O52: =N52/1.05 -> 390 | R52: 409.5 | AU52: =+N52/3 -> 136.5 | BK52: =+N52/3 -> 136.5 | CP52: =+N52/3 -> 136.5 | DW52: 0.09 | DX52: =O52/DW52 -> 4333.3333 | DZ52: 50.95 | EA52: =+O52-DZ52 -> 339.05 | EB52: =+DZ52/O52 -> 0.13064103 | EC52: 46076 | ED52: =+DZ52*1.15 -> 58.5925 | EE52: CPC | EF52: =+EG52/DX52 -> 0.22384615 | EG52: =+EN52 -> 970 | EH52: =IFERROR((+DZ52/EG52*1000),"") -> 52.525773 | EI52: =IFERROR(+DZ52/EO52,"") | EJ52: =+IFERROR(+DZ52/EN52,"") -> 0.052525773 | EK52: =IFERROR(+(+DZ52/EP52*1000),"") -> 1.0872581 | EN52: 970 | EP52: 46861 | EQ52: =+IFERROR(+EN52/EP52,"") -> 0.020699516 | ER52: =IFERROR(+EO52/EP52,"") -> 0 | ET52: EN PAUTA
D53: ESTABLECIMIENTO 3: COPA AIRLINES | E53: META | F53: VIDEO AD /REEL/ESTÁTICO | H53: RMK COMPORTAMIENTO DE VISUALIZACION LAYER 02 | I53: POR DEFINIR | J53: CPC | K53: =+N53/$N$84 -> 0.016450142 | M53: =+N53 -> 502.27 | N53: 502.27 | O53: =N53/1.15 -> 436.75652 | R53: 502.27 | AZ53: =+N53/3 -> 167.42333 | BK53: =+N53/3 -> 167.42333 | CP53: =+N53/3 -> 167.42333 | DW53: 0.05 | DX53: =O53/DW53 -> 8735.1304 | DZ53: 35.71 | EA53: =+O53-DZ53 -> 401.04652 | EB53: =+DZ53/O53 -> 0.081761801 | EC53: 46076 | ED53: =+DZ53*1.15 -> 41.0665 | EE53: CPC | EF53: =+EG53/DX53 -> 0.10955761 | EG53: =+EN53 -> 957 | EH53: =IFERROR((+DZ53/EG53*1000),"") -> 37.314525 | EI53: =IFERROR(+DZ53/EO53,"") -> 0.0036561892 | EJ53: =+IFERROR(+DZ53/EN53,"") -> 0.037314525 | EK53: =IFERROR(+(+DZ53/EP53*1000),"") -> 1.22871 | EL53: 9354 | EM53: 3.11 | EN53: 957 | EO53: 9767 | EP53: 29063 | EQ53: =+IFERROR(+EN53/EP53,"") -> 0.032928466 | ER53: =IFERROR(+EO53/EP53,"") -> 0.33606304 | ES53: JOB:DCEEA5A10068_MKT:MKT0022145_MARCA:DC_PLATAFORMA:META_FECHA:18022026_CAMPAÑA:VACCOSTA2026_ETAPA:LAYER03_COMPRA:CPC_COMUNICACION:AEROLINEAS_ESTABLECIMIENTO:COPAAIRLINES_FORMATO:VIDEOAD/REEL/ESTATICO_AUDIENCIA:VIEWSAEROLINEAS | ET53: EN PAUTA
E54: GOOGLE | F54: DEMAND GEN | H54: BASE SOCIOS DINERS REGION COSTA | I54: POR DEFINIR | J54: CPC | K54: =+N54/$N$84 -> 0.013411777 | M54: =+N54 -> 409.5 | N54: 409.5 | O54: =N54/1.05 -> 390 | R54: 409.5 | AU54: =+N54/3 -> 136.5 | BK54: =+N54/3 -> 136.5 | CP54: =+N54/3 -> 136.5 | DW54: 0.09 | DX54: =O54/DW54 -> 4333.3333 | DZ54: 50.89 | EA54: =+O54-DZ54 -> 339.11 | EB54: =+DZ54/O54 -> 0.13048718 | EC54: 46076 | ED54: =+DZ54*1.15 -> 58.5235 | EE54: CPC | EF54: =+EG54/DX54 -> 0.21184615 | EG54: =+EN54 -> 918 | EH54: =IFERROR((+DZ54/EG54*1000),"") -> 55.43573 | EI54: =IFERROR(+DZ54/EO54,"") | EJ54: =+IFERROR(+DZ54/EN54,"") -> 0.05543573 | EK54: =IFERROR(+(+DZ54/EP54*1000),"") -> 1.5810731 | EN54: 918 | EP54: 32187 | EQ54: =+IFERROR(+EN54/EP54,"") -> 0.028520831 | ER54: =IFERROR(+EO54/EP54,"") -> 0 | ET54: EN PAUTA
D55: ESTABLECIMIENTO 4: IBERIA | E55: META | F55: VIDEO AD /REEL/ESTÁTICO | H55: RMK COMPORTAMIENTO DE VISUALIZACION LAYER 02 | I55: POR DEFINIR | J55: CPC | K55: =+N55/$N$84 -> 0.016450142 | M55: =+N55 -> 502.27 | N55: 502.27 | O55: =N55/1.15 -> 436.75652 | R55: 502.27 | AZ55: =+N55/3 -> 167.42333 | BK55: =+N55/3 -> 167.42333 | CP55: =+N55/3 -> 167.42333 | DW55: 0.05 | DX55: =O55/DW55 -> 8735.1304 | DZ55: 34.75 | EA55: =+O55-DZ55 -> 402.00652 | EB55: =+DZ55/O55 -> 0.07956378 | EC55: 46076 | ED55: =+DZ55*1.15 -> 39.9625 | EE55: CPC | EF55: =+EG55/DX55 -> 0.16279093 | EG55: =+EN55 -> 1422 | EH55: =IFERROR((+DZ55/EG55*1000),"") -> 24.437412 | EI55: =IFERROR(+DZ55/EO55,"") -> 0.0025626844 | EJ55: =+IFERROR(+DZ55/EN55,"") -> 0.024437412 | EK55: =IFERROR(+(+DZ55/EP55*1000),"") -> 0.71268894 | EL55: 14785 | EM55: 3.3 | EN55: 1422 | EO55: 13560 | EP55: 48759 | EQ55: =+IFERROR(+EN55/EP55,"") -> 0.029163847 | ER55: =IFERROR(+EO55/EP55,"") -> 0.2781025 | ES55: JOB:DCEEA5A10068_MKT:MKT0022145_MARCA:DC_PLATAFORMA:META_FECHA:18022026_CAMPAÑA:VACCOSTA2026_ETAPA:LAYER03_COMPRA:CPC_COMUNICACION:AEROLINEAS_ESTABLECIMIENTO:IBERIA_FORMATO:VIDEOAD/REEL/ESTATICO_AUDIENCIA:VIEWAEROLINEAS | ET55: EN PAUTA
E56: GOOGLE | F56: DEMAND GEN | H56: BASE SOCIOS DINERS REGION COSTA | I56: POR DEFINIR | J56: CPC | K56: =+N56/$N$84 -> 0.013411777 | M56: =+N56 -> 409.5 | N56: 409.5 | O56: =N56/1.05 -> 390 | R56: 409.5 | AU56: =+N56/3 -> 136.5 | BK56: =+N56/3 -> 136.5 | CP56: =+N56/3 -> 136.5 | DW56: 0.09 | DX56: =O56/DW56 -> 4333.3333 | DZ56: 50.79 | EA56: =+O56-DZ56 -> 339.21 | EB56: =+DZ56/O56 -> 0.13023077 | EC56: 46076 | ED56: =+DZ56*1.15 -> 58.4085 | EE56: CPC | EF56: =+EG56/DX56 -> 0.20815385 | EG56: =+EN56 -> 902 | EH56: =IFERROR((+DZ56/EG56*1000),"") -> 56.308204 | EI56: =IFERROR(+DZ56/EO56,"") | EJ56: =+IFERROR(+DZ56/EN56,"") -> 0.056308204 | EK56: =IFERROR(+(+DZ56/EP56*1000),"") -> 1.3811013 | EN56: 902 | EP56: 36775 | EQ56: =+IFERROR(+EN56/EP56,"") -> 0.024527532 | ER56: =IFERROR(+EO56/EP56,"") -> 0 | ES56: JOB:DCEEA5A10068_MKT:MKT0022145_MARCA:DC_PLATAFORMA:GOOGLE_FECHA:13022026_CAMPAÑA:VACCOSTA2026_ETAPA:LAYER03_COMPRA:CPC_COMUNICACION:AEROLINEAS_ESTABLECIMIENTO:IBERIA_FORMATO:DEMANDGEN_AUDIENCIA_BASESOCIOS | ET56: EN PAUTA
C57: LAYER 03 AGENCIAS DE VIAJES | D57: ESTABLECIMIENTO 1: GO GALÁPAGOS | E57: META | F57: VIDEO AD /REEL/ESTÁTICO | G57: AGENCIA DE VIAJES | H57: RMK COMPORTAMIENTO DE VISUALIZACION LAYER 02 | I57: POR DEFINIR | J57: CPC | K57: =+N57/$N$84 -> 0.016450142 | M57: =+N57 -> 502.27 | N57: 502.27 | O57: =N57/1.15 -> 436.75652 | R57: 502.27 | AZ57: =+N57/3 -> 167.42333 | BK57: =+N57/3 -> 167.42333 | CP57: =+N57/3 -> 167.42333 | DW57: 0.05 | DX57: =O57/DW57 -> 8735.1304 | DZ57: 35.47 | EA57: =+O57-DZ57 -> 401.28652 | EB57: =+DZ57/O57 -> 0.081212296 | EC57: 46076 | ED57: =+DZ57*1.15 -> 40.7905 | EE57: CPC | EF57: =+EG57/DX57 -> 0.10337567 | EG57: =+EN57 -> 903 | EH57: =IFERROR((+DZ57/EG57*1000),"") -> 39.280177 | EI57: =IFERROR(+DZ57/EO57,"") -> 0.0047867746 | EJ57: =+IFERROR(+DZ57/EN57,"") -> 0.039280177 | EK57: =IFERROR(+(+DZ57/EP57*1000),"") -> 1.1753206 | EL57: 12345 | EM57: 2.44 | EN57: 903 | EO57: 7410 | EP57: 30179 | EQ57: =+IFERROR(+EN57/EP57,"") -> 0.029921469 | ER57: =IFERROR(+EO57/EP57,"") -> 0.24553497 | ES57: JOB:DCEEA5A10068_MKT:MKT0022145_MARCA:DC_PLATAFORMA:META_FECHA:18022026_CAMPAÑA:VACCOSTA2026_ETAPA:LAYER03_COMPRA:CPC_COMUNICACION:VIAJES_ESTABLECIMIENTO:GALAPAGOSGO_FORMATO:VIDEOAD/REEL/ESTATICO_AUDIENCIA:VIEWSVIAJES | ET57: EN PAUTA
E58: GOOGLE | F58: DEMAND GEN | H58: BASE SOCIOS DINERS REGION COSTA | I58: POR DEFINIR | J58: CPC | K58: =+N58/$N$84 -> 0.013411777 | M58: =+N58 -> 409.5 | N58: 409.5 | O58: =N58/1.05 -> 390 | R58: 409.5 | AU58: =+N58/3 -> 136.5 | BK58: =+N58/3 -> 136.5 | CP58: =+N58/3 -> 136.5 | DW58: 0.09 | DX58: =O58/DW58 -> 4333.3333 | DZ58: 53.74 | EA58: =+O58-DZ58 -> 336.26 | EB58: =+DZ58/O58 -> 0.13779487 | EC58: 46076 | ED58: =+DZ58*1.15 -> 61.801 | EE58: CPC | EF58: =+EG58/DX58 -> 1.9883077 | EG58: =+EN58 -> 8616 | EH58: =IFERROR((+DZ58/EG58*1000),"") -> 6.2372331 | EI58: =IFERROR(+DZ58/EO58,"") | EJ58: =+IFERROR(+DZ58/EN58,"") -> 0.0062372331 | EK58: =IFERROR(+(+DZ58/EP58*1000),"") -> 0.34628297 | EN58: 8616 | EP58: 155191 | EQ58: =+IFERROR(+EN58/EP58,"") -> 0.055518683 | ER58: =IFERROR(+EO58/EP58,"") -> 0 | ET58: EN PAUTA
D59: ESTABLECIMIENTO 2: MARKETING VIP | E59: META | F59: VIDEO AD /REEL/ESTÁTICO | H59: RMK COMPORTAMIENTO DE VISUALIZACION LAYER 02 | I59: POR DEFINIR | J59: CPC | K59: =+N59/$N$84 -> 0.016450142 | M59: =+N59 -> 502.27 | N59: 502.27 | O59: =N59/1.15 -> 436.75652 | R59: 502.27 | AZ59: =+N59/3 -> 167.42333 | BK59: =+N59/3 -> 167.42333 | CP59: =+N59/3 -> 167.42333 | DW59: 0.05 | DX59: =O59/DW59 -> 8735.1304 | DZ59: 35.83 | EA59: =+O59-DZ59 -> 400.92652 | EB59: =+DZ59/O59 -> 0.082036554 | EC59: 46076 | ED59: =+DZ59*1.15 -> 41.2045 | EE59: CPC | EF59: =+EG59/DX59 -> 0.095819977 | EG59: =+EN59 -> 837 | EH59: =IFERROR((+DZ59/EG59*1000),"") -> 42.807646 | EI59: =IFERROR(+DZ59/EO59,"") -> 0.003966128 | EJ59: =+IFERROR(+DZ59/EN59,"") -> 0.042807646 | EK59: =IFERROR(+(+DZ59/EP59*1000),"") -> 1.1904445 | EL59: 11019 | EM59: 2.73 | EN59: 837 | EO59: 9034 | EP59: 30098 | EQ59: =+IFERROR(+EN59/EP59,"") -> 0.027809157 | ER59: =IFERROR(+EO59/EP59,"") -> 0.30015283 | ES59: JOB:DCEEA5A10068_MKT:MKT0022145_MARCA:DC_PLATAFORMA:META_FECHA:18022026_CAMPAÑA:VACCOSTA2026_ETAPA:LAYER03_COMPRA:CPC_COMUNICACION:VIAJES_ESTABLECIMIENTO:MKTVIP_FORMATO:VIDEOAD/REEL/ESTATICO_AUDIENCIA:VIEWSVIAJES | ET59: EN PAUTA
E60: GOOGLE | F60: DEMAND GEN | H60: BASE SOCIOS DINERS REGION COSTA | I60: POR DEFINIR | J60: CPC | K60: =+N60/$N$84 -> 0.013411777 | M60: =+N60 -> 409.5 | N60: 409.5 | O60: =N60/1.05 -> 390 | R60: 409.5 | AU60: =+N60/3 -> 136.5 | BK60: =+N60/3 -> 136.5 | CP60: =+N60/3 -> 136.5 | DW60: 0.09 | DX60: =O60/DW60 -> 4333.3333 | DZ60: 51.4 | EA60: =+O60-DZ60 -> 338.6 | EB60: =+DZ60/O60 -> 0.13179487 | EC60: 46076 | ED60: =+DZ60*1.15 -> 59.11 | EE60: CPC | EF60: =+EG60/DX60 -> 0.17584615 | EG60: =+EN60 -> 762 | EH60: =IFERROR((+DZ60/EG60*1000),"") -> 67.454068 | EI60: =IFERROR(+DZ60/EO60,"") | EJ60: =+IFERROR(+DZ60/EN60,"") -> 0.067454068 | EK60: =IFERROR(+(+DZ60/EP60*1000),"") -> 1.3119273 | EN60: 762 | EP60: 39179 | EQ60: =+IFERROR(+EN60/EP60,"") -> 0.019449195 | ER60: =IFERROR(+EO60/EP60,"") -> 0 | ET60: EN PAUTA
D61: ESTABLECIMIENTO 3: POLIMUNDO | E61: META | F61: VIDEO AD /REEL/ESTÁTICO | H61: RMK COMPORTAMIENTO DE VISUALIZACION LAYER 02 | I61: POR DEFINIR | J61: CPC | K61: =+N61/$N$84 -> 0.016450142 | M61: =+N61 -> 502.27 | N61: 502.27 | O61: =N61/1.15 -> 436.75652 | R61: 502.27 | AZ61: =+N61/3 -> 167.42333 | BK61: =+N61/3 -> 167.42333 | CP61: =+N61/3 -> 167.42333 | DW61: 0.05 | DX61: =O61/DW61 -> 8735.1304 | DZ61: 36.9 | EA61: =+O61-DZ61 -> 399.85652 | EB61: =+DZ61/O61 -> 0.084486432 | EC61: 46076 | ED61: =+DZ61*1.15 -> 42.435 | EE61: CPC | EF61: =+EG61/DX61 -> 0.10635216 | EG61: =+EN61 -> 929 | EH61: =IFERROR((+DZ61/EG61*1000),"") -> 39.720129 | EI61: =IFERROR(+DZ61/EO61,"") -> 0.0047114402 | EJ61: =+IFERROR(+DZ61/EN61,"") -> 0.039720129 | EK61: =IFERROR(+(+DZ61/EP61*1000),"") -> 1.1724335 | EL61: 12050 | EM61: 2.61 | EN61: 929 | EO61: 7832 | EP61: 31473 | EQ61: =+IFERROR(+EN61/EP61,"") -> 0.029517364 | ER61: =IFERROR(+EO61/EP61,"") -> 0.24884822 | ES61: JOB:DCEEA5A10068_MKT:MKT0022145_MARCA:DC_PLATAFORMA:META_FECHA:18022026_CAMPAÑA:VACCOSTA2026_ETAPA:LAYER03_COMPRA:CPC_COMUNICACION:VIAJES_ESTABLECIMIENTO:POLIMUNDO_FORMATO:VIDEOAD/REEL/ESTATICO_AUDIENCIA:VIEWSVIAJES | ET61: EN PAUTA
E62: GOOGLE | F62: DEMAND GEN | H62: BASE SOCIOS DINERS REGION COSTA | I62: POR DEFINIR | J62: CPC | K62: =+N62/$N$84 -> 0.013411777 | M62: =+N62 -> 409.5 | N62: 409.5 | O62: =N62/1.05 -> 390 | R62: 409.5 | AU62: =+N62/3 -> 136.5 | BK62: =+N62/3 -> 136.5 | CP62: =+N62/3 -> 136.5 | DW62: 0.09 | DX62: =O62/DW62 -> 4333.3333 | DZ62: 49.92 | EA62: =+O62-DZ62 -> 340.08 | EB62: =+DZ62/O62 -> 0.128 | EC62: 46076 | ED62: =+DZ62*1.15 -> 57.408 | EE62: CPC | EF62: =+EG62/DX62 -> 0.16915385 | EG62: =+EN62 -> 733 | EH62: =IFERROR((+DZ62/EG62*1000),"") -> 68.103683 | EI62: =IFERROR(+DZ62/EO62,"") | EJ62: =+IFERROR(+DZ62/EN62,"") -> 0.068103683 | EK62: =IFERROR(+(+DZ62/EP62*1000),"") -> 2.1288754 | EN62: 733 | EP62: 23449 | EQ62: =+IFERROR(+EN62/EP62,"") -> 0.031259329 | ER62: =IFERROR(+EO62/EP62,"") -> 0 | ET62: EN PAUTA
D63: ESTABLECIMIENTO 4: SOL CARIBE | E63: META | F63: VIDEO AD /REEL/ESTÁTICO | H63: RMK COMPORTAMIENTO DE VISUALIZACION LAYER 02 | I63: POR DEFINIR | J63: CPC | K63: =+N63/$N$84 -> 0.016450142 | M63: =+N63 -> 502.27 | N63: 502.27 | O63: =N63/1.15 -> 436.75652 | R63: 502.27 | AZ63: =+N63/3 -> 167.42333 | BK63: =+N63/3 -> 167.42333 | CP63: =+N63/3 -> 167.42333 | DW63: 0.05 | DX63: =O63/DW63 -> 8735.1304 | DZ63: 35.29 | EA63: =+O63-DZ63 -> 401.46652 | EB63: =+DZ63/O63 -> 0.080800167 | EC63: 46076 | ED63: =+DZ63*1.15 -> 40.5835 | EE63: CPC | EF63: =+EG63/DX63 -> 0.09719374 | EG63: =+EN63 -> 849 | EH63: =IFERROR((+DZ63/EG63*1000),"") -> 41.566549 | EI63: =IFERROR(+DZ63/EO63,"") -> 0.0040507346 | EJ63: =+IFERROR(+DZ63/EN63,"") -> 0.041566549 | EK63: =IFERROR(+(+DZ63/EP63*1000),"") -> 1.2770962 | EL63: 9482 | EM63: 2.91 | EN63: 849 | EO63: 8712 | EP63: 27633 | EQ63: =+IFERROR(+EN63/EP63,"") -> 0.030724134 | ER63: =IFERROR(+EO63/EP63,"") -> 0.31527521 | ES63: JOB:DCEEA5A10068_MKT:MKT0022145_MARCA:DC_PLATAFORMA:META_FECHA:18022026_CAMPAÑA:VACCOSTA2026_ETAPA:LAYER03_COMPRA:CPC_COMUNICACION:VIAJES_ESTABLECIMIENTO:SOLCARIBE_FORMATO:VIDEOAD/REEL/ESTATICO_AUDIENCIA:VIEWSVIAJES | ET63: EN PAUTA
E64: GOOGLE | F64: DEMAND GEN | H64: BASE SOCIOS DINERS REGION COSTA | I64: POR DEFINIR | J64: CPC | K64: =+N64/$N$84 -> 0.013411777 | M64: =+N64 -> 409.5 | N64: 409.5 | O64: =N64/1.05 -> 390 | R64: 409.5 | AU64: =+N64/3 -> 136.5 | BK64: =+N64/3 -> 136.5 | CP64: =+N64/3 -> 136.5 | DW64: 0.09 | DX64: =O64/DW64 -> 4333.3333 | DZ64: 50.92 | EA64: =+O64-DZ64 -> 339.08 | EB64: =+DZ64/O64 -> 0.1305641 | EC64: 46076 | ED64: =+DZ64*1.15 -> 58.558 | EE64: CPC | EF64: =+EG64/DX64 -> 0.22176923 | EG64: =+EN64 -> 961 | EH64: =IFERROR((+DZ64/EG64*1000),"") -> 52.986472 | EI64: =IFERROR(+DZ64/EO64,"") | EJ64: =+IFERROR(+DZ64/EN64,"") -> 0.052986472 | EK64: =IFERROR(+(+DZ64/EP64*1000),"") -> 1.1121061 | EN64: 961 | EP64: 45787 | EQ64: =+IFERROR(+EN64/EP64,"") -> 0.02098849 | ER64: =IFERROR(+EO64/EP64,"") -> 0 | ET64: EN PAUTA
C65: LAYER 03 HOTELES | D65: ESTABLECIMIENTO 1: FINCHBAY | E65: META | F65: VIDEO AD /REEL/ESTÁTICO | G65: HOTELES | H65: RMK COMPORTAMIENTO DE VISUALIZACION LAYER 02 | I65: POR DEFINIR | J65: CPC | K65: =+N65/$N$84 -> 0.016450142 | M65: =+N65 -> 502.27 | N65: 502.27 | O65: =N65/1.15 -> 436.75652 | R65: 502.27 | AZ65: =+N65/3 -> 167.42333 | BK65: =+N65/3 -> 167.42333 | CP65: =+N65/3 -> 167.42333 | DW65: 0.05 | DX65: =O65/DW65 -> 8735.1304 | DZ65: 35.96 | EA65: =+O65-DZ65 -> 400.79652 | EB65: =+DZ65/O65 -> 0.082334203 | EC65: 46076 | ED65: =+DZ65*1.15 -> 41.354 | EE65: CPC | EF65: =+EG65/DX65 -> 0.11631194 | EG65: =+EN65 -> 1016 | EH65: =IFERROR((+DZ65/EG65*1000),"") -> 35.393701 | EI65: =IFERROR(+DZ65/EO65,"") -> 0.0030056837 | EJ65: =+IFERROR(+DZ65/EN65,"") -> 0.035393701 | EK65: =IFERROR(+(+DZ65/EP65*1000),"") -> 0.82333547 | EL65: 17324 | EM65: 2.52 | EN65: 1016 | EO65: 11964 | EP65: 43676 | EQ65: =+IFERROR(+EN65/EP65,"") -> 0.023262203 | ER65: =IFERROR(+EO65/EP65,"") -> 0.27392618 | ES65: JOB:DCEEA5A10068_MKT:MKT0022145_MARCA:DC_PLATAFORMA:META_FECHA:18022026_CAMPAÑA:VACCOSTA2026_ETAPA:LAYER03_COMPRA:CPC_COMUNICACION:VIAJES_FORMATO:VIDEOADREEL/ESTATICO | ET65: EN PAUTA
E66: GOOGLE | F66: DEMAND GEN | H66: BASE SOCIOS DINERS REGION COSTA | I66: POR DEFINIR | J66: CPC | K66: =+N66/$N$84 -> 0.013411777 | M66: =+N66 -> 409.5 | N66: 409.5 | O66: =N66/1.05 -> 390 | R66: 409.5 | AU66: =+N66/3 -> 136.5 | BK66: =+N66/3 -> 136.5 | CP66: =+N66/3 -> 136.5 | DW66: 0.09 | DX66: =O66/DW66 -> 4333.3333 | DZ66: 51.01 | EA66: =+O66-DZ66 -> 338.99 | EB66: =+DZ66/O66 -> 0.13079487 | EC66: 46076 | ED66: =+DZ66*1.15 -> 58.6615 | EE66: CPC | EF66: =+EG66/DX66 -> 0.21738462 | EG66: =+EN66 -> 942 | EH66: =IFERROR((+DZ66/EG66*1000),"") -> 54.150743 | EI66: =IFERROR(+DZ66/EO66,"") | EJ66: =+IFERROR(+DZ66/EN66,"") -> 0.054150743 | EK66: =IFERROR(+(+DZ66/EP66*1000),"") -> 1.4727451 | EN66: 942 | EP66: 34636 | EQ66: =+IFERROR(+EN66/EP66,"") -> 0.027197136 | ER66: =IFERROR(+EO66/EP66,"") -> 0 | ES66: JOB:DCEEA5A10068_MKT:MKT0022145_MARCA:DC_PLATAFORMA:GOOGLE_FECHA:13022026_CAMPAÑA:VACCOSTA2026_ETAPA:LAYER03_COMPRA:CPC_COMUNICACION:HOTELES_ESTABLECIMIENTO:ITZA_FORMATO:DEMANDGEN_AUDIENCIA_BASESOCIOS | ET66: EN PAUTA
D67: ESTABLECIMIENTO 2: LA CIÉNEGA | E67: META | F67: VIDEO AD /REEL/ESTÁTICO | H67: RMK COMPORTAMIENTO DE VISUALIZACION LAYER 02 | I67: POR DEFINIR | J67: CPC | K67: =+N67/$N$84 -> 0.016450142 | M67: =+N67 -> 502.27 | N67: 502.27 | O67: =N67/1.15 -> 436.75652 | R67: 502.27 | AZ67: =+N67/3 -> 167.42333 | BK67: =+N67/3 -> 167.42333 | CP67: =+N67/3 -> 167.42333 | DW67: 0.05 | DX67: =O67/DW67 -> 8735.1304 | DZ67: 36.99 | EA67: =+O67-DZ67 -> 399.76652 | EB67: =+DZ67/O67 -> 0.084692496 | EC67: 46076 | ED67: =+DZ67*1.15 -> 42.5385 | EE67: CPC | EF67: =+EG67/DX67 -> 0.12718757 | EG67: =+EN67 -> 1111 | EH67: =IFERROR((+DZ67/EG67*1000),"") -> 33.294329 | EI67: =IFERROR(+DZ67/EO67,"") -> 0.0031060542 | EJ67: =+IFERROR(+DZ67/EN67,"") -> 0.033294329 | EK67: =IFERROR(+(+DZ67/EP67*1000),"") -> 0.69328085 | EL67: 17969 | EM67: 2.97 | EN67: 1111 | EO67: 11909 | EP67: 53355 | EQ67: =+IFERROR(+EN67/EP67,"") -> 0.020822791 | ER67: =IFERROR(+EO67/EP67,"") -> 0.22320307 | ES67: JOB:DCEEA5A10068_MKT:MKT0022145_MARCA:DC_PLATAFORMA:META_FECHA:18022026_CAMPAÑA:VACCOSTA2026_ETAPA:LAYER03_COMPRA:CPC_COMUNICACION:VIAJES_FORMATO:VIDEOADREEL/ESTATICO | ET67: EN PAUTA
E68: GOOGLE | F68: DEMAND GEN | H68: BASE SOCIOS DINERS REGION COSTA | I68: POR DEFINIR | J68: CPC | K68: =+N68/$N$84 -> 0.013411777 | M68: =+N68 -> 409.5 | N68: 409.5 | O68: =N68/1.05 -> 390 | R68: 409.5 | AU68: =+N68/3 -> 136.5 | BK68: =+N68/3 -> 136.5 | CP68: =+N68/3 -> 136.5 | DW68: 0.09 | DX68: =O68/DW68 -> 4333.3333 | DZ68: 50.97 | EA68: =+O68-DZ68 -> 339.03 | EB68: =+DZ68/O68 -> 0.13069231 | EC68: 46076 | ED68: =+DZ68*1.15 -> 58.6155 | EE68: CPC | EF68: =+EG68/DX68 -> 0.20792308 | EG68: =+EN68 -> 901 | EH68: =IFERROR((+DZ68/EG68*1000),"") -> 56.570477 | EI68: =IFERROR(+DZ68/EO68,"") | EJ68: =+IFERROR(+DZ68/EN68,"") -> 0.056570477 | EK68: =IFERROR(+(+DZ68/EP68*1000),"") -> 0.98418583 | EN68: 901 | EP68: 51789 | EQ68: =+IFERROR(+EN68/EP68,"") -> 0.017397517 | ER68: =IFERROR(+EO68/EP68,"") -> 0 | ES68: JOB:DCEEA5A10068_MKT:MKT0022145_MARCA:DC_PLATAFORMA:GOOGLE_FECHA:13022026_CAMPAÑA:VACCOSTA2026_ETAPA:LAYER03_COMPRA:CPC_COMUNICACION:HOTELES_ESTABLECIMIENTO:TANUSURF_FORMATO:DEMANDGEN_AUDIENCIA_BASESOCIOS JOB:DCEEA5A10068_MKT:MKT0022145_MARCA:DC_PLATAFORMA:GOOGLE_FECHA:13022026_CAMPAÑA:VACCOSTA2026_ETAPA:LAYER03_COMPRA:CPC_COMUNICACION:HOTELES_ESTABLECIMIENTO:ITZA_FORMATO:DEMANDGEN_AUDIENCIA_BASESOCIOS | ET68: EN PAUTA
D69: ESTABLECIMIENTO 3: ITZA | E69: META | F69: VIDEO AD /REEL/ESTÁTICO | H69: RMK COMPORTAMIENTO DE VISUALIZACION LAYER 02 | I69: POR DEFINIR | J69: CPC | K69: =+N69/$N$84 -> 0.016450142 | M69: =+N69 -> 502.27 | N69: 502.27 | O69: =N69/1.15 -> 436.75652 | R69: 502.27 | AZ69: =+N69/3 -> 167.42333 | BK69: =+N69/3 -> 167.42333 | CP69: =+N69/3 -> 167.42333 | DW69: 0.05 | DX69: =O69/DW69 -> 8735.1304 | DZ69: 35.83 | EA69: =+O69-DZ69 -> 400.92652 | EB69: =+DZ69/O69 -> 0.082036554 | EC69: 46076 | ED69: =+DZ69*1.15 -> 41.2045 | EE69: CPC | EF69: =+EG69/DX69 -> 0.12684413 | EG69: =+EN69 -> 1108 | EH69: =IFERROR((+DZ69/EG69*1000),"") -> 32.337545 | EI69: =IFERROR(+DZ69/EO69,"") -> 0.0030089016 | EJ69: =+IFERROR(+DZ69/EN69,"") -> 0.032337545 | EK69: =IFERROR(+(+DZ69/EP69*1000),"") -> 0.69259467 | EL69: 18402 | EM69: 2.81 | EN69: 1108 | EO69: 11908 | EP69: 51733 | EQ69: =+IFERROR(+EN69/EP69,"") -> 0.021417664 | ER69: =IFERROR(+EO69/EP69,"") -> 0.2301819 | ES69: JOB:DCEEA5A10068_MKT:MKT0022145_MARCA:DC_PLATAFORMA:META_FECHA:18022026_CAMPAÑA:VACCOSTA2026_ETAPA:LAYER03_COMPRA:CPC_COMUNICACION:VIAJES_FORMATO:VIDEOADREEL/ESTATICO | ET69: EN PAUTA
E70: GOOGLE | F70: DEMAND GEN | H70: BASE SOCIOS DINERS REGION COSTA | I70: POR DEFINIR | J70: CPC | K70: =+N70/$N$84 -> 0.013411777 | M70: =+N70 -> 409.5 | N70: 409.5 | O70: =N70/1.05 -> 390 | R70: 409.5 | AU70: =+N70/3 -> 136.5 | BK70: =+N70/3 -> 136.5 | CP70: =+N70/3 -> 136.5 | DW70: 0.09 | DX70: =O70/DW70 -> 4333.3333 | DZ70: 50.9 | EA70: =+O70-DZ70 -> 339.1 | EB70: =+DZ70/O70 -> 0.13051282 | EC70: 46076 | ED70: =+DZ70*1.15 -> 58.535 | EE70: CPC | EF70: =+EG70/DX70 -> 0.22476923 | EG70: =+EN70 -> 974 | EH70: =IFERROR((+DZ70/EG70*1000),"") -> 52.258727 | EI70: =IFERROR(+DZ70/EO70,"") | EJ70: =+IFERROR(+DZ70/EN70,"") -> 0.052258727 | EK70: =IFERROR(+(+DZ70/EP70*1000),"") -> 1.589284 | EN70: 974 | EP70: 32027 | EQ70: =+IFERROR(+EN70/EP70,"") -> 0.03041184 | ER70: =IFERROR(+EO70/EP70,"") -> 0 | ES70: JOB:DCEEA5A10068_MKT:MKT0022145_MARCA:DC_PLATAFORMA:GOOGLE_FECHA:13022026_CAMPAÑA:VACCOSTA2026_ETAPA:LAYER03_COMPRA:CPC_COMUNICACION:HOTELES_ESTABLECIMIENTO:TANUSURF_FORMATO:DEMANDGEN_AUDIENCIA_BASESOCIOS JOB:DCEEA5A10068_MKT:MKT0022145_MARCA:DC_PLATAFORMA:GOOGLE_FECHA:13022026_CAMPAÑA:VACCOSTA2026_ETAPA:LAYER03_COMPRA:CPC_COMUNICACION:HOTELES_ESTABLECIMIENTO:ITZA_FORMATO:DEMANDGEN_AUDIENCIA_BASESOCIOS | ET70: EN PAUTA
D71: ESTABLECIMIENTO 4: POLYLEPSIS | E71: META | F71: VIDEO AD /REEL/ESTÁTICO | H71: RMK COMPORTAMIENTO DE VISUALIZACION LAYER 02 | I71: POR DEFINIR | J71: CPC | K71: =+N71/$N$84 -> 0.016450011 | M71: =+N71 -> 502.266 | N71: 502.266 | O71: =N71/1.15 -> 436.75304 | R71: 502.266 | AZ71: =+N71/3 -> 167.422 | BK71: =+N71/3 -> 167.422 | CP71: =+N71/3 -> 167.422 | DW71: 0.05 | DX71: =O71/DW71 -> 8735.0609 | DZ71: 37 | EA71: =+O71-DZ71 -> 399.75304 | EB71: =+DZ71/O71 -> 0.084716067 | EC71: 46076 | ED71: =+DZ71*1.15 -> 42.55 | EE71: CPC | EF71: =+EG71/DX71 -> 0.087692577 | EG71: =+EN71 -> 766 | EH71: =IFERROR((+DZ71/EG71*1000),"") -> 48.302872 | EI71: =IFERROR(+DZ71/EO71,"") -> 0.033333333 | EJ71: =+IFERROR(+DZ71/EN71,"") -> 0.048302872 | EK71: =IFERROR(+(+DZ71/EP71*1000),"") -> 1.7212505 | EL71: 10790 | EM71: 1.99 | EN71: 766 | EO71: 1110 | EP71: 21496 | EQ71: =+IFERROR(+EN71/EP71,"") -> 0.035634537 | ER71: =IFERROR(+EO71/EP71,"") -> 0.051637514 | ES71: JOB:DCEEA5A10068_MKT:MKT0022145_MARCA:DC_PLATAFORMA:META_FECHA:18022026_CAMPAÑA:VACCOSTA2026_ETAPA:LAYER03_COMPRA:CPC_COMUNICACION:VIAJES_FORMATO:VIDEOADREEL/ESTATICO | ET71: EN PAUTA
E72: GOOGLE | F72: DEMAND GEN | H72: BASE SOCIOS DINERS REGION COSTA | I72: POR DEFINIR | J72: CPC | K72: =+N72/$N$84 -> 0.013411777 | M72: =+N72 -> 409.5 | N72: 409.5 | O72: =N72/1.05 -> 390 | R72: 409.5 | AU72: =+N72/3 -> 136.5 | BK72: =+N72/3 -> 136.5 | CP72: =+N72/3 -> 136.5 | DW72: 0.09 | DX72: =O72/DW72 -> 4333.3333 | DZ72: 50.68 | EA72: =+O72-DZ72 -> 339.32 | EB72: =+DZ72/O72 -> 0.12994872 | EC72: 46076 | ED72: =+DZ72*1.15 -> 58.282 | EE72: CPC | EF72: =+EG72/DX72 -> 0.19338462 | EG72: =+EN72 -> 838 | EH72: =IFERROR((+DZ72/EG72*1000),"") -> 60.477327 | EI72: =IFERROR(+DZ72/EO72,"") | EJ72: =+IFERROR(+DZ72/EN72,"") -> 0.060477327 | EK72: =IFERROR(+(+DZ72/EP72*1000),"") -> 1.3081748 | EN72: 838 | EP72: 38741 | EQ72: =+IFERROR(+EN72/EP72,"") -> 0.02163083 | ER72: =IFERROR(+EO72/EP72,"") -> 0 | ES72: JOB:DCEEA5A10068_MKT:MKT0022145_MARCA:DC_PLATAFORMA:GOOGLE_FECHA:13022026_CAMPAÑA:VACCOSTA2026_ETAPA:LAYER03_COMPRA:CPC_COMUNICACION:HOTELES_ESTABLECIMIENTO:TANUSURF_FORMATO:DEMANDGEN_AUDIENCIA_BASESOCIOS JOB:DCEEA5A10068_MKT:MKT0022145_MARCA:DC_PLATAFORMA:GOOGLE_FECHA:13022026_CAMPAÑA:VACCOSTA2026_ETAPA:LAYER03_COMPRA:CPC_COMUNICACION:HOTELES_ESTABLECIMIENTO:ITZA_FORMATO:DEMANDGEN_AUDIENCIA_BASESOCIOS | ET72: EN PAUTA
D73: ESTABLECIMIENTO 5: TANUSURF | E73: META | F73: VIDEO AD /REEL/ESTÁTICO | H73: RMK COMPORTAMIENTO DE VISUALIZACION LAYER 02 | I73: POR DEFINIR | J73: CPC | K73: =+N73/$N$84 -> 0.016450011 | M73: =+N73 -> 502.266 | N73: 502.266 | O73: =N73/1.15 -> 436.75304 | R73: 502.266 | AZ73: =+N73/3 -> 167.422 | BK73: =+N73/3 -> 167.422 | CP73: =+N73/3 -> 167.422 | DW73: 0.05 | DX73: =O73/DW73 -> 8735.0609 | DZ73: 35.51 | EA73: =+O73-DZ73 -> 401.24304 | EB73: =+DZ73/O73 -> 0.081304528 | EC73: 46076 | ED73: =+DZ73*1.15 -> 40.8365 | EE73: CPC | EF73: =+EG73/DX73 -> 0.12753202 | EG73: =+EN73 -> 1114 | EH73: =IFERROR((+DZ73/EG73*1000),"") -> 31.876122 | EI73: =IFERROR(+DZ73/EO73,"") -> 0.0026094944 | EJ73: =+IFERROR(+DZ73/EN73,"") -> 0.031876122 | EK73: =IFERROR(+(+DZ73/EP73*1000),"") -> 0.53480527 | EL73: 19736 | EM73: 3.36 | EN73: 1114 | EO73: 13608 | EP73: 66398 | EQ73: =+IFERROR(+EN73/EP73,"") -> 0.016777614 | ER73: =IFERROR(+EO73/EP73,"") -> 0.20494593 | ES73: JOB:DCEEA5A10068_MKT:MKT0022145_MARCA:DC_PLATAFORMA:META_FECHA:18022026_CAMPAÑA:VACCOSTA2026_ETAPA:LAYER03_COMPRA:CPC_COMUNICACION:VIAJES_FORMATO:VIDEOADREEL/ESTATICO | ET73: EN PAUTA
E74: GOOGLE | F74: DEMAND GEN | H74: BASE SOCIOS DINERS REGION COSTA | I74: POR DEFINIR | J74: CPC | K74: =+N74/$N$84 -> 0.013411777 | M74: =+N74 -> 409.5 | N74: 409.5 | O74: =N74/1.05 -> 390 | R74: 409.5 | AU74: =+N74/3 -> 136.5 | BK74: =+N74/3 -> 136.5 | CP74: =+N74/3 -> 136.5 | DW74: 0.09 | DX74: =O74/DW74 -> 4333.3333 | DZ74: 50.82 | EA74: =+O74-DZ74 -> 339.18 | EB74: =+DZ74/O74 -> 0.13030769 | EC74: 46076 | ED74: =+DZ74*1.15 -> 58.443 | EE74: CPC | EF74: =+EG74/DX74 -> 0.21230769 | EG74: =+EN74 -> 920 | EH74: =IFERROR((+DZ74/EG74*1000),"") -> 55.23913 | EI74: =IFERROR(+DZ74/EO74,"") | EJ74: =+IFERROR(+DZ74/EN74,"") -> 0.05523913 | EK74: =IFERROR(+(+DZ74/EP74*1000),"") -> 1.4009649 | EN74: 920 | EP74: 36275 | EQ74: =+IFERROR(+EN74/EP74,"") -> 0.025361819 | ER74: =IFERROR(+EO74/EP74,"") -> 0 | ES74: JOB:DCEEA5A10068_MKT:MKT0022145_MARCA:DC_PLATAFORMA:GOOGLE_FECHA:13022026_CAMPAÑA:VACCOSTA2026_ETAPA:LAYER03_COMPRA:CPC_COMUNICACION:HOTELES_ESTABLECIMIENTO:TANUSURF_FORMATO:DEMANDGEN_AUDIENCIA_BASESOCIOS JOB:DCEEA5A10068_MKT:MKT0022145_MARCA:DC_PLATAFORMA:GOOGLE_FECHA:13022026_CAMPAÑA:VACCOSTA2026_ETAPA:LAYER03_COMPRA:CPC_COMUNICACION:HOTELES_ESTABLECIMIENTO:ITZA_FORMATO:DEMANDGEN_AUDIENCIA_BASESOCIOS | ET74: EN PAUTA
C75: LAYER 03 | L75: =SUM(L49:L74) -> 0 | M75: =SUM(M49:M74) -> 11853.002 | N75: =SUM(N49:N74) -> 11853.002 | O75: =SUM(O49:O74) -> 10747.828 | R75: 11853.002
C76: APP BLU DIFERIDO | D76: - | E76: META | F76: VIDEO AD /REEL/ESTÁTICO | G76: Diferir consumos internacionales. | H76: BASE SOCIOS DINERS REGION COSTA | I76: 266000 | J76: CPC | K76: =+N76/$N$84 -> 0.000177399 | M76: =+N76 -> 5.4165 | N76: 5.4165 | O76: =+N76/1.15 -> 4.71 | R76: 400 | AT76: =+N76/3 -> 1.8055 | BK76: =+N76/3 -> 1.8055 | CP76: =+N76/3 -> 1.8055 | DW76: 0.09 | DX76: =O76/DW76 -> 52.333333 | DZ76: 4.71 | EA76: =+O76-DZ76 -> 0 | EB76: =+DZ76/O76 -> 1 | EC76: 46067 | ED76: =+DZ76*1.15 -> 5.4165 | EE76: CPC | EF76: =+EG76/DX76 -> 3.6878981 | EG76: =+EN76 -> 193 | EH76: =IFERROR((+DZ76/EG76*1000),"") -> 24.404145 | EI76: =IFERROR(+DZ76/EO76,"") -> 0.005125136 | EJ76: =+IFERROR(+DZ76/EN76,"") -> 0.024404145 | EK76: =IFERROR(+(+DZ76/EP76*1000),"") -> 0.45084713 | EL76: 3917 | EM76: 2.67 | EN76: 193 | EO76: 919 | EP76: 10447 | EQ76: =+IFERROR(+EN76/EP76,"") -> 0.018474203 | ER76: =IFERROR(+EO76/EP76,"") -> 0.087967838 | ES76: JOB:DCEEA5A10068_MKT:MKT0022145_MARCA:DC_PLATAFORMA:META_FECHA:27012026_CAMPAÑA:VACCOSTA2026_ETAPA:APPBLU_COMPRA:CPC_COMUNICACION:DIFERIDO_FORMATO_VIDEOAD/REEL/ESTÁTICO_AUDIENCIA_BASESOCIOS | ET76: PAUSADO | EU76: se pausó el 13 de feb por pedido de cliente | EV76: https://bluapp.onelink.me/lZB9/rq3r79vr
C77: APP BLU DE UNA | D77: - | E77: META | F77: VIDEO AD /REEL/ESTÁTICO | G77: Pagar con deuna en los pequeños comercios (por ejemplo, los helados de las playas) | H77: BASE SOCIOS DINERS REGION COSTA | I77: 54000 | J77: CPC | K77: =+N77/$N$84 -> 0.00016835956 | M77: =+N77 -> 5.1405 | N77: 5.1405 | O77: =+N77/1.15 -> 4.47 | R77: 400 | AT77: =+N77/3 -> 1.7135 | BK77: =+N77/3 -> 1.7135 | CP77: =+N77/3 -> 1.7135 | DW77: 0.09 | DX77: =O77/DW77 -> 49.666667 | DZ77: 4.47 | EA77: =+O77-DZ77 -> 0 | EB77: =+DZ77/O77 -> 1 | EC77: 46067 | ED77: =+DZ77*1.15 -> 5.1405 | EE77: CPC | EF77: =+EG77/DX77 -> 3.3221477 | EG77: =+EN77 -> 165 | EH77: =IFERROR((+DZ77/EG77*1000),"") -> 27.090909 | EI77: =IFERROR(+DZ77/EO77,"") -> 0.0033135656 | EJ77: =+IFERROR(+DZ77/EN77,"") -> 0.027090909 | EK77: =IFERROR(+(+DZ77/EP77*1000),"") -> 0.82869855 | EL77: 4319 | EM77: 1.25 | EN77: 165 | EO77: 1349 | EP77: 5394 | EQ77: =+IFERROR(+EN77/EP77,"") -> 0.030589544 | ER77: =IFERROR(+EO77/EP77,"") -> 0.2500927 | ES77: JOB:DCEEA5A10068_MKT:MKT0022145_MARCA:DC_PLATAFORMA:META_FECHA:27012026_CAMPAÑA:VACCOSTA2026_ETAPA:APPBLJOB:DCEEA5A10068_MKT:MKT0022145_MARCA:DC_PLATAFORMA:META_FECHA:12022026_CAMPAÑA:VACCOSTA2026_ETAPA:APPBLU_COMPRA:CPC_COMUNICACION:DEUNA_FORMATO_VIDEOAD/REEL/ESTÁTICO_AUDIENCIA_BASESOCIOS | ET77: PAUSADO | EU77: se pausó el 13 de feb por pedido de cliente | EV77: https://bluapp.onelink.me/lZB9/rq3r79vr
C78: APP BLU NUMERO TARJETA | D78: - | E78: META | F78: VIDEO AD /REEL/ESTÁTICO | G78: Encuentras el número, mes de caducidad y CVV de tu tarjeta | H78: BASE SOCIOS DINERS REGION COSTA | I78: 266000 | J78: CPC | K78: =+N78/$N$84 -> 0.00011223971 | M78: =+N78 -> 3.427 | N78: 3.427 | O78: =+N78/1.15 -> 2.98 | R78: 400 | AT78: =+N78/3 -> 1.1423333 | BK78: =+N78/3 -> 1.1423333 | CP78: =+N78/3 -> 1.1423333 | DW78: 0.09 | DX78: =O78/DW78 -> 33.111111 | DZ78: 2.98 | EA78: =+O78-DZ78 -> 0 | EB78: =+DZ78/O78 -> 1 | EC78: 46067 | ED78: =+DZ78*1.15 -> 3.427 | EE78: CPC | EF78: =+EG78/DX78 -> 2.8087248 | EG78: =+EN78 -> 93 | EH78: =IFERROR((+DZ78/EG78*1000),"") -> 32.043011 | EI78: =IFERROR(+DZ78/EO78,"") -> 0.0046058733 | EJ78: =+IFERROR(+DZ78/EN78,"") -> 0.032043011 | EK78: =IFERROR(+(+DZ78/EP78*1000),"") -> 1.0067568 | EL78: 2518 | EM78: 1.18 | EN78: 93 | EO78: 647 | EP78: 2960 | EQ78: =+IFERROR(+EN78/EP78,"") -> 0.031418919 | ER78: =IFERROR(+EO78/EP78,"") -> 0.21858108 | ES78: JOB:DCEEA5A10068_MKT:MKT0022145_MARCA:DC_PLATAFORMA:META_FECHA:27012026_CAMPAÑA:VACCOSTA2026_ETAPA:APPBLJOB:DCEEA5A10068_MKT:MKT0022145_MARCA:DC_PLATAFORMA:META_FECHA:12022026_CAMPAÑA:VACCOSTA2026_ETAPA:APPBLU_COMPRA:CPC_COMUNICACION:TARJETA_FORMATO_VIDEOAD/REEL/ESTÁTICO_AUDIENCIA_BASESOCIOS | ET78: PAUSADO | EU78: se pausó el 13 de feb por pedido de cliente | EV78: https://bluapp.onelink.me/lZB9/rq3r79vr
C79: APP BLU CONSULTA TUS MOVIMIENTOS | D79: - | E79: META | F79: VIDEO AD /REEL/ESTÁTICO | G79: Consulta tus movimientos cuando quieras | H79: BASE SOCIOS DINERS REGION COSTA | I79: 54000 | J79: CPC | K79: =+N79/$N$84 -> 0.0002086604 | M79: =+N79 -> 6.371 | N79: 6.371 | O79: =+N79/1.15 -> 5.54 | R79: 400 | AT79: =+N79/3 -> 2.1236667 | BK79: =+N79/3 -> 2.1236667 | CP79: =+N79/3 -> 2.1236667 | DW79: 0.09 | DX79: =O79/DW79 -> 61.555556 | DZ79: 5.54 | EA79: =+O79-DZ79 -> 0 | EB79: =+DZ79/O79 -> 1 | EC79: 46067 | ED79: =+DZ79*1.15 -> 6.371 | EE79: CPC | EF79: =+EG79/DX79 -> 4.9873646 | EG79: =+EN79 -> 307 | EH79: =IFERROR((+DZ79/EG79*1000),"") -> 18.045603 | EI79: =IFERROR(+DZ79/EO79,"") -> 0.011737288 | EJ79: =+IFERROR(+DZ79/EN79,"") -> 0.018045603 | EK79: =IFERROR(+(+DZ79/EP79*1000),"") -> 1.0761461 | EL79: 4206 | EM79: 1.22 | EN79: 307 | EO79: 472 | EP79: 5148 | EQ79: =+IFERROR(+EN79/EP79,"") -> 0.05963481 | ER79: =IFERROR(+EO79/EP79,"") -> 0.091686092 | ES79: JOB:DCEEA5A10068_MKT:MKT0022145_MARCA:DC_PLATAFORMA:META_FECHA:12022026_CAMPAÑA:VACCOSTA2026_ETAPA:APPBLU_COMPRA:CPC_COMUNICACION:CONSULTA_FORMATO_VIDEOAD/REEL/ESTÁTICO_AUDIENCIA_BASESOCIOS | ET79: PAUSADO | EU79: se pausó el 13 de feb por pedido de cliente | EV79: https://bluapp.onelink.me/lZB9/rq3r79vr
C80: APP BLU | L80: =SUM(L76:L79) -> 0 | M80: =SUM(M76:M79) -> 20.355 | N80: =SUM(N76:N79) -> 20.355 | O80: =SUM(O76:O79) -> 17.7 | R80: 1600
C81: DE UNA | D81: - | E81: META | F81: POST AD/STORY | G81: Tu duiners llega a todas partes, de una | H81: BASE SOCIOS DINERS NACIONAL | I81: 266000 | J81: CPM | M81: =+N81 -> 499.1 | N81: 499.1 | O81: =N81/1.15 -> 434 | R81: =434.782608695652*1.15 -> 500 | AT81: =+N81 -> 499.1 | DW81: 0.05 | DX81: =O81/DW81*1000 -> 8680000 | DZ81: 434 | EA81: =+O81-DZ81 -> 0 | EB81: =+DZ81/O81 -> 1 | EC81: 46073 | ED81: =+DZ81*1.15 -> 499.1 | EE81: =J81 -> CPM | EF81: =+EG81/DX81 -> 0.13854816 | EG81: =+EP81 -> 1202598 | EH81: =IFERROR((+DZ81/EG81*1000),"") -> 0.36088535 | EI81: =IFERROR(+DZ81/EO81,"") | EJ81: =+IFERROR(+DZ81/EN81,"") -> 0.26658477 | EK81: =IFERROR(+(+DZ81/EP81*1000),"") -> 0.36088535 | EL81: 185180 | EM81: 6.49 | EN81: 1628 | EO81: - | EP81: 1202598 | EQ81: =+IFERROR(+EN81/EP81,"") -> 0.0013537358 | ER81: =IFERROR(+EO81/EP81,"") | ES81: JOB:DCEEA5A10068_MKT:MKT0022145_MARCA:DC_PLATAFORMA:META_FECHA:12022026_CAMPAÑA:VACCOSTA2026_ETAPA:DEUNA_COMPRA:CPM_COMUNICACION:DEUNA_FORMATO:POSTAD/STORY | ET81: FINALIZADO | EV81: https://bluapp.onelink.me/lZB9/n841tnfg
D82: - | E82: GOOGLE | F82: DEMAND GEN | G82: Tu duiners llega a todas partes, de una | H82: BASE SOCIOS DINERS NACIONAL | I82: 54000 | J82: CPC | M82: =+N82 -> 296.5095 | N82: 296.5095 | O82: =N82/1.05 -> 282.39 | R82: =285.714285714286*1.05 -> 300 | AT82: =+N82 -> 296.5095 | DW82: 0.09 | DX82: =O82/DW82 -> 3137.6667 | DZ82: 282.39 | EA82: =+O82-DZ82 -> 0 | EB82: =+DZ82/O82 -> 1 | EC82: 46073 | ED82: =+DZ82*1.05 -> 296.5095 | EE82: =J82 -> CPC | EF82: =+EG82/DX82 -> 1.3363434 | EG82: =+EN82 -> 4193 | EH82: =IFERROR((+DZ82/EG82*1000),"") -> 67.347961 | EI82: =IFERROR(+DZ82/EO82,"") | EJ82: =+IFERROR(+DZ82/EN82,"") -> 0.067347961 | EK82: =IFERROR(+(+DZ82/EP82*1000),"") -> 1.5315652 | EN82: 4193 | EP82: 184380 | EQ82: =+IFERROR(+EN82/EP82,"") -> 0.022741078 | ER82: =IFERROR(+EO82/EP82,"") -> 0 | ES82: JOB:DCEEA5A10068_MKT:MKT0022145_MARCA:DC_PLATAFORMA:GOOGLE_FECHA:12022026_CAMPAÑA:VACCOSTA2026_ETAPA:DEUNA_COMPRA:CPC_COMUNICACION:DEUNA_FORMATO:DEMANDGEN_AUDIENCIA_BASESOCIOS | ET82: FINALIZADO
C83: =C81 -> DE UNA | L83: =SUM(L78:L82) -> 0 | M83: =SUM(M78:M82) -> 825.7625 | N83: =+N82+N81 -> 795.6095 | O83: =SUM(O81:O82) -> 716.39 | R83: =R82+R81 -> 800
C84: TOTAL MEDIOS CAMPAÑA | L84: =+L80+L75+L48+L17 -> 5758.3415 | M84: =+M80+M75+M48+M17 -> 16778.915 | N84: =+N75+N48+N23+N80+N83 -> 30532.866 | O84: =+O75+O48+O23+O80+O83 -> 27825.946
C85: FEE DE MEDIOS | L85: =+L84*20% -> 1151.6683 | M85: =+M84*20% -> 3355.7831 | N85: =+N84*20% -> 6106.5733 | O85: =+O84*20% -> 5565.1892
C86: FEE PRIMICIAS | L86: =+N86-M86 -> 3328.8434 | M86: =+M85*20% -> 671.15661 | N86: =+N95 -> 4000 | O86: 1760 | EN86: 42883 | EP86: 1757310
C87: SUBTOTAL PAUTA + FEE | L87: =SUM(L84:L86) -> 10238.853 | M87: =SUM(M84:M86) -> 20805.855 | N87: =SUM(N84:N86) -> 40639.44 | O87: =SUM(O84:O86) -> 35151.135 | EN87: =EN86/EP86 -> 0.024402638
C88: IVA | L88: =+L87*15% -> 1535.828 | M88: =+M87*15% -> 3120.8782 | N88: =+N87*15% -> 6095.9159 | O88: =+O87*15% -> 5272.6703
C89: TOTAL MEDIOS CAMPAÑA | L89: =+L87+L88 -> 11774.681 | M89: =+M87+M88 -> 23926.733 | N89: =+N87+N88 -> 46735.356 | O89: =+O87+O88 -> 40423.806
C91: PRIMICIAS
E92: PRIMICIAS | F92: 3 TAKEOVER (viajes, hoteles y aerolíneas) | H92: AUDIENCIA MEDIO IP SOLO GUAYAQUIL | I92: 110000 | J92: COMPRA FIJA | N92: 7000 | O92: 1900 | BK92: =N92 -> 7000
E93: PRIMICIAS | F93: TOMA RRSS | H93: AUDIENCIA MEDIO IP SOLO GUAYAQUIL | I93: 110000 | J93: COMPRA FIJA | N93: 5500 | O93: 1900 | AI93: =N93 -> 5500
C94: TOTAL CARGO PRECOMPRA | N94: =+N93+N92 -> 12500 | O94: =+O93+O92 -> 3800
C95: FEE DE MEDIOS | N95: 4000 | O95: =+O94*20% -> 760
C96: SUBTOTAL PAUTA + FEE | N96: =+N94+N95 -> 16500 | O96: =+O94+O95 -> 4560
C97: IVA | N97: =+N96*15% -> 2475 | O97: =+O96*15% -> 684
C98: TOTAL MEDIOS CAMPAÑA | N98: =+N97+N96 -> 18975 | O98: =+O97+O96 -> 5244
EV99: https://www.dinersclub.com.ec/blubenefits/?utm_source=PRIMICIAS&utm_medium=CPM&utm_campaign=DINERS-VACCOSTA-2026-MKT0022145&utm_id=DINERS-VACCOSTA-2026-MKT0022145&utm_term=DINERS-VACCOSTA-2026-MKT0022145&utm_content=PRIMICIAS
I109: 10758

Sheet SHARE
C3: VAC COSTA 2026
C5: TOTAL ICLUIDO FEE - DIGITAL | F5: 24600
C6: TOTAL ICLUIDO FEE | F6: 80000
F8: TOTAL + FEE
C9: AWARENESS | F9: =+F6+F5 -> 104600
C10: TELEVISION | E10: =+'FLOW MEDIOS'!X10 -> 45620 | F10: =+E10/F9 -> 0.43613767
C11: DIGITAL | E11: 34460 | F11: =+E11/F9 -> 0.32944551
C12: VIA PÚBLICA | E12: =+'FLOW MEDIOS'!X13 -> 13000 | F12: =+E12/F9 -> 0.12428298
C13: RADIO | F13: =+E13/F9 -> 0
C14: PANTALLAS LED | F14: =+E14/F9 -> 0
C15: REVISTA | E15: =+F9*F15 -> 0 | F15: 0
C16: CINE | E16: =+F9*F16 -> 0 | F16: 0
C17: TOTAL | D17: =SUM(D16:D16) -> 0 | E17: =SUM(E10:E16) -> 93080 | F17: =SUM(F10:F16) -> 0.88986616
E19: =+F9-E17 -> 11520
C21: TELEVISIÓN
C22: ECUAVISA | D22: 27600
C23: TC | D23: 18000
D24: =+D22+D23 -> 45600
C28: SHARE DIGITAL
C29: TOTAL | D29: =+E11 -> 34460
C30: FEE PRIMICIAS | D30: 2500
C31: SUBTOTAL | D31: =+D29-D30 -> 31960
C32: INVERSION ANTES DE FEE | D32: =+D31/1.2 -> 26633.333

Sheet PAUTA TELEVISIÓN OP1 
C3: CLIENTE: | D3: BANCO DINERS DEL ECUADOR
C4: PRODUCTO: | D4: DINERS CLUB | K4: PAUTA DE TELEVISIÓN
C5: CAMPAÑA: | D5: VAC COSTA
C6: TARGET: | D6: PERSONAS AB
K7: 1 | R7: 2 | Y7: 3 | AF7: 4 | AM7: 5 | AT7: 6 | BA7: 6 | BH7: 7 | BO7: 9 | BV7: 10 | CH7: =CH8/CJ8 -> 0.57213533 | CI7: =CI8/CJ8 -> 0.42786467 | CJ7: UNIV
K8: ENERO | X8: FEBRERO | AY8: MARZO | CH8: 1246660 | CI8: 932300 | CJ8: 2178960
C9: PROGRAMA | D9: HORA | E9: GENERO | F9: DÍAS | G9: FRANJA | H9: MENSAJE | I9: FORMATO | J9: SEG | K9: L | L9: M | M9: X | N9: J | O9: V | P9: S | Q9: D | R9: L | S9: M | T9: X | U9: J | V9: V | W9: S | X9: D | Y9: L | Z9: M | AA9: X | AB9: J | AC9: V | AD9: S | AE9: D | AF9: L | AG9: M | AH9: X | AI9: J | AJ9: V | AK9: S | AL9: D | AM9: L | AN9: M | AO9: X | AP9: J | AQ9: V | AR9: S | AS9: D | AT9: L | AU9: M | AV9: X | AW9: J | AX9: V | AY9: S | AZ9: D | BA9: L | BB9: M | BC9: X | BD9: J | BE9: V | BF9: S | BG9: D | BH9: L | BI9: M | BJ9: X | BK9: J | BL9: V | BM9: S | BN9: D | BO9: L | BP9: M | BQ9: X | BR9: J | BS9: V | BT9: S | BU9: D | BV9: L | BW9: M | BX9: X | BY9: J | BZ9: V | CA9: S | CB9: D | CC9: L | CD9: TOTAL | CE9: Rtg Personas AB | CH9: Trp´s Personas AB | CM9: TARIFA REAL | CO9: TARIFA NEG | CP9: INVERSIÓN REAL | CQ9: INVERSIÓN NEGOCIADA | CR9: Costo Trp´s | CT9: AWARENESS | CV9: MOVILIZACIÓN
K10: 19 | L10: =K10+1 -> 20 | M10: =L10+1 -> 21 | N10: =M10+1 -> 22 | O10: =N10+1 -> 23 | P10: =O10+1 -> 24 | Q10: =P10+1 -> 25 | R10: =Q10+1 -> 26 | S10: =R10+1 -> 27 | ... V10: =U10+1 -> 30 | W10: 31 | X10: 1 | Y10: =X10+1 -> 2 | Z10: =Y10+1 -> 3 | AA10: =Z10+1 -> 4 | AB10: =AA10+1 -> 5 | AC10: =AB10+1 -> 6 | AD10: =AC10+1 -> 7 | AE10: =AD10+1 -> 8 | AF10: =AE10+1 -> 9 | ... AX10: =AW10+1 -> 27 | AY10: 1 | AZ10: =AY10+1 -> 2 | BA10: =AZ10+1 -> 3 | BB10: =BA10+1 -> 4 | BC10: =BB10+1 -> 5 | BD10: =BC10+1 -> 6 | BE10: =BD10+1 -> 7 | BF10: =BE10+1 -> 8 | BG10: =BF10+1 -> 9 | ... CC10: =CB10+1 -> 31 | CD10: CUÑAS | CE10: UIO | CF10: GYE | CG10: NAC | CH10: UIO | CI10: GYE | CJ10: NAC | CT10: ENERO | CU10: FEBRERO | CV10: FEBRERO 20SEG | CX10: 1 | DA10: 2 | DD10: 3 | DG10: 4 | DJ10: 5 | DM10: 6 | DP10: 7
C11: ECUAVISA 8 - QUITO | AM11: FERIADO | CX11: UIO | CY11: GYE | CZ11: NAC | DA11: UIO | DB11: GYE | DC11: NAC | DD11: UIO | DE11: GYE | DF11: NAC | DG11: UIO | DH11: GYE | DI11: NAC | DJ11: UIO | DK11: GYE | DL11: NAC | DM11: UIO | DN11: GYE | DO11: NAC | DP11: UIO | DQ11: GYE | DR11: NAC
C12: TELEVISTAZO AL AMANECER | D12: 0.25 | E12: NOTICIERO | F12: LMWJV | G12: =IF(D12<=0.541,"DAY",(IF(D12<=0.74930556,"EARLY",(IF(D12<=0.97916667,"PRIME","LATE"))))) -> DAY | H12: AWARENESS | I12: SPOT | J12: 40 | K12: 1 | M12: 1 | R12: 1 | T12: 1 | V12: 1 | CD12: =SUM(K12:CC12) -> 5 | CE12: 2.7 | CG12: =(CE12*$CH$7)+(CF12*$CI$7) -> 1.5447654 | CH12: =+CD12*CE12 -> 13.5 | CI12: =+CD12*CF12 -> 0 | CJ12: =CD12*CG12 -> 7.723827 | CK12: =2673/2 -> 1336.5 | CL12: =2673/2 -> 1336.5 | CM12: =CL12/30*J12 -> 1782 | CO12: 345 | CP12: =CM12*CD12 -> 8910 | CQ12: =CO12*CD12 -> 1725 | CR12: =CQ12/CJ12 -> 223.33488 | CT12: =SUM(K12:W12)*CO12 -> 1725 | CU12: =SUM(X12:AX12)*CO12 -> 0 | CX12: =COUNTA(R12:X12)*$CE12 -> 8.1 | CY12: =COUNTA(R12:X12)*$CF12 -> 0 | CZ12: =COUNTA(K12:Q12)*$CG12 -> 3.0895308 | DA12: =COUNTA(Y12:AE12)*$CE12 -> 0 | DB12: =COUNTA(Y12:AE12)*$CF12 -> 0 | DC12: =COUNTA(R12:X12)*$CG12 -> 4.6342962 | DD12: =COUNTA(AF12:AL12)*$CE12 -> 0 | DE12: =COUNTA(AF12:AL12)*$CF12 -> 0 | DF12: =COUNTA(Y12:AE12)*$CG12 -> 0 | DG12: =COUNTA(AM12:AS12)*$CE12 -> 0 | DH12: =COUNTA(AM12:AS12)*$CF12 -> 0 | DI12: =COUNTA(AF12:AL12)*$CG12 -> 0 | DJ12: =COUNTA(AT12:AZ12)*$CE12 -> 0 | DK12: =COUNTA(AT12:AZ12)*$CF12 -> 0 | DL12: =COUNTA(AM12:AS12)*$CG12 -> 0 | DM12: =COUNTA(BA12:BG12)*$CE12 -> 0 | DN12: =COUNTA(BA12:BG12)*$CF12 -> 0 | DO12: =COUNTA(AT12:AX12)*$CG12 -> 0 | DP12: =COUNTA(BH12:BN12)*$CE12 -> 0 | DQ12: =COUNTA(BH12:BN12)*$CF12 -> 0 | DR12: =COUNTA(BH12:BN12)*$CG12 -> 0
C13: CONTACTO DIRECTO | D13: 0.29166667 | E13: NOTICIERO | F13: LMWJV | G13: =IF(D13<=0.541,"DAY",(IF(D13<=0.74930556,"EARLY",(IF(D13<=0.97916667,"PRIME","LATE"))))) -> DAY | H13: AWARENESS | I13: SPOT | J13: 40 | L13: 1 | N13: 1 | S13: 1 | U13: 1 | Y13: 1 | CD13: =SUM(K13:CC13) -> 5 | CE13: 2.6 | CG13: =(CE13*$CH$7)+(CF13*$CI$7) -> 1.4875519 | CH13: =+CD13*CE13 -> 13 | CI13: =+CD13*CF13 -> 0 | CJ13: =CD13*CG13 -> 7.4377593 | CK13: =(480+12)/2 -> 246 | CL13: =(480+12)/2 -> 246 | CM13: =CL13/30*J13 -> 328 | CO13: 345 | CP13: =CM13*CD13 -> 1640 | CQ13: =CO13*CD13 -> 1725 | CR13: =CQ13/CJ13 -> 231.92469 | CT13: =SUM(K13:W13)*CO13 -> 1380 | CU13: =SUM(X13:AX13)*CO13 -> 345 | CX13: =COUNTA(R13:X13)*$CE13 -> 5.2 | CY13: =COUNTA(R13:X13)*$CF13 -> 0 | CZ13: =COUNTA(K13:Q13)*$CG13 -> 2.9751037 | DA13: =COUNTA(Y13:AE13)*$CE13 -> 2.6 | DB13: =COUNTA(Y13:AE13)*$CF13 -> 0 | DC13: =COUNTA(R13:X13)*$CG13 -> 2.9751037 | DD13: =COUNTA(AF13:AL13)*$CE13 -> 0 | DE13: =COUNTA(AF13:AL13)*$CF13 -> 0 | DF13: =COUNTA(Y13:AE13)*$CG13 -> 1.4875519 | DG13: =COUNTA(AM13:AS13)*$CE13 -> 0 | DH13: =COUNTA(AM13:AS13)*$CF13 -> 0 | DI13: =COUNTA(AF13:AL13)*$CG13 -> 0 | DJ13: =COUNTA(AT13:AZ13)*$CE13 -> 0 | DK13: =COUNTA(AT13:AZ13)*$CF13 -> 0 | DL13: =COUNTA(AM13:AS13)*$CG13 -> 0 | DM13: =COUNTA(BA13:BG13)*$CE13 -> 0 | DN13: =COUNTA(BA13:BG13)*$CF13 -> 0 | DO13: =COUNTA(AT13:AX13)*$CG13 -> 0 | DP13: =COUNTA(BH13:BN13)*$CE13 -> 0 | DQ13: =COUNTA(BH13:BN13)*$CF13 -> 0 | DR13: =COUNTA(BH13:BN13)*$CG13 -> 0
C14: EN CONTACTO | D14: 0.4375 | E14: MAGAZINE | F14: LMWJV | G14: =IF(D14<=0.541,"DAY",(IF(D14<=0.74930556,"EARLY",(IF(D14<=0.97916667,"PRIME","LATE"))))) -> DAY | H14: AWARENESS | I14: MENCION | J14: 15 | M14: 1 | O14: 1 | R14: 1 | T14: 1 | CD14: =SUM(K14:CC14) -> 4 | CE14: 1.4 | CG14: =(CE14*$CH$7)+(CF14*$CI$7) -> 0.80098946 | CH14: =+CD14*CE14 -> 5.6 | CI14: =+CD14*CF14 -> 0 | CJ14: =CD14*CG14 -> 3.2039579 | CK14: =(480+12)/2 -> 246 | CL14: =(480+12)/2 -> 246 | CM14: =CL14/30*J14 -> 123 | CO14: 345 | CP14: =CM14*CD14 -> 492 | CQ14: =CO14*CD14 -> 1380 | CR14: =CQ14/CJ14 -> 430.71728 | CT14: =SUM(K14:W14)*CO14 -> 1380 | CU14: =SUM(X14:AX14)*CO14 -> 0 | CZ14: =COUNTA(K14:Q14)*$CG14 -> 1.6019789 | DC14: =COUNTA(R14:X14)*$CG14 -> 1.6019789 | DF14: =COUNTA(Y14:AE14)*$CG14 -> 0 | DI14: =COUNTA(AF14:AL14)*$CG14 -> 0 | DL14: =COUNTA(AM14:AS14)*$CG14 -> 0 | DO14: =COUNTA(AT14:AX14)*$CG14 -> 0
C15: TELEVISTAZO II | D15: 0.54166667 | E15: NOTICIERO | F15: LMWJV | G15: =IF(D15<=0.541,"DAY",(IF(D15<=0.74930556,"EARLY",(IF(D15<=0.97916667,"PRIME","LATE"))))) -> EARLY | H15: AWARENESS | I15: SPOT | J15: 40 | L15: 1 | N15: 1 | S15: 1 | V15: 1 | Z15: 1 | CD15: =SUM(K15:CC15) -> 5 | CE15: 3.6 | CG15: =(CE15*$CH$7)+(CF15*$CI$7) -> 2.0596872 | CH15: =+CD15*CE15 -> 18 | CI15: =+CD15*CF15 -> 0 | CJ15: =CD15*CG15 -> 10.298436 | CK15: =1417/2 -> 708.5 | CL15: =1417/2 -> 708.5 | CM15: =CL15/30*J15 -> 944.66667 | CO15: 345 | CP15: =CM15*CD15 -> 4723.3333 | CQ15: =CO15*CD15 -> 1725 | CR15: =CQ15/CJ15 -> 167.50116 | CT15: =SUM(K15:W15)*CO15 -> 1380 | CU15: =SUM(X15:AX15)*CO15 -> 345 | CX15: =COUNTA(R15:X15)*$CE15 -> 7.2 | CY15: =COUNTA(R15:X15)*$CF15 -> 0 | CZ15: =COUNTA(K15:Q15)*$CG15 -> 4.1193744 | DA15: =COUNTA(Y15:AE15)*$CE15 -> 3.6 | DB15: =COUNTA(Y15:AE15)*$CF15 -> 0 | DC15: =COUNTA(R15:X15)*$CG15 -> 4.1193744 | DD15: =COUNTA(AF15:AL15)*$CE15 -> 0 | DE15: =COUNTA(AF15:AL15)*$CF15 -> 0 | DF15: =COUNTA(Y15:AE15)*$CG15 -> 2.0596872 | DG15: =COUNTA(AM15:AS15)*$CE15 -> 0 | DH15: =COUNTA(AM15:AS15)*$CF15 -> 0 | DI15: =COUNTA(AF15:AL15)*$CG15 -> 0 | DJ15: =COUNTA(AT15:AZ15)*$CE15 -> 0 | DK15: =COUNTA(AT15:AZ15)*$CF15 -> 0 | DL15: =COUNTA(AM15:AS15)*$CG15 -> 0 | DM15: =COUNTA(BA15:BG15)*$CE15 -> 0 | DN15: =COUNTA(BA15:BG15)*$CF15 -> 0 | DO15: =COUNTA(AT15:AX15)*$CG15 -> 0 | DP15: =COUNTA(BH15:BN15)*$CE15 -> 0 | DQ15: =COUNTA(BH15:BN15)*$CF15 -> 0 | DR15: =COUNTA(BH15:BN15)*$CG15 -> 0
C16: TELEVISTAZO AL AMANECER | D16: 0.25 | E16: NOTICIERO | F16: LMWJV | G16: =IF(D16<=0.541,"DAY",(IF(D16<=0.74930556,"EARLY",(IF(D16<=0.97916667,"PRIME","LATE"))))) -> DAY | H16: AWARENESS | I16: SPOT | J16: 20 | AB16: 1 | AG16: 1 | AO16: 1 | AV16: 1 | CD16: =SUM(K16:CC16) -> 4 | CE16: 2.7 | CG16: =(CE16*$CH$7)+(CF16*$CI$7) -> 1.5447654 | CH16: =+CD16*CE16 -> 10.8 | CI16: =+CD16*CF16 -> 0 | CJ16: =CD16*CG16 -> 6.1790616 | CK16: =2673/2 -> 1336.5 | CL16: =2673/2 -> 1336.5 | CM16: =CL16/30*J16 -> 891 | CO16: 345 | CP16: =CM16*CD16 -> 3564 | CQ16: =CO16*CD16 -> 1380 | CR16: =CQ16/CJ16 -> 223.33488 | CS16: 27600 | CT16: =SUM(K16:W16)*CO16 -> 0 | CU16: =SUM(X16:AX16)*CO16 -> 1380 | CX16: =COUNTA(R16:X16)*$CE16 -> 0 | CY16: =COUNTA(R16:X16)*$CF16 -> 0 | CZ16: =COUNTA(K16:Q16)*$CG16 -> 0 | DA16: =COUNTA(Y16:AE16)*$CE16 -> 2.7 | DB16: =COUNTA(Y16:AE16)*$CF16 -> 0 | DC16: =COUNTA(R16:X16)*$CG16 -> 0 | DD16: =COUNTA(AF16:AL16)*$CE16 -> 2.7 | DE16: =COUNTA(AF16:AL16)*$CF16 -> 0 | DF16: =COUNTA(Y16:AE16)*$CG16 -> 1.5447654 | DG16: =COUNTA(AM16:AS16)*$CE16 -> 2.7 | DH16: =COUNTA(AM16:AS16)*$CF16 -> 0 | DI16: =COUNTA(AF16:AL16)*$CG16 -> 1.5447654 | DJ16: =COUNTA(AT16:AZ16)*$CE16 -> 2.7 | DK16: =COUNTA(AT16:AZ16)*$CF16 -> 0 | DL16: =COUNTA(AM16:AS16)*$CG16 -> 1.5447654 | DM16: =COUNTA(BA16:BG16)*$CE16 -> 0 | DN16: =COUNTA(BA16:BG16)*$CF16 -> 0 | DO16: =COUNTA(AT16:AX16)*$CG16 -> 1.5447654 | DP16: =COUNTA(BH16:BN16)*$CE16 -> 0 | DQ16: =COUNTA(BH16:BN16)*$CF16 -> 0 | DR16: =COUNTA(BH16:BN16)*$CG16 -> 0 | DT16: =+CQ20+CQ56 -> 27600
C17: TELEVISTAZO EN LA COMUNIDAD | D17: 0.3125 | E17: NOTICIERO | F17: LMWJV | G17: =IF(D17<=0.541,"DAY",(IF(D17<=0.74930556,"EARLY",(IF(D17<=0.97916667,"PRIME","LATE"))))) -> DAY | H17: AWARENESS | I17: SPOT | J17: 20 | AA17: 1 | AI17: 1 | AP17: 1 | AT17: 1 | CD17: =SUM(K17:CC17) -> 4 | CE17: 2.6 | CG17: =(CE17*$CH$7)+(CF17*$CI$7) -> 1.4875519 | CH17: =+CD17*CE17 -> 10.4 | CI17: =+CD17*CF17 -> 0 | CJ17: =CD17*CG17 -> 5.9502074 | CK17: =(480+12)/2 -> 246 | CL17: =(480+12)/2 -> 246 | CM17: =CL17/30*J17 -> 164 | CO17: 345 | CP17: =CM17*CD17 -> 656 | CQ17: =CO17*CD17 -> 1380 | CR17: =CQ17/CJ17 -> 231.92469 | CS17: =+CS16*40% -> 11040 | CT17: =SUM(K17:W17)*CO17 -> 0 | CU17: =SUM(X17:AX17)*CO17 -> 1380 | CX17: =COUNTA(R17:X17)*$CE17 -> 0 | CY17: =COUNTA(R17:X17)*$CF17 -> 0 | CZ17: =COUNTA(K17:Q17)*$CG17 -> 0 | DA17: =COUNTA(Y17:AE17)*$CE17 -> 2.6 | DB17: =COUNTA(Y17:AE17)*$CF17 -> 0 | DC17: =COUNTA(R17:X17)*$CG17 -> 0 | DD17: =COUNTA(AF17:AL17)*$CE17 -> 2.6 | DE17: =COUNTA(AF17:AL17)*$CF17 -> 0 | DF17: =COUNTA(Y17:AE17)*$CG17 -> 1.4875519 | DG17: =COUNTA(AM17:AS17)*$CE17 -> 2.6 | DH17: =COUNTA(AM17:AS17)*$CF17 -> 0 | DI17: =COUNTA(AF17:AL17)*$CG17 -> 1.4875519 | DJ17: =COUNTA(AT17:AZ17)*$CE17 -> 2.6 | DK17: =COUNTA(AT17:AZ17)*$CF17 -> 0 | DL17: =COUNTA(AM17:AS17)*$CG17 -> 1.4875519 | DM17: =COUNTA(BA17:BG17)*$CE17 -> 0 | DN17: =COUNTA(BA17:BG17)*$CF17 -> 0 | DO17: =COUNTA(AT17:AX17)*$CG17 -> 1.4875519 | DP17: =COUNTA(BH17:BN17)*$CE17 -> 0 | DQ17: =COUNTA(BH17:BN17)*$CF17 -> 0 | DR17: =COUNTA(BH17:BN17)*$CG17 -> 0 | DT17: =+CS17/32 -> 345
C18: TELEVISTAZO ESTELAR | D18: 0.79166667 | E18: NOTICIERO | F18: LMWJV | G18: =IF(D18<=0.541,"DAY",(IF(D18<=0.74930556,"EARLY",(IF(D18<=0.97916667,"PRIME","LATE"))))) -> PRIME | H18: AWARENESS | I18: SPOT | J18: 20 | AB18: 1 | AF18: 1 | AO18: 1 | AU18: 1 | CD18: =SUM(K18:CC18) -> 4 | CE18: 5.8 | CG18: =(CE18*$CH$7)+(CF18*$CI$7) -> 3.3183849 | CH18: =+CD18*CE18 -> 23.2 | CI18: =+CD18*CF18 -> 0 | CJ18: =CD18*CG18 -> 13.27354 | CK18: =1417/2 -> 708.5 | CL18: =1417/2 -> 708.5 | CM18: =CL18/30*J18 -> 472.33333 | CO18: 345 | CP18: =CM18*CD18 -> 1889.3333 | CQ18: =CO18*CD18 -> 1380 | CR18: =CQ18/CJ18 -> 103.96624 | CS18: =+CS16*60% -> 16560 | CT18: =SUM(K18:W18)*CO18 -> 0 | CU18: =SUM(X18:AX18)*CO18 -> 1380 | CX18: =COUNTA(R18:X18)*$CE18 -> 0 | CY18: =COUNTA(R18:X18)*$CF18 -> 0 | CZ18: =COUNTA(K18:Q18)*$CG18 -> 0 | DA18: =COUNTA(Y18:AE18)*$CE18 -> 5.8 | DB18: =COUNTA(Y18:AE18)*$CF18 -> 0 | DC18: =COUNTA(R18:X18)*$CG18 -> 0 | DD18: =COUNTA(AF18:AL18)*$CE18 -> 5.8 | DE18: =COUNTA(AF18:AL18)*$CF18 -> 0 | DF18: =COUNTA(Y18:AE18)*$CG18 -> 3.3183849 | DG18: =COUNTA(AM18:AS18)*$CE18 -> 5.8 | DH18: =COUNTA(AM18:AS18)*$CF18 -> 0 | DI18: =COUNTA(AF18:AL18)*$CG18 -> 3.3183849 | DJ18: =COUNTA(AT18:AZ18)*$CE18 -> 5.8 | DK18: =COUNTA(AT18:AZ18)*$CF18 -> 0 | DL18: =COUNTA(AM18:AS18)*$CG18 -> 3.3183849 | DM18: =COUNTA(BA18:BG18)*$CE18 -> 0 | DN18: =COUNTA(BA18:BG18)*$CF18 -> 0 | DO18: =COUNTA(AT18:AX18)*$CG18 -> 3.3183849 | DP18: =COUNTA(BH18:BN18)*$CE18 -> 0 | DQ18: =COUNTA(BH18:BN18)*$CF18 -> 0 | DR18: =COUNTA(BH18:BN18)*$CG18 -> 0 | DT18: =+CS18/66 -> 250.90909
C19: TELEVISTAZO (S-D) | D19: 0.79166667 | E19: NOTICIERO | F19: SD | G19: =IF(D19<=0.541,"DAY",(IF(D19<=0.74930556,"EARLY",(IF(D19<=0.97916667,"PRIME","LATE"))))) -> PRIME | H19: AWARENESS | I19: SPOT | J19: 20 | AE19: 1 | CD19: =SUM(K19:CC19) -> 1 | CE19: 5.7 | CG19: =(CE19*$CH$7)+(CF19*$CI$7) -> 3.2611714 | CH19: =+CD19*CE19 -> 5.7 | CI19: =+CD19*CF19 -> 0 | CJ19: =CD19*CG19 -> 3.2611714 | CK19: =14.8*4*I19 -> #VALUE! | CL19: =14.8*4*J19 -> 1184 | CM19: =CL19/30*J19 -> 789.33333 | CO19: 345 | CP19: =CM19*CD19 -> 789.33333 | CQ19: =CO19*CD19 -> 345 | CR19: =CQ19/CJ19 -> 105.79021 | CT19: =SUM(K19:W19)*CO19 -> 0 | CU19: =SUM(X19:AX19)*CO19 -> 345 | CX19: =COUNTA(R19:X19)*$CE19 -> 0 | CZ19: =COUNTA(K19:Q19)*$CG19 -> 0 | DC19: =COUNTA(R19:X19)*$CG19 -> 0 | DF19: =COUNTA(Y19:AE19)*$CG19 -> 3.2611714 | DI19: =COUNTA(AF19:AL19)*$CG19 -> 0 | DL19: =COUNTA(AM19:AS19)*$CG19 -> 0 | DM19: =COUNTA(BA19:BG19)*$CE19 -> 0 | DO19: =COUNTA(AT19:AX19)*$CG19 -> 0 | DP19: =COUNTA(BH19:BN19)*$CE19 -> 0
C20: TOTAL ECUAVISA 8 | K20: =SUM(K12:K19) -> 1 | L20: =SUM(L12:L19) -> 2 | M20: =SUM(M12:M19) -> 2 | N20: =SUM(N12:N19) -> 2 | O20: =SUM(O12:O19) -> 1 | P20: =SUM(P12:P19) -> 0 | Q20: =SUM(Q12:Q19) -> 0 | R20: =SUM(R12:R19) -> 2 | ... CD20: =SUM(CD12:CD19) -> 32 | CH20: =SUM(CH12:CH19) -> 100.2 | CI20: =SUM(CI12:CI19) -> 0 | CJ20: =SUM(CJ12:CJ19) -> 57.32796 | CP20: =SUM(CP12:CP19) -> 22664 | CQ20: =SUM(CQ12:CQ19) -> 11040 | CR20: =CQ20/CJ20 -> 192.57619 | CT20: =SUM(CT12:CT18) -> 5865 | CU20: =SUM(CU12:CU19) -> 5175 | CV20: =SUM(CV12:CV18) -> 0 | CX20: =SUM(CX12:CX19) -> 20.5 | CY20: =SUM(CY12:CY18) -> 0 | CZ20: =SUM(CZ12:CZ19) -> 11.785988 | DA20: =SUM(DA12:DA18) -> 17.3 | DB20: =SUM(DB12:DB18) -> 0 | DC20: =SUM(DC12:DC19) -> 13.330753 | DD20: =SUM(DD12:DD18) -> 11.1 | DE20: =SUM(DE12:DE18) -> 0 | DF20: =SUM(DF12:DF19) -> 13.159113 | DG20: =SUM(DG12:DG18) -> 11.1 | DH20: =SUM(DH12:DH18) -> 0 | DI20: =SUM(DI12:DI19) -> 6.3507022 | DJ20: =SUM(DJ12:DJ18) -> 11.1 | DK20: =SUM(DK12:DK18) -> 0 | DL20: =SUM(DL12:DL19) -> 6.3507022 | DM20: =SUM(DM12:DM19) -> 0 | DN20: =SUM(DN12:DN18) -> 0 | DO20: =SUM(DO12:DO19) -> 6.3507022 | DP20: =SUM(DP12:DP19) -> 0 | DQ20: =SUM(DQ12:DQ18) -> 0 | DR20: =SUM(DR12:DR18) -> 0
C22: ECUAVISA 2 - GUAYAQUIL | CX22: 1 | DA22: 2 | DD22: 3 | DG22: 4 | DJ22: 5 | DM22: 6 | DP22: 7
C23: TELEVISTAZO AL AMANECER | D23: 0.25 | E23: NOTICIERO | F23: LMWJV | G23: =IF(D23<=0.541,"DAY",(IF(D23<=0.74930556,"EARLY",(IF(D23<=0.97916667,"PRIME","LATE"))))) -> DAY | H23: AWARENESS | I23: SPOT | J23: 40 | K23: 1 | M23: 1 | R23: 1 | T23: 1 | V23: 1 | CD23: =SUM(K23:CC23) -> 5 | CF23: 2.5 | CG23: =(CE23*$CH$7)+(CF23*$CI$7) -> 1.0696617 | CH23: =+CD23*CE23 -> 0 | CI23: =+CD23*CF23 -> 12.5 | CJ23: =CD23*CG23 -> 5.3483084 | CK23: =13.8*3.8*I23 -> #VALUE! | CL23: =13.8*3.8*J23 -> 2097.6 | CM23: =CL23/30*J23 -> 2796.8 | CO23: 250.9 | CP23: =CM23*CD23 -> 13984 | CQ23: =CO23*CD23 -> 1254.5 | CR23: =CQ23/CJ23 -> 234.56015 | CT23: =SUM(K23:W23)*CO23 -> 1254.5 | CU23: =SUM(X23:AX23)*CO23 -> 0 | CX23: =COUNTA(R23:X23)*$CE23 -> 0 | CY23: =COUNTA(R23:X23)*$CF23 -> 7.5 | CZ23: =COUNTA(K23:Q23)*$CG23 -> 2.1393233 | DA23: =COUNTA(Y23:AE23)*$CE23 -> 0 | DB23: =COUNTA(Y23:AE23)*$CF23 -> 0 | DC23: =COUNTA(R23:X23)*$CG23 -> 3.208985 | DD23: =COUNTA(AF23:AL23)*$CE23 -> 0 | DE23: =COUNTA(AF23:AL23)*$CF23 -> 0 | DF23: =COUNTA(Y23:AE23)*$CG23 -> 0 | DG23: =COUNTA(AM23:AS23)*$CE23 -> 0 | DH23: =COUNTA(AM23:AS23)*$CF23 -> 0 | DI23: =COUNTA(AF23:AL23)*$CG23 -> 0 | DJ23: =COUNTA(AT23:AZ23)*$CE23 -> 0 | DK23: =COUNTA(AT23:AZ23)*$CF23 -> 0 | DL23: =COUNTA(AM23:AS23)*$CG23 -> 0 | DM23: =COUNTA(BA23:BG23)*$CE23 -> 0 | DN23: =COUNTA(BA23:BG23)*$CF23 -> 0 | DO23: =COUNTA(AT23:AX23)*$CG23 -> 0 | DP23: =COUNTA(BH23:BN23)*$CE23 -> 0 | DQ23: =COUNTA(BH23:BN23)*$CF23 -> 0 | DR23: =COUNTA(BH23:BN23)*$CG23 -> 0
C24: CONTACTO DIRECTO | D24: 0.29166667 | E24: NOTICIERO | F24: LMWJV | G24: =IF(D24<=0.541,"DAY",(IF(D24<=0.74930556,"EARLY",(IF(D24<=0.97916667,"PRIME","LATE"))))) -> DAY | H24: AWARENESS | I24: SPOT | J24: 40 | L24: 1 | N24: 1 | S24: 1 | U24: 1 | Y24: 1 | CD24: =SUM(K24:CC24) -> 5 | CF24: 2.4 | CG24: =(CE24*$CH$7)+(CF24*$CI$7) -> 1.0268752 | CH24: =+CD24*CE24 -> 0 | CI24: =+CD24*CF24 -> 12 | CJ24: =CD24*CG24 -> 5.134376 | CK24: =(480+12)/2 -> 246 | CL24: =(480+12)/2 -> 246 | CM24: =CL24/30*J24 -> 328 | CO24: 250.91 | CP24: =CM24*CD24 -> 1640 | CQ24: =CO24*CD24 -> 1254.55 | CR24: =CQ24/CJ24 -> 244.34323 | CT24: =SUM(K24:W24)*CO24 -> 1003.64 | CU24: =SUM(X24:AX24)*CO24 -> 250.91 | CX24: =COUNTA(R24:X24)*$CE24 -> 0 | CY24: =COUNTA(R24:X24)*$CF24 -> 4.8 | CZ24: =COUNTA(K24:Q24)*$CG24 -> 2.0537504 | DA24: =COUNTA(Y24:AE24)*$CE24 -> 0 | DB24: =COUNTA(Y24:AE24)*$CF24 -> 2.4 | DC24: =COUNTA(R24:X24)*$CG24 -> 2.0537504 | DD24: =COUNTA(AF24:AL24)*$CE24 -> 0 | DE24: =COUNTA(AF24:AL24)*$CF24 -> 0 | DF24: =COUNTA(Y24:AE24)*$CG24 -> 1.0268752 | DG24: =COUNTA(AM24:AS24)*$CE24 -> 0 | DH24: =COUNTA(AM24:AS24)*$CF24 -> 0 | DI24: =COUNTA(AF24:AL24)*$CG24 -> 0 | DJ24: =COUNTA(AT24:AZ24)*$CE24 -> 0 | DK24: =COUNTA(AT24:AZ24)*$CF24 -> 0 | DL24: =COUNTA(AM24:AS24)*$CG24 -> 0 | DM24: =COUNTA(BA24:BG24)*$CE24 -> 0 | DN24: =COUNTA(BA24:BG24)*$CF24 -> 0 | DO24: =COUNTA(AT24:AX24)*$CG24 -> 0 | DP24: =COUNTA(BH24:BN24)*$CE24 -> 0 | DQ24: =COUNTA(BH24:BN24)*$CF24 -> 0 | DR24: =COUNTA(BH24:BN24)*$CG24 -> 0
C25: TNV. 09:00 | D25: 0.375 | E25: TELENOVELA | F25: LMWJV | G25: =IF(D25<=0.541,"DAY",(IF(D25<=0.74930556,"EARLY",(IF(D25<=0.97916667,"PRIME","LATE"))))) -> DAY | H25: AWARENESS | I25: SPOT | J25: 40 | K25: 1 | M25: 1 | O25: 1 | R25: 1 | T25: 1 | CD25: =SUM(K25:CC25) -> 5 | CF25: 2 | CG25: =(CE25*$CH$7)+(CF25*$CI$7) -> 0.85572934 | CH25: =+CD25*CE25 -> 0 | CI25: =+CD25*CF25 -> 10 | CJ25: =CD25*CG25 -> 4.2786467 | CK25: =(480+12)/2 -> 246 | CL25: =(480+12)/2 -> 246 | CM25: =CL25/30*J25 -> 328 | CO25: 250.91 | CP25: =CM25*CD25 -> 1640 | CQ25: =CO25*CD25 -> 1254.55 | CR25: =CQ25/CJ25 -> 293.21187 | CT25: =SUM(K25:W25)*CO25 -> 1254.55 | CU25: =SUM(X25:AX25)*CO25 -> 0 | CX25: =COUNTA(R25:X25)*$CE25 -> 0 | CY25: =COUNTA(R25:X25)*$CF25 -> 4 | CZ25: =COUNTA(K25:Q25)*$CG25 -> 2.567188 | DA25: =COUNTA(Y25:AE25)*$CE25 -> 0 | DB25: =COUNTA(Y25:AE25)*$CF25 -> 0 | DC25: =COUNTA(R25:X25)*$CG25 -> 1.7114587 | DD25: =COUNTA(AF25:AL25)*$CE25 -> 0 | DE25: =COUNTA(AF25:AL25)*$CF25 -> 0 | DF25: =COUNTA(Y25:AE25)*$CG25 -> 0 | DG25: =COUNTA(AM25:AS25)*$CE25 -> 0 | DH25: =COUNTA(AM25:AS25)*$CF25 -> 0 | DI25: =COUNTA(AF25:AL25)*$CG25 -> 0 | DJ25: =COUNTA(AT25:AZ25)*$CE25 -> 0 | DK25: =COUNTA(AT25:AZ25)*$CF25 -> 0 | DL25: =COUNTA(AM25:AS25)*$CG25 -> 0 | DM25: =COUNTA(BA25:BG25)*$CE25 -> 0 | DN25: =COUNTA(BA25:BG25)*$CF25 -> 0 | DO25: =COUNTA(AT25:AX25)*$CG25 -> 0
C26: EN CONTACTO | D26: 0.4375 | E26: MAGAZINE | F26: LMWJV | G26: =IF(D26<=0.541,"DAY",(IF(D26<=0.74930556,"EARLY",(IF(D26<=0.97916667,"PRIME","LATE"))))) -> DAY | H26: AWARENESS | I26: MENCION | J26: 15 | M26: 1 | O26: 1 | R26: 1 | T26: 1 | CD26: =SUM(K26:CC26) -> 4 | CF26: 2.5 | CG26: =(CE26*$CH$7)+(CF26*$CI$7) -> 1.0696617 | CH26: =+CD26*CE26 -> 0 | CI26: =+CD26*CF26 -> 10 | CJ26: =CD26*CG26 -> 4.2786467 | CK26: =(480+12)/2 -> 246 | CL26: =(480+12)/2 -> 246 | CM26: =CL26/30*J26 -> 123 | CO26: 250.91 | CP26: =CM26*CD26 -> 492 | CQ26: =CO26*CD26 -> 1003.64 | CR26: =CQ26/CJ26 -> 234.5695 | CT26: =SUM(K26:W26)*CO26 -> 1003.64 | CU26: =SUM(X26:AX26)*CO26 -> 0 | CX26: =COUNTA(R26:X26)*$CE26 -> 0 | CY26: =COUNTA(R26:X26)*$CF26 -> 5 | CZ26: =COUNTA(K26:Q26)*$CG26 -> 2.1393233 | DA26: =COUNTA(Y26:AE26)*$CE26 -> 0 | DB26: =COUNTA(Y26:AE26)*$CF26 -> 0 | DC26: =COUNTA(R26:X26)*$CG26 -> 2.1393233 | DD26: =COUNTA(AF26:AL26)*$CE26 -> 0 | DE26: =COUNTA(AF26:AL26)*$CF26 -> 0 | DF26: =COUNTA(Y26:AE26)*$CG26 -> 0 | DG26: =COUNTA(AM26:AS26)*$CE26 -> 0 | DH26: =COUNTA(AM26:AS26)*$CF26 -> 0 | DI26: =COUNTA(AF26:AL26)*$CG26 -> 0 | DJ26: =COUNTA(AT26:AZ26)*$CE26 -> 0 | DK26: =COUNTA(AT26:AZ26)*$CF26 -> 0 | DL26: =COUNTA(AM26:AS26)*$CG26 -> 0 | DM26: =COUNTA(BA26:BG26)*$CE26 -> 0 | DN26: =COUNTA(BA26:BG26)*$CF26 -> 0 | DO26: =COUNTA(AT26:AX26)*$CG26 -> 0
C27: TELEVISTAZO II | D27: 0.54166667 | E27: NOTICIERO | F27: LMWJV | G27: =IF(D27<=0.541,"DAY",(IF(D27<=0.74930556,"EARLY",(IF(D27<=0.97916667,"PRIME","LATE"))))) -> EARLY | H27: AWARENESS | I27: SPOT | J27: 40 | L27: 1 | N27: 1 | S27: 1 | V27: 1 | Z27: 1 | CD27: =SUM(K27:CC27) -> 5 | CF27: 4.3 | CG27: =(CE27*$CH$7)+(CF27*$CI$7) -> 1.8398181 | CH27: =+CD27*CE27 -> 0 | CI27: =+CD27*CF27 -> 21.5 | CJ27: =CD27*CG27 -> 9.1990904 | CK27: =23.6*7.6*I27 -> #VALUE! | CL27: =23.6*7.6*J27 -> 7174.4 | CM27: =CL27/30*J27 -> 9565.8667 | CO27: 250.91 | CP27: =CM27*CD27 -> 47829.333 | CQ27: =CO27*CD27 -> 1254.55 | CR27: =CQ27/CJ27 -> 136.37761 | CT27: =SUM(K27:W27)*CO27 -> 1003.64 | CU27: =SUM(X27:AX27)*CO27 -> 250.91 | CX27: =COUNTA(R27:X27)*$CE27 -> 0 | CY27: =COUNTA(R27:X27)*$CF27 -> 8.6 | CZ27: =COUNTA(K27:Q27)*$CG27 -> 3.6796362 | DA27: =COUNTA(Y27:AE27)*$CE27 -> 0 | DB27: =COUNTA(Y27:AE27)*$CF27 -> 4.3 | DC27: =COUNTA(R27:X27)*$CG27 -> 3.6796362 | DD27: =COUNTA(AF27:AL27)*$CE27 -> 0 | DE27: =COUNTA(AF27:AL27)*$CF27 -> 0 | DF27: =COUNTA(Y27:AE27)*$CG27 -> 1.8398181 | DG27: =COUNTA(AM27:AS27)*$CE27 -> 0 | DH27: =COUNTA(AM27:AS27)*$CF27 -> 0 | DI27: =COUNTA(AF27:AL27)*$CG27 -> 0 | DJ27: =COUNTA(AT27:AZ27)*$CE27 -> 0 | DK27: =COUNTA(AT27:AZ27)*$CF27 -> 0 | DL27: =COUNTA(AM27:AS27)*$CG27 -> 0 | DM27: =COUNTA(BA27:BG27)*$CE27 -> 0 | DN27: =COUNTA(BA27:BG27)*$CF27 -> 0 | DO27: =COUNTA(AT27:AX27)*$CG27 -> 0 | DP27: =COUNTA(BH27:BN27)*$CE27 -> 0 | DQ27: =COUNTA(BH27:BN27)*$CF27 -> 0 | DR27: =COUNTA(BH27:BN27)*$CG27 -> 0
C28: TNV. DESALMADA | D28: 0.72916667 | E28: TELENOVELA | F28: LMWJV | G28: =IF(D28<=0.541,"DAY",(IF(D28<=0.74930556,"EARLY",(IF(D28<=0.97916667,"PRIME","LATE"))))) -> EARLY | H28: AWARENESS | I28: SPOT | J28: 40 | K28: 1 | M28: 1 | R28: 1 | T28: 1 | Y28: 1 | CD28: =SUM(K28:CC28) -> 5 | CF28: 3.9 | CG28: =(CE28*$CH$7)+(CF28*$CI$7) -> 1.6686722 | CH28: =+CD28*CE28 -> 0 | CI28: =+CD28*CF28 -> 19.5 | CJ28: =CD28*CG28 -> 8.3433611 | CK28: =14.8*2.3*I28 -> #VALUE! | CL28: =14.8*2.3*J28 -> 1361.6 | CM28: =CL28/30*J28 -> 1815.4667 | CO28: 250.91 | CP28: =CM28*CD28 -> 9077.3333 | CQ28: =CO28*CD28 -> 1254.55 | CR28: =CQ28/CJ28 -> 150.36506 | CT28: =SUM(K28:W28)*CO28 -> 1003.64 | CU28: =SUM(X28:AX28)*CO28 -> 250.91 | CX28: =COUNTA(R28:X28)*$CE28 -> 0 | CY28: =COUNTA(R28:X28)*$CF28 -> 7.8 | CZ28: =COUNTA(K28:Q28)*$CG28 -> 3.3373444 | DA28: =COUNTA(Y28:AE28)*$CE28 -> 0 | DB28: =COUNTA(Y28:AE28)*$CF28 -> 3.9 | DC28: =COUNTA(R28:X28)*$CG28 -> 3.3373444 | DD28: =COUNTA(AF28:AL28)*$CE28 -> 0 | DE28: =COUNTA(AF28:AL28)*$CF28 -> 0 | DF28: =COUNTA(Y28:AE28)*$CG28 -> 1.6686722 | DG28: =COUNTA(AM28:AS28)*$CE28 -> 0 | DH28: =COUNTA(AM28:AS28)*$CF28 -> 0 | DI28: =COUNTA(AF28:AL28)*$CG28 -> 0 | DJ28: =COUNTA(AT28:AZ28)*$CE28 -> 0 | DK28: =COUNTA(AT28:AZ28)*$CF28 -> 0 | DL28: =COUNTA(AM28:AS28)*$CG28 -> 0 | DM28: =COUNTA(BA28:BG28)*$CE28 -> 0 | DN28: =COUNTA(BA28:BG28)*$CF28 -> 0 | DO28: =COUNTA(AT28:AX28)*$CG28 -> 0 | DP28: =COUNTA(BH28:BN28)*$CE28 -> 0 | DQ28: =COUNTA(BH28:BN28)*$CF28 -> 0 | DR28: =COUNTA(BH28:BN28)*$CG28 -> 0
C29: LARGOMETRAJE (D) | D29: 0.83333333 | E29: LARGOMETRAJE | F29: D | G29: =IF(D29<=0.541,"DAY",(IF(D29<=0.74930556,"EARLY",(IF(D29<=0.97916667,"PRIME","LATE"))))) -> PRIME | H29: AWARENESS | I29: SPOT | J29: 40 | Q29: 2 | X29: 2 | CD29: =SUM(K29:CC29) -> 4 | CF29: 3 | CG29: =(CE29*$CH$7)+(CF29*$CI$7) -> 1.283594 | CH29: =+CD29*CE29 -> 0 | CI29: =+CD29*CF29 -> 12 | CJ29: =CD29*CG29 -> 5.134376 | CK29: =14.8*4*I29 -> #VALUE! | CL29: =14.8*4*J29 -> 2368 | CM29: =CL29/30*J29 -> 3157.3333 | CO29: 250.91 | CP29: =CM29*CD29 -> 12629.333 | CQ29: =CO29*CD29 -> 1003.64 | CR29: =CQ29/CJ29 -> 195.47458 | CT29: =SUM(K29:W29)*CO29 -> 501.82 | CU29: =SUM(X29:AX29)*CO29 -> 501.82 | CX29: =COUNTA(R29:X29)*$CE29 -> 0 | CY29: =COUNTA(R29:X29)*$CF29 -> 3 | CZ29: =COUNTA(K29:Q29)*$CG29 -> 1.283594 | DA29: =COUNTA(Y29:AE29)*$CE29 -> 0 | DB29: =COUNTA(Y29:AE29)*$CF29 -> 0 | DC29: =COUNTA(R29:X29)*$CG29 -> 1.283594 | DD29: =COUNTA(AF29:AL29)*$CE29 -> 0 | DE29: =COUNTA(AF29:AL29)*$CF29 -> 0 | DF29: =COUNTA(Y29:AE29)*$CG29 -> 0 | DG29: =COUNTA(AM29:AS29)*$CE29 -> 0 | DH29: =COUNTA(AM29:AS29)*$CF29 -> 0 | DI29: =COUNTA(AF29:AL29)*$CG29 -> 0 | DJ29: =COUNTA(AT29:AZ29)*$CE29 -> 0 | DK29: =COUNTA(AT29:AZ29)*$CF29 -> 0 | DL29: =COUNTA(AM29:AS29)*$CG29 -> 0 | DM29: =COUNTA(BA29:BG29)*$CE29 -> 0 | DN29: =COUNTA(BA29:BG29)*$CF29 -> 0 | DO29: =COUNTA(AT29:AX29)*$CG29 -> 0 | DP29: =COUNTA(BH29:BN29)*$CE29 -> 0 | DQ29: =COUNTA(BH29:BN29)*$CF29 -> 0 | DR29: =COUNTA(BH29:BN29)*$CG29 -> 0
C30: TNV. HIJOS DE NADIE | D30: 0.85416667 | E30: TELENOVELA | F30: LMWJV | G30: =IF(D30<=0.541,"DAY",(IF(D30<=0.74930556,"EARLY",(IF(D30<=0.97916667,"PRIME","LATE"))))) -> PRIME | H30: AWARENESS | I30: SPOT | J30: 40 | K30: 1 | N30: 1 | R30: 1 | T30: 1 | Y30: 1 | CD30: =SUM(K30:CC30) -> 5 | CF30: 4.8 | CG30: =(CE30*$CH$7)+(CF30*$CI$7) -> 2.0537504 | CH30: =+CD30*CE30 -> 0 | CI30: =+CD30*CF30 -> 24 | CJ30: =CD30*CG30 -> 10.268752 | CK30: =12.4*2.5*I30 -> #VALUE! | CL30: =12.4*2.5*J30 -> 1240 | CM30: =CL30/30*J30 -> 1653.3333 | CO30: 250.91 | CP30: =CM30*CD30 -> 8266.6667 | CQ30: =CO30*CD30 -> 1254.55 | CR30: =CQ30/CJ30 -> 122.17161 | CT30: =SUM(K30:W30)*CO30 -> 1003.64 | CU30: =SUM(X30:AX30)*CO30 -> 250.91 | CX30: =COUNTA(R30:X30)*$CE30 -> 0 | CY30: =COUNTA(R30:X30)*$CF30 -> 9.6 | CZ30: =COUNTA(K30:Q30)*$CG30 -> 4.1075008 | DA30: =COUNTA(Y30:AE30)*$CE30 -> 0 | DB30: =COUNTA(Y30:AE30)*$CF30 -> 4.8 | DC30: =COUNTA(R30:X30)*$CG30 -> 4.1075008 | DD30: =COUNTA(AF30:AL30)*$CE30 -> 0 | DE30: =COUNTA(AF30:AL30)*$CF30 -> 0 | DF30: =COUNTA(Y30:AE30)*$CG30 -> 2.0537504 | DG30: =COUNTA(AM30:AS30)*$CE30 -> 0 | DH30: =COUNTA(AM30:AS30)*$CF30 -> 0 | DI30: =COUNTA(AF30:AL30)*$CG30 -> 0 | DJ30: =COUNTA(AT30:AZ30)*$CE30 -> 0 | DK30: =COUNTA(AT30:AZ30)*$CF30 -> 0 | DL30: =COUNTA(AM30:AS30)*$CG30 -> 0 | DM30: =COUNTA(BA30:BG30)*$CE30 -> 0 | DN30: =COUNTA(BA30:BG30)*$CF30 -> 0 | DO30: =COUNTA(AT30:AX30)*$CG30 -> 0 | DP30: =COUNTA(BH30:BN30)*$CE30 -> 0 | DQ30: =COUNTA(BH30:BN30)*$CF30 -> 0 | DR30: =COUNTA(BH30:BN30)*$CG30 -> 0
C31: TNV. FRUTO PROHIBIDO | D31: 0.91666667 | E31: TELENOVELA | F31: LMWJV | G31: =IF(D31<=0.541,"DAY",(IF(D31<=0.74930556,"EARLY",(IF(D31<=0.97916667,"PRIME","LATE"))))) -> PRIME | H31: AWARENESS | I31: SPOT | J31: 40 | CD31: =SUM(K31:CC31) -> 0 | CF31: 4.6 | CG31: =(CE31*$CH$7)+(CF31*$CI$7) -> 1.9681775 | CH31: =+CD31*CE31 -> 0 | CI31: =+CD31*CF31 -> 0 | CJ31: =CD31*CG31 -> 0 | CK31: =1417/2 -> 708.5 | CL31: =1417/2 -> 708.5 | CM31: =CL31/30*J31 -> 944.66667 | CO31: 250.91 | CP31: =CM31*CD31 -> 0 | CQ31: =CO31*CD31 -> 0 | CR31: =CQ31/CJ31 -> #DIV/0! | CT31: =SUM(K31:W31)*CO31 -> 0 | CU31: =SUM(X31:AX31)*CO31 -> 0 | CX31: =COUNTA(R31:X31)*$CE31 -> 0 | CY31: =COUNTA(R31:X31)*$CF31 -> 0 | CZ31: =COUNTA(K31:Q31)*$CG31 -> 0 | DA31: =COUNTA(Y31:AE31)*$CE31 -> 0 | DB31: =COUNTA(Y31:AE31)*$CF31 -> 0 | DC31: =COUNTA(R31:X31)*$CG31 -> 0 | DD31: =COUNTA(AF31:AL31)*$CE31 -> 0 | DE31: =COUNTA(AF31:AL31)*$CF31 -> 0 | DF31: =COUNTA(Y31:AE31)*$CG31 -> 0 | DG31: =COUNTA(AM31:AS31)*$CE31 -> 0 | DH31: =COUNTA(AM31:AS31)*$CF31 -> 0 | DI31: =COUNTA(AF31:AL31)*$CG31 -> 0 | DJ31: =COUNTA(AT31:AZ31)*$CE31 -> 0 | DK31: =COUNTA(AT31:AZ31)*$CF31 -> 0 | DL31: =COUNTA(AM31:AS31)*$CG31 -> 0 | DM31: =COUNTA(BA31:BG31)*$CE31 -> 0 | DN31: =COUNTA(BA31:BG31)*$CF31 -> 0 | DO31: =COUNTA(AT31:AX31)*$CG31 -> 0 | DP31: =COUNTA(BH31:BN31)*$CE31 -> 0 | DQ31: =COUNTA(BH31:BN31)*$CF31 -> 0 | DR31: =COUNTA(BH31:BN31)*$CG31 -> 0
C32: TELEVISTAZO AL AMANECER | D32: 0.25 | E32: NOTICIERO | F32: LMWJV | G32: =IF(D32<=0.541,"DAY",(IF(D32<=0.74930556,"EARLY",(IF(D32<=0.97916667,"PRIME","LATE"))))) -> DAY | H32: AWARENESS | I32: SPOT | J32: 20 | AB32: 1 | AG32: 1 | AO32: 1 | AV32: 1 | CD32: =SUM(K32:CC32) -> 4 | CF32: 2.5 | CG32: =(CE32*$CH$7)+(CF32*$CI$7) -> 1.0696617 | CH32: =+CD32*CE32 -> 0 | CI32: =+CD32*CF32 -> 10 | CJ32: =CD32*CG32 -> 4.2786467 | CK32: =13.8*3.8*I32 -> #VALUE! | CL32: =13.8*3.8*J32 -> 1048.8 | CM32: =CL32/30*J32 -> 699.2 | CO32: 250.91 | CP32: =CM32*CD32 -> 2796.8 | CQ32: =CO32*CD32 -> 1003.64 | CR32: =CQ32/CJ32 -> 234.5695 | CT32: =SUM(K32:W32)*CO32 -> 0 | CU32: =SUM(X32:AX32)*CO32 -> 1003.64 | CX32: =COUNTA(R32:X32)*$CE32 -> 0 | CY32: =COUNTA(R32:X32)*$CF32 -> 0 | CZ32: =COUNTA(K32:Q32)*$CG32 -> 0 | DA32: =COUNTA(Y32:AE32)*$CE32 -> 0 | DB32: =COUNTA(Y32:AE32)*$CF32 -> 2.5 | DC32: =COUNTA(R32:X32)*$CG32 -> 0 | DD32: =COUNTA(AF32:AL32)*$CE32 -> 0 | DE32: =COUNTA(AF32:AL32)*$CF32 -> 2.5 | DF32: =COUNTA(Y32:AE32)*$CG32 -> 1.0696617 | DG32: =COUNTA(AM32:AS32)*$CE32 -> 0 | DH32: =COUNTA(AM32:AS32)*$CF32 -> 2.5 | DI32: =COUNTA(AF32:AL32)*$CG32 -> 1.0696617 | DJ32: =COUNTA(AT32:AZ32)*$CE32 -> 0 | DK32: =COUNTA(AT32:AZ32)*$CF32 -> 2.5 | DL32: =COUNTA(AM32:AS32)*$CG32 -> 1.0696617 | DM32: =COUNTA(BA32:BG32)*$CE32 -> 0 | DN32: =COUNTA(BA32:BG32)*$CF32 -> 0 | DO32: =COUNTA(AT32:AX32)*$CG32 -> 1.0696617 | DP32: =COUNTA(BH32:BN32)*$CE32 -> 0 | DQ32: =COUNTA(BH32:BN32)*$CF32 -> 0 | DR32: =COUNTA(BH32:BN32)*$CG32 -> 0
C33: TELEVISTAZO EN LA COMUNIDAD | D33: 0.3125 | E33: NOTICIERO | F33: LMWJV | G33: =IF(D33<=0.541,"DAY",(IF(D33<=0.74930556,"EARLY",(IF(D33<=0.97916667,"PRIME","LATE"))))) -> DAY | H33: AWARENESS | I33: SPOT | J33: 20 | AA33: 1 | AI33: 1 | AP33: 1 | AT33: 1 | CD33: =SUM(K33:CC33) -> 4 | CF33: 2.6 | CG33: =(CE33*$CH$7)+(CF33*$CI$7) -> 1.1124481 | CH33: =+CD33*CE33 -> 0 | CI33: =+CD33*CF33 -> 10.4 | CJ33: =CD33*CG33 -> 4.4497926 | CK33: =17.9*5.1*I33 -> #VALUE! | CL33: =17.9*5.1*J33 -> 1825.8 | CM33: =CL33/30*J33 -> 1217.2 | CO33: 250.91 | CP33: =CM33*CD33 -> 4868.8 | CQ33: =CO33*CD33 -> 1003.64 | CR33: =CQ33/CJ33 -> 225.54759 | CT33: =SUM(K33:W33)*CO33 -> 0 | CU33: =SUM(X33:AX33)*CO33 -> 1003.64 | CX33: =COUNTA(R33:X33)*$CE33 -> 0 | CY33: =COUNTA(R33:X33)*$CF33 -> 0 | CZ33: =COUNTA(K33:Q33)*$CG33 -> 0 | DA33: =COUNTA(Y33:AE33)*$CE33 -> 0 | DB33: =COUNTA(Y33:AE33)*$CF33 -> 2.6 | DC33: =COUNTA(R33:X33)*$CG33 -> 0 | DD33: =COUNTA(AF33:AL33)*$CE33 -> 0 | DE33: =COUNTA(AF33:AL33)*$CF33 -> 2.6 | DF33: =COUNTA(Y33:AE33)*$CG33 -> 1.1124481 | DG33: =COUNTA(AM33:AS33)*$CE33 -> 0 | DH33: =COUNTA(AM33:AS33)*$CF33 -> 2.6 | DI33: =COUNTA(AF33:AL33)*$CG33 -> 1.1124481 | DJ33: =COUNTA(AT33:AZ33)*$CE33 -> 0 | DK33: =COUNTA(AT33:AZ33)*$CF33 -> 2.6 | DL33: =COUNTA(AM33:AS33)*$CG33 -> 1.1124481 | DM33: =COUNTA(BA33:BG33)*$CE33 -> 0 | DN33: =COUNTA(BA33:BG33)*$CF33 -> 0 | DO33: =COUNTA(AT33:AX33)*$CG33 -> 1.1124481 | DP33: =COUNTA(BH33:BN33)*$CE33 -> 0 | DQ33: =COUNTA(BH33:BN33)*$CF33 -> 0 | DR33: =COUNTA(BH33:BN33)*$CG33 -> 0
C34: TNV. COMO DICE EL DICHO | D34: 0.64583333 | E34: TELENOVELA | F34: LMWJV | G34: =IF(D34<=0.541,"DAY",(IF(D34<=0.74930556,"EARLY",(IF(D34<=0.97916667,"PRIME","LATE"))))) -> EARLY | H34: AWARENESS | I34: SPOT | J34: 20 | CD34: =SUM(K34:CC34) -> 0 | CF34: 2 | CG34: =(CE34*$CH$7)+(CF34*$CI$7) -> 0.85572934 | CH34: =+CD34*CE34 -> 0 | CI34: =+CD34*CF34 -> 0 | CJ34: =CD34*CG34 -> 0 | CK34: =17.5*1.4*I34 -> #VALUE! | CL34: =17.5*1.4*J34 -> 490 | CM34: =CL34/30*J34 -> 326.66667 | CO34: 250.91 | CP34: =CM34*CD34 -> 0 | CQ34: =CO34*CD34 -> 0 | CR34: =CQ34/CJ34 -> #DIV/0! | CT34: =SUM(K34:W34)*CO34 -> 0 | CU34: =SUM(X34:AX34)*CO34 -> 0 | CX34: =COUNTA(R34:X34)*$CE34 -> 0 | CY34: =COUNTA(R34:X34)*$CF34 -> 0 | CZ34: =COUNTA(K34:Q34)*$CG34 -> 0 | DA34: =COUNTA(Y34:AE34)*$CE34 -> 0 | DB34: =COUNTA(Y34:AE34)*$CF34 -> 0 | DC34: =COUNTA(R34:X34)*$CG34 -> 0 | DD34: =COUNTA(AF34:AL34)*$CE34 -> 0 | DE34: =COUNTA(AF34:AL34)*$CF34 -> 0 | DF34: =COUNTA(Y34:AE34)*$CG34 -> 0 | DG34: =COUNTA(AM34:AS34)*$CE34 -> 0 | DH34: =COUNTA(AM34:AS34)*$CF34 -> 0 | DI34: =COUNTA(AF34:AL34)*$CG34 -> 0 | DJ34: =COUNTA(AT34:AZ34)*$CE34 -> 0 | DK34: =COUNTA(AT34:AZ34)*$CF34 -> 0 | DL34: =COUNTA(AM34:AS34)*$CG34 -> 0 | DM34: =COUNTA(BA34:BG34)*$CE34 -> 0 | DN34: =COUNTA(BA34:BG34)*$CF34 -> 0 | DO34: =COUNTA(AT34:AX34)*$CG34 -> 0 | DP34: =COUNTA(BH34:BN34)*$CE34 -> 0 | DQ34: =COUNTA(BH34:BN34)*$CF34 -> 0 | DR34: =COUNTA(BH34:BN34)*$CG34 -> 0
C35: TNV. ASUNTOS DE FAMILIA | D35: 0.6875 | E35: TELENOVELA | F35: LMWJV | G35: =IF(D35<=0.541,"DAY",(IF(D35<=0.74930556,"EARLY",(IF(D35<=0.97916667,"PRIME","LATE"))))) -> EARLY | H35: AWARENESS | I35: SPOT | J35: 20 | CD35: =SUM(K35:CC35) -> 0 | CF35: 1.5 | CG35: =(CE35*$CH$7)+(CF35*$CI$7) -> 0.641797 | CH35: =+CD35*CE35 -> 0 | CI35: =+CD35*CF35 -> 0 | CJ35: =CD35*CG35 -> 0 | CK35: =7.5*1.1*I35 -> #VALUE! | CL35: =7.5*1.1*J35 -> 165 | CM35: =CL35/30*J35 -> 110 | CO35: 250.91 | CP35: =CM35*CD35 -> 0 | CQ35: =CO35*CD35 -> 0 | CR35: =CQ35/CJ35 -> #DIV/0! | CT35: =SUM(K35:W35)*CO35 -> 0 | CU35: =SUM(X35:AX35)*CO35 -> 0 | CX35: =COUNTA(R35:X35)*$CE35 -> 0 | CY35: =COUNTA(R35:X35)*$CF35 -> 0 | CZ35: =COUNTA(K35:Q35)*$CG35 -> 0 | DA35: =COUNTA(Y35:AE35)*$CE35 -> 0 | DB35: =COUNTA(Y35:AE35)*$CF35 -> 0 | DC35: =COUNTA(R35:X35)*$CG35 -> 0 | DD35: =COUNTA(AF35:AL35)*$CE35 -> 0 | DE35: =COUNTA(AF35:AL35)*$CF35 -> 0 | DF35: =COUNTA(Y35:AE35)*$CG35 -> 0 | DG35: =COUNTA(AM35:AS35)*$CE35 -> 0 | DH35: =COUNTA(AM35:AS35)*$CF35 -> 0 | DI35: =COUNTA(AF35:AL35)*$CG35 -> 0 | DJ35: =COUNTA(AT35:AZ35)*$CE35 -> 0 | DK35: =COUNTA(AT35:AZ35)*$CF35 -> 0 | DL35: =COUNTA(AM35:AS35)*$CG35 -> 0 | DM35: =COUNTA(BA35:BG35)*$CE35 -> 0 | DN35: =COUNTA(BA35:BG35)*$CF35 -> 0 | DO35: =COUNTA(AT35:AX35)*$CG35 -> 0 | DP35: =COUNTA(BH35:BN35)*$CE35 -> 0 | DQ35: =COUNTA(BH35:BN35)*$CF35 -> 0 | DR35: =COUNTA(BH35:BN35)*$CG35 -> 0
C36: TNV. DESALMADA | D36: 0.72916667 | E36: TELENOVELA | F36: LMWJV | G36: =IF(D36<=0.541,"DAY",(IF(D36<=0.74930556,"EARLY",(IF(D36<=0.97916667,"PRIME","LATE"))))) -> EARLY | H36: AWARENESS | I36: SPOT | J36: 20 | AA36: 1 | AH36: 1 | AP36: 1 | AW36: 1 | CD36: =SUM(K36:CC36) -> 4 | CF36: 3.9 | CG36: =(CE36*$CH$7)+(CF36*$CI$7) -> 1.6686722 | CH36: =+CD36*CE36 -> 0 | CI36: =+CD36*CF36 -> 15.6 | CJ36: =CD36*CG36 -> 6.6746888 | CK36: =14.8*2.3*I36 -> #VALUE! | CL36: =14.8*2.3*J36 -> 680.8 | CM36: =CL36/30*J36 -> 453.86667 | CO36: 250.91 | CP36: =CM36*CD36 -> 1815.4667 | CQ36: =CO36*CD36 -> 1003.64 | CR36: =CQ36/CJ36 -> 150.36506 | CT36: =SUM(K36:W36)*CO36 -> 0 | CU36: =SUM(X36:AX36)*CO36 -> 1003.64 | CX36: =COUNTA(R36:X36)*$CE36 -> 0 | CY36: =COUNTA(R36:X36)*$CF36 -> 0 | CZ36: =COUNTA(K36:Q36)*$CG36 -> 0 | DA36: =COUNTA(Y36:AE36)*$CE36 -> 0 | DB36: =COUNTA(Y36:AE36)*$CF36 -> 3.9 | DC36: =COUNTA(R36:X36)*$CG36 -> 0 | DD36: =COUNTA(AF36:AL36)*$CE36 -> 0 | DE36: =COUNTA(AF36:AL36)*$CF36 -> 3.9 | DF36: =COUNTA(Y36:AE36)*$CG36 -> 1.6686722 | DG36: =COUNTA(AM36:AS36)*$CE36 -> 0 | DH36: =COUNTA(AM36:AS36)*$CF36 -> 3.9 | DI36: =COUNTA(AF36:AL36)*$CG36 -> 1.6686722 | DJ36: =COUNTA(AT36:AZ36)*$CE36 -> 0 | DK36: =COUNTA(AT36:AZ36)*$CF36 -> 3.9 | DL36: =COUNTA(AM36:AS36)*$CG36 -> 1.6686722 | DM36: =COUNTA(BA36:BG36)*$CE36 -> 0 | DN36: =COUNTA(BA36:BG36)*$CF36 -> 0 | DO36: =COUNTA(AT36:AX36)*$CG36 -> 1.6686722 | DP36: =COUNTA(BH36:BN36)*$CE36 -> 0 | DQ36: =COUNTA(BH36:BN36)*$CF36 -> 0 | DR36: =COUNTA(BH36:BN36)*$CG36 -> 0
C37: TELEVISTAZO III ESTELAR | D37: 0.79166667 | E37: NOTICIERO | F37: LMWJV | G37: =IF(D37<=0.541,"DAY",(IF(D37<=0.74930556,"EARLY",(IF(D37<=0.97916667,"PRIME","LATE"))))) -> PRIME | H37: AWARENESS | I37: SPOT | J37: 20 | AB37: 1 | AF37: 1 | AO37: 1 | AU37: 1 | CD37: =SUM(K37:CC37) -> 4 | CF37: 5.6 | CG37: =(CE37*$CH$7)+(CF37*$CI$7) -> 2.3960421 | CH37: =+CD37*CE37 -> 0 | CI37: =+CD37*CF37 -> 22.4 | CJ37: =CD37*CG37 -> 9.5841686 | CK37: =14.8*4*I37 -> #VALUE! | CL37: =14.8*4*J37 -> 1184 | CM37: =CL37/30*J37 -> 789.33333 | CO37: 250.91 | CP37: =CM37*CD37 -> 3157.3333 | CQ37: =CO37*CD37 -> 1003.64 | CR37: =CQ37/CJ37 -> 104.71853 | CT37: =SUM(K37:W37)*CO37 -> 0 | CU37: =SUM(X37:AX37)*CO37 -> 1003.64 | CX37: =COUNTA(R37:X37)*$CE37 -> 0 | CY37: =COUNTA(R37:X37)*$CF37 -> 0 | CZ37: =COUNTA(K37:Q37)*$CG37 -> 0 | DA37: =COUNTA(Y37:AE37)*$CE37 -> 0 | DB37: =COUNTA(Y37:AE37)*$CF37 -> 5.6 | DC37: =COUNTA(R37:X37)*$CG37 -> 0 | DD37: =COUNTA(AF37:AL37)*$CE37 -> 0 | DE37: =COUNTA(AF37:AL37)*$CF37 -> 5.6 | DF37: =COUNTA(Y37:AE37)*$CG37 -> 2.3960421 | DG37: =COUNTA(AM37:AS37)*$CE37 -> 0 | DH37: =COUNTA(AM37:AS37)*$CF37 -> 5.6 | DI37: =COUNTA(AF37:AL37)*$CG37 -> 2.3960421 | DJ37: =COUNTA(AT37:AZ37)*$CE37 -> 0 | DK37: =COUNTA(AT37:AZ37)*$CF37 -> 5.6 | DL37: =COUNTA(AM37:AS37)*$CG37 -> 2.3960421 | DM37: =COUNTA(BA37:BG37)*$CE37 -> 0 | DN37: =COUNTA(BA37:BG37)*$CF37 -> 0 | DO37: =COUNTA(AT37:AX37)*$CG37 -> 2.3960421 | DP37: =COUNTA(BH37:BN37)*$CE37 -> 0 | DQ37: =COUNTA(BH37:BN37)*$CF37 -> 0 | DR37: =COUNTA(BH37:BN37)*$CG37 -> 0
C38: TELEVISTAZO (S-D) | D38: 0.79166667 | E38: NOTICIERO | F38: SD | G38: =IF(D38<=0.541,"DAY",(IF(D38<=0.74930556,"EARLY",(IF(D38<=0.97916667,"PRIME","LATE"))))) -> PRIME | H38: AWARENESS | I38: SPOT | J38: 20 | AE38: 1 | CD38: =SUM(K38:CC38) -> 1 | CF38: 4.6 | CG38: =(CE38*$CH$7)+(CF38*$CI$7) -> 1.9681775 | CH38: =+CD38*CE38 -> 0 | CI38: =+CD38*CF38 -> 4.6 | CJ38: =CD38*CG38 -> 1.9681775 | CK38: =14.8*4*I38 -> #VALUE! | CL38: =14.8*4*J38 -> 1184 | CM38: =CL38/30*J38 -> 789.33333 | CO38: 250.9 | CP38: =CM38*CD38 -> 789.33333 | CQ38: =CO38*CD38 -> 250.9 | CR38: =CQ38/CJ38 -> 127.47834 | CT38: =SUM(K38:W38)*CO38 -> 0 | CU38: =SUM(X38:AX38)*CO38 -> 250.9 | CX38: =COUNTA(R38:X38)*$CE38 -> 0 | CY38: =COUNTA(R38:X38)*$CF38 -> 0 | CZ38: =COUNTA(K38:Q38)*$CG38 -> 0 | DA38: =COUNTA(Y38:AE38)*$CE38 -> 0 | DB38: =COUNTA(Y38:AE38)*$CF38 -> 4.6 | DC38: =COUNTA(R38:X38)*$CG38 -> 0 | DD38: =COUNTA(AF38:AL38)*$CE38 -> 0 | DE38: =COUNTA(AF38:AL38)*$CF38 -> 0 | DF38: =COUNTA(Y38:AE38)*$CG38 -> 1.9681775 | DG38: =COUNTA(AM38:AS38)*$CE38 -> 0 | DH38: =COUNTA(AM38:AS38)*$CF38 -> 0 | DI38: =COUNTA(AF38:AL38)*$CG38 -> 0 | DJ38: =COUNTA(AT38:AZ38)*$CE38 -> 0 | DK38: =COUNTA(AT38:AZ38)*$CF38 -> 0 | DL38: =COUNTA(AM38:AS38)*$CG38 -> 0 | DM38: =COUNTA(BA38:BG38)*$CE38 -> 0 | DN38: =COUNTA(BA38:BG38)*$CF38 -> 0 | DO38: =COUNTA(AT38:AX38)*$CG38 -> 0 | DP38: =COUNTA(BH38:BN38)*$CE38 -> 0 | DQ38: =COUNTA(BH38:BN38)*$CF38 -> 0 | DR38: =COUNTA(BH38:BN38)*$CG38 -> 0
C39: LARGOMETRAJE (S) | D39: 0.83333333 | E39: LARGOMETRAJE | F39: S | G39: =IF(D39<=0.541,"DAY",(IF(D39<=0.74930556,"EARLY",(IF(D39<=0.97916667,"PRIME","LATE"))))) -> PRIME | H39: AWARENESS | I39: SPOT | J39: 20 | AD39: 1 | AR39: 1 | CD39: =SUM(K39:CC39) -> 2 | CF39: 3 | CG39: =(CE39*$CH$7)+(CF39*$CI$7) -> 1.283594 | CH39: =+CD39*CE39 -> 0 | CI39: =+CD39*CF39 -> 6 | CJ39: =CD39*CG39 -> 2.567188 | CK39: =14.8*4*I39 -> #VALUE! | CL39: =14.8*4*J39 -> 1184 | CM39: =CL39/30*J39 -> 789.33333 | CO39: 250.91 | CP39: =CM39*CD39 -> 1578.6667 | CQ39: =CO39*CD39 -> 501.82 | CR39: =CQ39/CJ39 -> 195.47458 | CT39: =SUM(K39:W39)*CO39 -> 0 | CU39: =SUM(X39:AX39)*CO39 -> 501.82 | CX39: =COUNTA(R39:X39)*$CE39 -> 0 | CY39: =COUNTA(R39:X39)*$CF39 -> 0 | CZ39: =COUNTA(K39:Q39)*$CG39 -> 0 | DA39: =COUNTA(Y39:AE39)*$CE39 -> 0 | DB39: =COUNTA(Y39:AE39)*$CF39 -> 3 | DC39: =COUNTA(R39:X39)*$CG39 -> 0 | DD39: =COUNTA(AF39:AL39)*$CE39 -> 0 | DE39: =COUNTA(AF39:AL39)*$CF39 -> 0 | DF39: =COUNTA(Y39:AE39)*$CG39 -> 1.283594 | DG39: =COUNTA(AM39:AS39)*$CE39 -> 0 | DH39: =COUNTA(AM39:AS39)*$CF39 -> 3 | DI39: =COUNTA(AF39:AL39)*$CG39 -> 0 | DJ39: =COUNTA(AT39:AZ39)*$CE39 -> 0 | DK39: =COUNTA(AT39:AZ39)*$CF39 -> 0 | DL39: =COUNTA(AM39:AS39)*$CG39 -> 1.283594 | DM39: =COUNTA(BA39:BG39)*$CE39 -> 0 | DN39: =COUNTA(BA39:BG39)*$CF39 -> 0 | DO39: =COUNTA(AT39:AX39)*$CG39 -> 0
C40: LARGOMETRAJE (D) | D40: 0.83333333 | E40: LARGOMETRAJE | F40: D | G40: =IF(D40<=0.541,"DAY",(IF(D40<=0.74930556,"EARLY",(IF(D40<=0.97916667,"PRIME","LATE"))))) -> PRIME | H40: AWARENESS | I40: SPOT | J40: 20 | AE40: 1 | AS40: 2 | CD40: =SUM(K40:CC40) -> 3 | CF40: 3 | CG40: =(CE40*$CH$7)+(CF40*$CI$7) -> 1.283594 | CH40: =+CD40*CE40 -> 0 | CI40: =+CD40*CF40 -> 9 | CJ40: =CD40*CG40 -> 3.850782 | CK40: =14.8*4*I40 -> #VALUE! | CL40: =14.8*4*J40 -> 1184 | CM40: =CL40/30*J40 -> 789.33333 | CO40: 250.91 | CP40: =CM40*CD40 -> 2368 | CQ40: =CO40*CD40 -> 752.73 | CR40: =CQ40/CJ40 -> 195.47458 | CT40: =SUM(K40:W40)*CO40 -> 0 | CU40: =SUM(X40:AX40)*CO40 -> 752.73 | CX40: =COUNTA(R40:X40)*$CE40 -> 0 | CY40: =COUNTA(R40:X40)*$CF40 -> 0 | CZ40: =COUNTA(K40:Q40)*$CG40 -> 0 | DA40: =COUNTA(Y40:AE40)*$CE40 -> 0 | DB40: =COUNTA(Y40:AE40)*$CF40 -> 3 | DC40: =COUNTA(R40:X40)*$CG40 -> 0 | DD40: =COUNTA(AF40:AL40)*$CE40 -> 0 | DE40: =COUNTA(AF40:AL40)*$CF40 -> 0 | DF40: =COUNTA(Y40:AE40)*$CG40 -> 1.283594 | DG40: =COUNTA(AM40:AS40)*$CE40 -> 0 | DH40: =COUNTA(AM40:AS40)*$CF40 -> 3 | DI40: =COUNTA(AF40:AL40)*$CG40 -> 0 | DJ40: =COUNTA(AT40:AZ40)*$CE40 -> 0 | DK40: =COUNTA(AT40:AZ40)*$CF40 -> 0 | DL40: =COUNTA(AM40:AS40)*$CG40 -> 1.283594 | DM40: =COUNTA(BA40:BG40)*$CE40 -> 0 | DN40: =COUNTA(BA40:BG40)*$CF40 -> 0 | DO40: =COUNTA(AT40:AX40)*$CG40 -> 0 | DP40: =COUNTA(BH40:BN40)*$CE40 -> 0 | DQ40: =COUNTA(BH40:BN40)*$CF40 -> 0 | DR40: =COUNTA(BH40:BN40)*$CG40 -> 0
C41: TNV. HIJOS DE NADIE | D41: 0.85416667 | E41: TELENOVELA | F41: LMWJV | G41: =IF(D41<=0.541,"DAY",(IF(D41<=0.74930556,"EARLY",(IF(D41<=0.97916667,"PRIME","LATE"))))) -> PRIME | H41: AWARENESS | I41: SPOT | J41: 20 | AA41: 1 | AF41: 1 | AH41: 1 | AI41: 1 | AO41: 1 | AT41: 1 | CD41: =SUM(K41:CC41) -> 6 | CF41: 4.8 | CG41: =(CE41*$CH$7)+(CF41*$CI$7) -> 2.0537504 | CH41: =+CD41*CE41 -> 0 | CI41: =+CD41*CF41 -> 28.8 | CJ41: =CD41*CG41 -> 12.322502 | CK41: =12.4*2.5*I41 -> #VALUE! | CL41: =12.4*2.5*J41 -> 620 | CM41: =CL41/30*J41 -> 413.33333 | CO41: 250.91 | CP41: =CM41*CD41 -> 2480 | CQ41: =CO41*CD41 -> 1505.46 | CR41: =CQ41/CJ41 -> 122.17161 | CT41: =SUM(K41:W41)*CO41 -> 0 | CU41: =SUM(X41:AX41)*CO41 -> 1505.46 | CX41: =COUNTA(R41:X41)*$CE41 -> 0 | CY41: =COUNTA(R41:X41)*$CF41 -> 0 | CZ41: =COUNTA(K41:Q41)*$CG41 -> 0 | DA41: =COUNTA(Y41:AE41)*$CE41 -> 0 | DB41: =COUNTA(Y41:AE41)*$CF41 -> 4.8 | DC41: =COUNTA(R41:X41)*$CG41 -> 0 | DD41: =COUNTA(AF41:AL41)*$CE41 -> 0 | DE41: =COUNTA(AF41:AL41)*$CF41 -> 14.4 | DF41: =COUNTA(Y41:AE41)*$CG41 -> 2.0537504 | DG41: =COUNTA(AM41:AS41)*$CE41 -> 0 | DH41: =COUNTA(AM41:AS41)*$CF41 -> 4.8 | DI41: =COUNTA(AF41:AL41)*$CG41 -> 6.1612512 | DJ41: =COUNTA(AT41:AZ41)*$CE41 -> 0 | DK41: =COUNTA(AT41:AZ41)*$CF41 -> 4.8 | DL41: =COUNTA(AM41:AS41)*$CG41 -> 2.0537504 | DM41: =COUNTA(BA41:BG41)*$CE41 -> 0 | DN41: =COUNTA(BA41:BG41)*$CF41 -> 0 | DO41: =COUNTA(AT41:AX41)*$CG41 -> 2.0537504 | DP41: =COUNTA(BH41:BN41)*$CE41 -> 0 | DQ41: =COUNTA(BH41:BN41)*$CF41 -> 0 | DR41: =COUNTA(BH41:BN41)*$CG41 -> 0
C42: TNV. FRUTO PROHIBIDO | D42: 0.91666667 | E42: TELENOVELA | F42: LMWJV | G42: =IF(D42<=0.541,"DAY",(IF(D42<=0.74930556,"EARLY",(IF(D42<=0.97916667,"PRIME","LATE"))))) -> PRIME | H42: AWARENESS | I42: SPOT | J42: 20 | CD42: =SUM(K42:CC42) -> 0 | CF42: 4.6 | CG42: =(CE42*$CH$7)+(CF42*$CI$7) -> 1.9681775 | CH42: =+CD42*CE42 -> 0 | CI42: =+CD42*CF42 -> 0 | CJ42: =CD42*CG42 -> 0 | CK42: =1417/2 -> 708.5 | CL42: =1417/2 -> 708.5 | CM42: =CL42/30*J42 -> 472.33333 | CO42: 293.57798 | CP42: =CM42*CD42 -> 0 | CQ42: =CO42*CD42 -> 0 | CR42: =CQ42/CJ42 -> #DIV/0! | CT42: =SUM(R42:V42)*CO42 -> 0 | CU42: =SUM(W42:AX42)*CO42 -> 0 | CX42: =COUNTA(R42:X42)*$CE42 -> 0 | CY42: =COUNTA(R42:X42)*$CF42 -> 0 | CZ42: =COUNTA(R42:X42)*$CG42 -> 0 | DA42: =COUNTA(Y42:AE42)*$CE42 -> 0 | DB42: =COUNTA(Y42:AE42)*$CF42 -> 0 | DC42: =COUNTA(Y42:AE42)*$CG42 -> 0 | DD42: =COUNTA(AF42:AL42)*$CE42 -> 0 | DE42: =COUNTA(AF42:AL42)*$CF42 -> 0 | DF42: =COUNTA(AF42:AL42)*$CG42 -> 0 | DG42: =COUNTA(AM42:AS42)*$CE42 -> 0 | DH42: =COUNTA(AM42:AS42)*$CF42 -> 0 | DI42: =COUNTA(AM42:AS42)*$CG42 -> 0 | DJ42: =COUNTA(AT42:AZ42)*$CE42 -> 0 | DK42: =COUNTA(AT42:AZ42)*$CF42 -> 0 | DL42: =COUNTA(AT42:AZ42)*$CG42 -> 0 | DM42: =COUNTA(BA42:BG42)*$CE42 -> 0 | DN42: =COUNTA(BA42:BG42)*$CF42 -> 0 | DO42: =COUNTA(BA42:BG42)*$CG42 -> 0 | DP42: =COUNTA(BH42:BN42)*$CE42 -> 0 | DQ42: =COUNTA(BH42:BN42)*$CF42 -> 0 | DR42: =COUNTA(BH42:BN42)*$CG42 -> 0
C43: TNV. LA REINA DE LA NOCHE | D43: 0.91666667 | E43: TELENOVELA | F43: LMWJV | G43: =IF(D43<=0.541,"DAY",(IF(D43<=0.74930556,"EARLY",(IF(D43<=0.97916667,"PRIME","LATE"))))) -> PRIME | H43: AWARENESS | I43: SPOT | J43: 20 | CD43: =SUM(K43:CC43) -> 0 | CF43: 1.8 | CG43: =(CE43*$CH$7)+(CF43*$CI$7) -> 0.7701564 | CH43: =+CD43*CE43 -> 0 | CI43: =+CD43*CF43 -> 0 | CJ43: =CD43*CG43 -> 0 | CK43: =12.4*5*I43 -> #VALUE! | CL43: =12.4*5*J43 -> 1240 | CM43: =CL43/30*J43 -> 826.66667 | CO43: 293.57798 | CP43: =CM43*CD43 -> 0 | CQ43: =CO43*CD43 -> 0 | CR43: =CQ43/CJ43 -> #DIV/0! | CT43: =SUM(R43:V43)*CO43 -> 0 | CU43: =SUM(W43:AX43)*CO43 -> 0 | CX43: =COUNTA(R43:X43)*$CE43 -> 0 | CY43: =COUNTA(R43:X43)*$CF43 -> 0 | CZ43: =COUNTA(R43:X43)*$CG43 -> 0 | DA43: =COUNTA(Y43:AE43)*$CE43 -> 0 | DB43: =COUNTA(Y43:AE43)*$CF43 -> 0 | DC43: =COUNTA(Y43:AE43)*$CG43 -> 0 | DD43: =COUNTA(AF43:AL43)*$CE43 -> 0 | DE43: =COUNTA(AF43:AL43)*$CF43 -> 0 | DF43: =COUNTA(AF43:AL43)*$CG43 -> 0 | DG43: =COUNTA(AM43:AS43)*$CE43 -> 0 | DH43: =COUNTA(AM43:AS43)*$CF43 -> 0 | DI43: =COUNTA(AM43:AS43)*$CG43 -> 0 | DJ43: =COUNTA(AT43:AZ43)*$CE43 -> 0 | DK43: =COUNTA(AT43:AZ43)*$CF43 -> 0 | DL43: =COUNTA(AT43:AZ43)*$CG43 -> 0 | DM43: =COUNTA(BA43:BG43)*$CE43 -> 0 | DN43: =COUNTA(BA43:BG43)*$CF43 -> 0 | DO43: =COUNTA(BA43:BG43)*$CG43 -> 0 | DP43: =COUNTA(BH43:BN43)*$CE43 -> 0 | DQ43: =COUNTA(BH43:BN43)*$CF43 -> 0 | DR43: =COUNTA(BH43:BN43)*$CG43 -> 0
C44: TNV. SILVANA SIN LANA | D44: 0.375 | E44: TELENOVELA | F44: LMWJV | G44: =IF(D44<=0.541,"DAY",(IF(D44<=0.74930556,"EARLY",(IF(D44<=0.97916667,"PRIME","LATE"))))) -> DAY | H44: MOVILIZACIÓN | I44: BUMPER | J44: 12 | CD44: =SUM(K44:CC44) -> 0 | CF44: 2.2 | CG44: =(CE44*$CH$7)+(CF44*$CI$7) -> 0.94130227 | CH44: =+CD44*CE44 -> 0 | CI44: =+CD44*CF44 -> 0 | CJ44: =CD44*CG44 -> 0 | CK44: =13.8*3.8*I44 -> #VALUE! | CL44: =13.8*3.8*J44 -> 629.28 | CM44: =CL44/30*J44 -> 251.712 | CO44: 293.57798 | CP44: =CM44*CD44 -> 0 | CQ44: =CO44*CD44 -> 0 | CR44: =CQ44/CJ44 -> #DIV/0! | CV44: =SUM(W44:AX44)*CO44 -> 0 | CX44: =COUNTA(R44:X44)*$CE44 -> 0 | CY44: =COUNTA(R44:X44)*$CF44 -> 0 | CZ44: =COUNTA(R44:X44)*$CG44 -> 0 | DA44: =COUNTA(Y44:AE44)*$CE44 -> 0 | DB44: =COUNTA(Y44:AE44)*$CF44 -> 0 | DC44: =COUNTA(Y44:AE44)*$CG44 -> 0 | DD44: =COUNTA(AF44:AL44)*$CE44 -> 0 | DE44: =COUNTA(AF44:AL44)*$CF44 -> 0 | DF44: =COUNTA(AF44:AL44)*$CG44 -> 0 | DG44: =COUNTA(AM44:AS44)*$CE44 -> 0 | DH44: =COUNTA(AM44:AS44)*$CF44 -> 0 | DI44: =COUNTA(AM44:AS44)*$CG44 -> 0 | DJ44: =COUNTA(AT44:AZ44)*$CE44 -> 0 | DK44: =COUNTA(AT44:AZ44)*$CF44 -> 0 | DL44: =COUNTA(AT44:AZ44)*$CG44 -> 0 | DM44: =COUNTA(BA44:BG44)*$CE44 -> 0 | DN44: =COUNTA(BA44:BG44)*$CF44 -> 0 | DO44: =COUNTA(BA44:BG44)*$CG44 -> 0 | DP44: =COUNTA(BH44:BN44)*$CE44 -> 0 | DQ44: =COUNTA(BH44:BN44)*$CF44 -> 0 | DR44: =COUNTA(BH44:BN44)*$CG44 -> 0
C45: TNV. CARITA DE ÁNGEL | D45: 0.40625 | E45: TELENOVELA | F45: LMWJV | G45: =IF(D45<=0.541,"DAY",(IF(D45<=0.74930556,"EARLY",(IF(D45<=0.97916667,"PRIME","LATE"))))) -> DAY | H45: MOVILIZACIÓN | I45: BUMPER | J45: 12 | CD45: =SUM(K45:CC45) -> 0 | CF45: 1.8 | CG45: =(CE45*$CH$7)+(CF45*$CI$7) -> 0.7701564 | CH45: =+CD45*CE45 -> 0 | CI45: =+CD45*CF45 -> 0 | CJ45: =CD45*CG45 -> 0 | CK45: =17.5*1.4*I45 -> #VALUE! | CL45: =17.5*1.4*J45 -> 294 | CM45: =CL45/30*J45 -> 117.6 | CO45: 293.57798 | CP45: =CM45*CD45 -> 0 | CQ45: =CO45*CD45 -> 0 | CR45: =CQ45/CJ45 -> #DIV/0! | CV45: =SUM(W45:AX45)*CO45 -> 0 | CX45: =COUNTA(R45:X45)*$CE45 -> 0 | CY45: =COUNTA(R45:X45)*$CF45 -> 0 | CZ45: =COUNTA(R45:X45)*$CG45 -> 0 | DA45: =COUNTA(Y45:AE45)*$CE45 -> 0 | DB45: =COUNTA(Y45:AE45)*$CF45 -> 0 | DC45: =COUNTA(Y45:AE45)*$CG45 -> 0 | DD45: =COUNTA(AF45:AL45)*$CE45 -> 0 | DE45: =COUNTA(AF45:AL45)*$CF45 -> 0 | DF45: =COUNTA(AF45:AL45)*$CG45 -> 0 | DG45: =COUNTA(AM45:AS45)*$CE45 -> 0 | DH45: =COUNTA(AM45:AS45)*$CF45 -> 0 | DI45: =COUNTA(AM45:AS45)*$CG45 -> 0 | DJ45: =COUNTA(AT45:AZ45)*$CE45 -> 0 | DK45: =COUNTA(AT45:AZ45)*$CF45 -> 0 | DL45: =COUNTA(AT45:AZ45)*$CG45 -> 0 | DM45: =COUNTA(BA45:BG45)*$CE45 -> 0 | DN45: =COUNTA(BA45:BG45)*$CF45 -> 0 | DO45: =COUNTA(BA45:BG45)*$CG45 -> 0 | DP45: =COUNTA(BH45:BN45)*$CE45 -> 0 | DQ45: =COUNTA(BH45:BN45)*$CF45 -> 0 | DR45: =COUNTA(BH45:BN45)*$CG45 -> 0
C46: TNV. COMO DICE EL DICHO | D46: 0.64583333 | E46: TELENOVELA | F46: LMWJV | G46: =IF(D46<=0.541,"DAY",(IF(D46<=0.74930556,"EARLY",(IF(D46<=0.97916667,"PRIME","LATE"))))) -> EARLY | H46: MOVILIZACIÓN | I46: BUMPER | J46: 12 | CD46: =SUM(K46:CC46) -> 0 | CF46: 2 | CG46: =(CE46*$CH$7)+(CF46*$CI$7) -> 0.85572934 | CH46: =+CD46*CE46 -> 0 | CI46: =+CD46*CF46 -> 0 | CJ46: =CD46*CG46 -> 0 | CK46: =17.5*1.4*I46 -> #VALUE! | CL46: =17.5*1.4*J46 -> 294 | CM46: =CL46/30*J46 -> 117.6 | CO46: 293.57798 | CP46: =CM46*CD46 -> 0 | CQ46: =CO46*CD46 -> 0 | CR46: =CQ46/CJ46 -> #DIV/0! | CV46: =SUM(W46:AX46)*CO46 -> 0 | CX46: =COUNTA(R46:X46)*$CE46 -> 0 | CY46: =COUNTA(R46:X46)*$CF46 -> 0 | CZ46: =COUNTA(R46:X46)*$CG46 -> 0 | DA46: =COUNTA(Y46:AE46)*$CE46 -> 0 | DB46: =COUNTA(Y46:AE46)*$CF46 -> 0 | DC46: =COUNTA(Y46:AE46)*$CG46 -> 0 | DD46: =COUNTA(AF46:AL46)*$CE46 -> 0 | DE46: =COUNTA(AF46:AL46)*$CF46 -> 0 | DF46: =COUNTA(AF46:AL46)*$CG46 -> 0 | DG46: =COUNTA(AM46:AS46)*$CE46 -> 0 | DH46: =COUNTA(AM46:AS46)*$CF46 -> 0 | DI46: =COUNTA(AM46:AS46)*$CG46 -> 0 | DJ46: =COUNTA(AT46:AZ46)*$CE46 -> 0 | DK46: =COUNTA(AT46:AZ46)*$CF46 -> 0 | DL46: =COUNTA(AT46:AZ46)*$CG46 -> 0 | DM46: =COUNTA(BA46:BG46)*$CE46 -> 0 | DN46: =COUNTA(BA46:BG46)*$CF46 -> 0 | DO46: =COUNTA(BA46:BG46)*$CG46 -> 0 | DP46: =COUNTA(BH46:BN46)*$CE46 -> 0 | DQ46: =COUNTA(BH46:BN46)*$CF46 -> 0 | DR46: =COUNTA(BH46:BN46)*$CG46 -> 0
C47: TNV. ASUNTOS DE FAMILIA | D47: 0.6875 | E47: TELENOVELA | F47: LMWJV | G47: =IF(D47<=0.541,"DAY",(IF(D47<=0.74930556,"EARLY",(IF(D47<=0.97916667,"PRIME","LATE"))))) -> EARLY | H47: MOVILIZACIÓN | I47: BUMPER | J47: 12 | CD47: =SUM(K47:CC47) -> 0 | CF47: 1.5 | CG47: =(CE47*$CH$7)+(CF47*$CI$7) -> 0.641797 | CH47: =+CD47*CE47 -> 0 | CI47: =+CD47*CF47 -> 0 | CJ47: =CD47*CG47 -> 0 | CK47: =7.5*1.1*I47 -> #VALUE! | CL47: =7.5*1.1*J47 -> 99 | CM47: =CL47/30*J47 -> 39.6 | CO47: 293.57798 | CP47: =CM47*CD47 -> 0 | CQ47: =CO47*CD47 -> 0 | CR47: =CQ47/CJ47 -> #DIV/0! | CV47: =SUM(W47:AX47)*CO47 -> 0 | CX47: =COUNTA(R47:X47)*$CE47 -> 0 | CY47: =COUNTA(R47:X47)*$CF47 -> 0 | CZ47: =COUNTA(R47:X47)*$CG47 -> 0 | DA47: =COUNTA(Y47:AE47)*$CE47 -> 0 | DB47: =COUNTA(Y47:AE47)*$CF47 -> 0 | DC47: =COUNTA(Y47:AE47)*$CG47 -> 0 | DD47: =COUNTA(AF47:AL47)*$CE47 -> 0 | DE47: =COUNTA(AF47:AL47)*$CF47 -> 0 | DF47: =COUNTA(AF47:AL47)*$CG47 -> 0 | DG47: =COUNTA(AM47:AS47)*$CE47 -> 0 | DH47: =COUNTA(AM47:AS47)*$CF47 -> 0 | DI47: =COUNTA(AM47:AS47)*$CG47 -> 0 | DJ47: =COUNTA(AT47:AZ47)*$CE47 -> 0 | DK47: =COUNTA(AT47:AZ47)*$CF47 -> 0 | DL47: =COUNTA(AT47:AZ47)*$CG47 -> 0 | DM47: =COUNTA(BA47:BG47)*$CE47 -> 0 | DN47: =COUNTA(BA47:BG47)*$CF47 -> 0 | DO47: =COUNTA(BA47:BG47)*$CG47 -> 0 | DP47: =COUNTA(BH47:BN47)*$CE47 -> 0 | DQ47: =COUNTA(BH47:BN47)*$CF47 -> 0 | DR47: =COUNTA(BH47:BN47)*$CG47 -> 0
C48: TNV. TERESA | D48: 0.72916667 | E48: TELENOVELA | F48: LMWJV | G48: =IF(D48<=0.541,"DAY",(IF(D48<=0.74930556,"EARLY",(IF(D48<=0.97916667,"PRIME","LATE"))))) -> EARLY | H48: MOVILIZACIÓN | I48: BUMPER | J48: 12 | CD48: =SUM(K48:CC48) -> 0 | CF48: 2.3 | CG48: =(CE48*$CH$7)+(CF48*$CI$7) -> 0.98408874 | CH48: =+CD48*CE48 -> 0 | CI48: =+CD48*CF48 -> 0 | CJ48: =CD48*CG48 -> 0 | CK48: =14.8*2.3*I48 -> #VALUE! | CL48: =14.8*2.3*J48 -> 408.48 | CM48: =CL48/30*J48 -> 163.392 | CO48: 293.57798 | CP48: =CM48*CD48 -> 0 | CQ48: =CO48*CD48 -> 0 | CR48: =CQ48/CJ48 -> #DIV/0! | CV48: =SUM(W48:AX48)*CO48 -> 0 | CX48: =COUNTA(R48:X48)*$CE48 -> 0 | CY48: =COUNTA(R48:X48)*$CF48 -> 0 | CZ48: =COUNTA(R48:X48)*$CG48 -> 0 | DA48: =COUNTA(Y48:AE48)*$CE48 -> 0 | DB48: =COUNTA(Y48:AE48)*$CF48 -> 0 | DC48: =COUNTA(Y48:AE48)*$CG48 -> 0 | DD48: =COUNTA(AF48:AL48)*$CE48 -> 0 | DE48: =COUNTA(AF48:AL48)*$CF48 -> 0 | DF48: =COUNTA(AF48:AL48)*$CG48 -> 0 | DG48: =COUNTA(AM48:AS48)*$CE48 -> 0 | DH48: =COUNTA(AM48:AS48)*$CF48 -> 0 | DI48: =COUNTA(AM48:AS48)*$CG48 -> 0 | DJ48: =COUNTA(AT48:AZ48)*$CE48 -> 0 | DK48: =COUNTA(AT48:AZ48)*$CF48 -> 0 | DL48: =COUNTA(AT48:AZ48)*$CG48 -> 0 | DM48: =COUNTA(BA48:BG48)*$CE48 -> 0 | DN48: =COUNTA(BA48:BG48)*$CF48 -> 0 | DO48: =COUNTA(BA48:BG48)*$CG48 -> 0 | DP48: =COUNTA(BH48:BN48)*$CE48 -> 0 | DQ48: =COUNTA(BH48:BN48)*$CF48 -> 0 | DR48: =COUNTA(BH48:BN48)*$CG48 -> 0
C49: LARGOMETRAJE (S) | D49: 0.8125 | E49: LARGOMETRAJE | F49: S | G49: =IF(D49<=0.541,"DAY",(IF(D49<=0.74930556,"EARLY",(IF(D49<=0.97916667,"PRIME","LATE"))))) -> PRIME | H49: MOVILIZACIÓN | I49: BUMPER | J49: 12 | CD49: =SUM(K49:CC49) -> 0 | CF49: 3 | CG49: =(CE49*$CH$7)+(CF49*$CI$7) -> 1.283594 | CH49: =+CD49*CE49 -> 0 | CI49: =+CD49*CF49 -> 0 | CJ49: =CD49*CG49 -> 0 | CK49: =14.8*4*I49 -> #VALUE! | CL49: =14.8*4*J49 -> 710.4 | CM49: =CL49/30*J49 -> 284.16 | CO49: 293.57798 | CP49: =CM49*CD49 -> 0 | CQ49: =CO49*CD49 -> 0 | CR49: =CQ49/CJ49 -> #DIV/0! | CV49: =SUM(W49:AX49)*CO49 -> 0 | CX49: =COUNTA(R49:X49)*$CE49 -> 0 | CY49: =COUNTA(R49:X49)*$CF49 -> 0 | CZ49: =COUNTA(R49:X49)*$CG49 -> 0 | DA49: =COUNTA(Y49:AE49)*$CE49 -> 0 | DB49: =COUNTA(Y49:AE49)*$CF49 -> 0 | DC49: =COUNTA(Y49:AE49)*$CG49 -> 0 | DD49: =COUNTA(AF49:AL49)*$CE49 -> 0 | DE49: =COUNTA(AF49:AL49)*$CF49 -> 0 | DF49: =COUNTA(AF49:AL49)*$CG49 -> 0 | DG49: =COUNTA(AM49:AS49)*$CE49 -> 0 | DH49: =COUNTA(AM49:AS49)*$CF49 -> 0 | DI49: =COUNTA(AM49:AS49)*$CG49 -> 0 | DJ49: =COUNTA(AT49:AZ49)*$CE49 -> 0 | DK49: =COUNTA(AT49:AZ49)*$CF49 -> 0 | DL49: =COUNTA(AT49:AZ49)*$CG49 -> 0 | DM49: =COUNTA(BA49:BG49)*$CE49 -> 0 | DN49: =COUNTA(BA49:BG49)*$CF49 -> 0 | DO49: =COUNTA(BA49:BG49)*$CG49 -> 0 | DP49: =COUNTA(BH49:BN49)*$CE49 -> 0 | DQ49: =COUNTA(BH49:BN49)*$CF49 -> 0 | DR49: =COUNTA(BH49:BN49)*$CG49 -> 0
C50: LARGOMETRAJE (D) | D50: 0.83333333 | E50: LARGOMETRAJE | F50: D | G50: =IF(D50<=0.541,"DAY",(IF(D50<=0.74930556,"EARLY",(IF(D50<=0.97916667,"PRIME","LATE"))))) -> PRIME | H50: MOVILIZACIÓN | I50: BUMPER | J50: 12 | CD50: =SUM(K50:CC50) -> 0 | CF50: 3 | CG50: =(CE50*$CH$7)+(CF50*$CI$7) -> 1.283594 | CH50: =+CD50*CE50 -> 0 | CI50: =+CD50*CF50 -> 0 | CJ50: =CD50*CG50 -> 0 | CK50: =14.8*4*I50 -> #VALUE! | CL50: =14.8*4*J50 -> 710.4 | CM50: =CL50/30*J50 -> 284.16 | CO50: 293.57798 | CP50: =CM50*CD50 -> 0 | CQ50: =CO50*CD50 -> 0 | CR50: =CQ50/CJ50 -> #DIV/0! | CV50: =SUM(W50:AX50)*CO50 -> 0 | CX50: =COUNTA(R50:X50)*$CE50 -> 0 | CY50: =COUNTA(R50:X50)*$CF50 -> 0 | CZ50: =COUNTA(R50:X50)*$CG50 -> 0 | DA50: =COUNTA(Y50:AE50)*$CE50 -> 0 | DB50: =COUNTA(Y50:AE50)*$CF50 -> 0 | DC50: =COUNTA(Y50:AE50)*$CG50 -> 0 | DD50: =COUNTA(AF50:AL50)*$CE50 -> 0 | DE50: =COUNTA(AF50:AL50)*$CF50 -> 0 | DF50: =COUNTA(AF50:AL50)*$CG50 -> 0 | DG50: =COUNTA(AM50:AS50)*$CE50 -> 0 | DH50: =COUNTA(AM50:AS50)*$CF50 -> 0 | DI50: =COUNTA(AM50:AS50)*$CG50 -> 0 | DJ50: =COUNTA(AT50:AZ50)*$CE50 -> 0 | DK50: =COUNTA(AT50:AZ50)*$CF50 -> 0 | DL50: =COUNTA(AT50:AZ50)*$CG50 -> 0 | DM50: =COUNTA(BA50:BG50)*$CE50 -> 0 | DN50: =COUNTA(BA50:BG50)*$CF50 -> 0 | DO50: =COUNTA(BA50:BG50)*$CG50 -> 0 | DP50: =COUNTA(BH50:BN50)*$CE50 -> 0 | DQ50: =COUNTA(BH50:BN50)*$CF50 -> 0 | DR50: =COUNTA(BH50:BN50)*$CG50 -> 0
C51: TNV. LA HIJA DEL EMBAJADOR | D51: 0.85416667 | E51: TELENOVELA | F51: LMWJV | G51: =IF(D51<=0.541,"DAY",(IF(D51<=0.74930556,"EARLY",(IF(D51<=0.97916667,"PRIME","LATE"))))) -> PRIME | H51: MOVILIZACIÓN | I51: BUMPER | J51: 12 | CD51: =SUM(K51:CC51) -> 0 | CF51: 4.4 | CG51: =(CE51*$CH$7)+(CF51*$CI$7) -> 1.8826045 | CH51: =+CD51*CE51 -> 0 | CI51: =+CD51*CF51 -> 0 | CJ51: =CD51*CG51 -> 0 | CK51: =12.4*2.5*I51 -> #VALUE! | CL51: =12.4*2.5*J51 -> 372 | CM51: =CL51/30*J51 -> 148.8 | CO51: 293.57798 | CP51: =CM51*CD51 -> 0 | CQ51: =CO51*CD51 -> 0 | CR51: =CQ51/CJ51 -> #DIV/0! | CV51: =SUM(W51:AX51)*CO51 -> 0 | CX51: =COUNTA(R51:X51)*$CE51 -> 0 | CY51: =COUNTA(R51:X51)*$CF51 -> 0 | CZ51: =COUNTA(R51:X51)*$CG51 -> 0 | DA51: =COUNTA(Y51:AE51)*$CE51 -> 0 | DB51: =COUNTA(Y51:AE51)*$CF51 -> 0 | DC51: =COUNTA(Y51:AE51)*$CG51 -> 0 | DD51: =COUNTA(AF51:AL51)*$CE51 -> 0 | DE51: =COUNTA(AF51:AL51)*$CF51 -> 0 | DF51: =COUNTA(AF51:AL51)*$CG51 -> 0 | DG51: =COUNTA(AM51:AS51)*$CE51 -> 0 | DH51: =COUNTA(AM51:AS51)*$CF51 -> 0 | DI51: =COUNTA(AM51:AS51)*$CG51 -> 0 | DJ51: =COUNTA(AT51:AZ51)*$CE51 -> 0 | DK51: =COUNTA(AT51:AZ51)*$CF51 -> 0 | DL51: =COUNTA(AT51:AZ51)*$CG51 -> 0 | DM51: =COUNTA(BA51:BG51)*$CE51 -> 0 | DN51: =COUNTA(BA51:BG51)*$CF51 -> 0 | DO51: =COUNTA(BA51:BG51)*$CG51 -> 0 | DP51: =COUNTA(BH51:BN51)*$CE51 -> 0 | DQ51: =COUNTA(BH51:BN51)*$CF51 -> 0 | DR51: =COUNTA(BH51:BN51)*$CG51 -> 0
C52: TNV. GOLDEN BOY | D52: 0.88541667 | E52: TELENOVELA | F52: LMWJV | G52: =IF(D52<=0.541,"DAY",(IF(D52<=0.74930556,"EARLY",(IF(D52<=0.97916667,"PRIME","LATE"))))) -> PRIME | H52: MOVILIZACIÓN | I52: BUMPER | J52: 12 | CD52: =SUM(K52:CC52) -> 0 | CF52: 4.6 | CG52: =(CE52*$CH$7)+(CF52*$CI$7) -> 1.9681775 | CH52: =+CD52*CE52 -> 0 | CI52: =+CD52*CF52 -> 0 | CJ52: =CD52*CG52 -> 0 | CK52: =1417/2 -> 708.5 | CL52: =1417/2 -> 708.5 | CM52: =CL52/30*J52 -> 283.4 | CO52: 293.57798 | CP52: =CM52*CD52 -> 0 | CQ52: =CO52*CD52 -> 0 | CR52: =CQ52/CJ52 -> #DIV/0! | CV52: =SUM(W52:AX52)*CO52 -> 0 | CX52: =COUNTA(R52:X52)*$CE52 -> 0 | CY52: =COUNTA(R52:X52)*$CF52 -> 0 | CZ52: =COUNTA(R52:X52)*$CG52 -> 0 | DA52: =COUNTA(Y52:AE52)*$CE52 -> 0 | DB52: =COUNTA(Y52:AE52)*$CF52 -> 0 | DC52: =COUNTA(Y52:AE52)*$CG52 -> 0 | DD52: =COUNTA(AF52:AL52)*$CE52 -> 0 | DE52: =COUNTA(AF52:AL52)*$CF52 -> 0 | DF52: =COUNTA(AF52:AL52)*$CG52 -> 0 | DG52: =COUNTA(AM52:AS52)*$CE52 -> 0 | DH52: =COUNTA(AM52:AS52)*$CF52 -> 0 | DI52: =COUNTA(AM52:AS52)*$CG52 -> 0 | DJ52: =COUNTA(AT52:AZ52)*$CE52 -> 0 | DK52: =COUNTA(AT52:AZ52)*$CF52 -> 0 | DL52: =COUNTA(AT52:AZ52)*$CG52 -> 0 | DM52: =COUNTA(BA52:BG52)*$CE52 -> 0 | DN52: =COUNTA(BA52:BG52)*$CF52 -> 0 | DO52: =COUNTA(BA52:BG52)*$CG52 -> 0 | DP52: =COUNTA(BH52:BN52)*$CE52 -> 0 | DQ52: =COUNTA(BH52:BN52)*$CF52 -> 0 | DR52: =COUNTA(BH52:BN52)*$CG52 -> 0
C53: LARGOMETRAJE (S) | D53: 0.89583333 | E53: LARGOMETRAJE | F53: S | G53: =IF(D53<=0.541,"DAY",(IF(D53<=0.74930556,"EARLY",(IF(D53<=0.97916667,"PRIME","LATE"))))) -> PRIME | H53: MOVILIZACIÓN | I53: BUMPER | J53: 12 | CD53: =SUM(K53:CC53) -> 0 | CF53: 3 | CG53: =(CE53*$CH$7)+(CF53*$CI$7) -> 1.283594 | CH53: =+CD53*CE53 -> 0 | CI53: =+CD53*CF53 -> 0 | CJ53: =CD53*CG53 -> 0 | CK53: =1417/2 -> 708.5 | CL53: =1417/2 -> 708.5 | CM53: =CL53/30*J53 -> 283.4 | CO53: 293.57798 | CP53: =CM53*CD53 -> 0 | CQ53: =CO53*CD53 -> 0 | CR53: =CQ53/CJ53 -> #DIV/0! | CV53: =SUM(W53:AX53)*CO53 -> 0 | CX53: =COUNTA(R53:X53)*$CE53 -> 0 | CY53: =COUNTA(R53:X53)*$CF53 -> 0 | CZ53: =COUNTA(R53:X53)*$CG53 -> 0 | DA53: =COUNTA(Y53:AE53)*$CE53 -> 0 | DB53: =COUNTA(Y53:AE53)*$CF53 -> 0 | DC53: =COUNTA(Y53:AE53)*$CG53 -> 0 | DD53: =COUNTA(AF53:AL53)*$CE53 -> 0 | DE53: =COUNTA(AF53:AL53)*$CF53 -> 0 | DF53: =COUNTA(AF53:AL53)*$CG53 -> 0 | DG53: =COUNTA(AM53:AS53)*$CE53 -> 0 | DH53: =COUNTA(AM53:AS53)*$CF53 -> 0 | DI53: =COUNTA(AM53:AS53)*$CG53 -> 0 | DJ53: =COUNTA(AT53:AZ53)*$CE53 -> 0 | DK53: =COUNTA(AT53:AZ53)*$CF53 -> 0 | DL53: =COUNTA(AT53:AZ53)*$CG53 -> 0 | DM53: =COUNTA(BA53:BG53)*$CE53 -> 0 | DN53: =COUNTA(BA53:BG53)*$CF53 -> 0 | DO53: =COUNTA(BA53:BG53)*$CG53 -> 0 | DP53: =COUNTA(BH53:BN53)*$CE53 -> 0 | DQ53: =COUNTA(BH53:BN53)*$CF53 -> 0 | DR53: =COUNTA(BH53:BN53)*$CG53 -> 0
C54: TNV. LA REINA DE LA NOCHE | D54: 0.91666667 | E54: TELENOVELA | F54: LMWJV | G54: =IF(D54<=0.541,"DAY",(IF(D54<=0.74930556,"EARLY",(IF(D54<=0.97916667,"PRIME","LATE"))))) -> PRIME | H54: MOVILIZACIÓN | I54: BUMPER | J54: 12 | CD54: =SUM(K54:CC54) -> 0 | CF54: 1.8 | CG54: =(CE54*$CH$7)+(CF54*$CI$7) -> 0.7701564 | CH54: =+CD54*CE54 -> 0 | CI54: =+CD54*CF54 -> 0 | CJ54: =CD54*CG54 -> 0 | CK54: =12.4*5*I54 -> #VALUE! | CL54: =12.4*5*J54 -> 744 | CM54: =CL54/30*J54 -> 297.6 | CO54: 293.57798 | CP54: =CM54*CD54 -> 0 | CQ54: =CO54*CD54 -> 0 | CR54: =CQ54/CJ54 -> #DIV/0! | CV54: =SUM(W54:AX54)*CO54 -> 0 | CX54: =COUNTA(R54:X54)*$CE54 -> 0 | CY54: =COUNTA(R54:X54)*$CF54 -> 0 | CZ54: =COUNTA(R54:X54)*$CG54 -> 0 | DA54: =COUNTA(Y54:AE54)*$CE54 -> 0 | DB54: =COUNTA(Y54:AE54)*$CF54 -> 0 | DC54: =COUNTA(Y54:AE54)*$CG54 -> 0 | DD54: =COUNTA(AF54:AL54)*$CE54 -> 0 | DE54: =COUNTA(AF54:AL54)*$CF54 -> 0 | DF54: =COUNTA(AF54:AL54)*$CG54 -> 0 | DG54: =COUNTA(AM54:AS54)*$CE54 -> 0 | DH54: =COUNTA(AM54:AS54)*$CF54 -> 0 | DI54: =COUNTA(AM54:AS54)*$CG54 -> 0 | DJ54: =COUNTA(AT54:AZ54)*$CE54 -> 0 | DK54: =COUNTA(AT54:AZ54)*$CF54 -> 0 | DL54: =COUNTA(AT54:AZ54)*$CG54 -> 0 | DM54: =COUNTA(BA54:BG54)*$CE54 -> 0 | DN54: =COUNTA(BA54:BG54)*$CF54 -> 0 | DO54: =COUNTA(BA54:BG54)*$CG54 -> 0 | DP54: =COUNTA(BH54:BN54)*$CE54 -> 0 | DQ54: =COUNTA(BH54:BN54)*$CF54 -> 0 | DR54: =COUNTA(BH54:BN54)*$CG54 -> 0
C55: LARGOMETRAJE (D) | D55: 0.91666667 | E55: LARGOMETRAJE | F55: D | G55: =IF(D55<=0.541,"DAY",(IF(D55<=0.74930556,"EARLY",(IF(D55<=0.97916667,"PRIME","LATE"))))) -> PRIME | H55: MOVILIZACIÓN | I55: BUMPER | J55: 12 | CD55: =SUM(K55:CC55) -> 0 | CF55: 3 | CG55: =(CE55*$CH$7)+(CF55*$CI$7) -> 1.283594 | CH55: =+CD55*CE55 -> 0 | CI55: =+CD55*CF55 -> 0 | CJ55: =CD55*CG55 -> 0 | CK55: =12.4*5*I55 -> #VALUE! | CL55: =12.4*5*J55 -> 744 | CM55: =CL55/30*J55 -> 297.6 | CO55: 293.57798 | CP55: =CM55*CD55 -> 0 | CQ55: =CO55*CD55 -> 0 | CR55: =CQ55/CJ55 -> #DIV/0! | CV55: =SUM(W55:AX55)*CO55 -> 0 | CX55: =COUNTA(R55:X55)*$CE55 -> 0 | CY55: =COUNTA(R55:X55)*$CF55 -> 0 | CZ55: =COUNTA(R55:X55)*$CG55 -> 0 | DA55: =COUNTA(Y55:AE55)*$CE55 -> 0 | DB55: =COUNTA(Y55:AE55)*$CF55 -> 0 | DC55: =COUNTA(Y55:AE55)*$CG55 -> 0 | DD55: =COUNTA(AF55:AL55)*$CE55 -> 0 | DE55: =COUNTA(AF55:AL55)*$CF55 -> 0 | DF55: =COUNTA(AF55:AL55)*$CG55 -> 0 | DG55: =COUNTA(AM55:AS55)*$CE55 -> 0 | DH55: =COUNTA(AM55:AS55)*$CF55 -> 0 | DI55: =COUNTA(AM55:AS55)*$CG55 -> 0 | DJ55: =COUNTA(AT55:AZ55)*$CE55 -> 0 | DK55: =COUNTA(AT55:AZ55)*$CF55 -> 0 | DL55: =COUNTA(AT55:AZ55)*$CG55 -> 0 | DM55: =COUNTA(BA55:BG55)*$CE55 -> 0 | DN55: =COUNTA(BA55:BG55)*$CF55 -> 0 | DO55: =COUNTA(BA55:BG55)*$CG55 -> 0 | DP55: =COUNTA(BH55:BN55)*$CE55 -> 0 | DQ55: =COUNTA(BH55:BN55)*$CF55 -> 0 | DR55: =COUNTA(BH55:BN55)*$CG55 -> 0
C56: TOTAL ECUAVISA 2 | K56: =SUM(K23:K55) -> 4 | L56: =SUM(L23:L55) -> 2 | M56: =SUM(M23:M55) -> 4 | N56: =SUM(N23:N55) -> 3 | O56: =SUM(O23:O55) -> 2 | P56: =SUM(P23:P55) -> 0 | Q56: =SUM(Q23:Q55) -> 2 | R56: =SUM(R23:R55) -> 5 | ... CD56: =SUM(CD23:CD55) -> 66 | CH56: =SUM(CH23:CH55) -> 0 | CI56: =SUM(CI23:CI55) -> 228.3 | CJ56: =SUM(CJ23:CJ55) -> 97.681504 | CP56: =SUM(CP23:CP55) -> 115413.07 | CQ56: =SUM(CQ23:CQ55) -> 16560 | CR56: =CQ56/CJ56 -> 169.53056 | CT56: =SUM(CT23:CT55) -> 8029.07 | CU56: =SUM(CU23:CU55) -> 8530.93 | CV56: =SUM(CV23:CV55) -> 0 | CX56: =SUM(CX23:CX55) -> 0 | CY56: =SUM(CY23:CY55) -> 50.3 | CZ56: =SUM(CZ23:CZ55) -> 21.307661 | DA56: =SUM(DA23:DA55) -> 0 | DB56: =SUM(DB23:DB55) -> 45.4 | DC56: =SUM(DC23:DC55) -> 21.521593 | DD56: =SUM(DD23:DD55) -> 0 | DE56: =SUM(DE23:DE55) -> 29 | ... DR56: =SUM(DR23:DR55) -> 0
CK57: PNT | CL57: PNT | CN57: REG-NOT | CO57: NOT ESTE
C58: TC TELEVISIÓN | CK58: 0.5 | CL58: 0.5 | CN58: 0.72 | CO58: 0.7 | CX58: 1 | DA58: 2 | DD58: 3 | DG58: 4 | DJ58: 5 | DM58: 6 | DP58: 7
C59: EL NOTICIERO I | D59: 0.29166667 | E59: NOTICIERO | F59: LMWJV | G59: =IF(D59<=0.541,"DAY",(IF(D59<=0.74930556,"EARLY",(IF(D59<=0.97916667,"PRIME","LATE"))))) -> DAY | H59: AWARENESS | I59: SPOT | J59: 40 | K59: 1 | N59: 1 | R59: 1 | U59: 1 | CD59: =SUM(K59:CC59) -> 4 | CE59: 2.1 | CF59: 3.1 | CG59: 3.82 | CH59: =+CD59*CE59 -> 8.4 | CI59: =+CD59*CF59 -> 12.4 | CJ59: =CD59*CG59 -> 15.28 | CK59: 1100 | CL59: 1100 | CM59: =CL59/30*J59 -> 1466.6667 | CN59: =CL59*(1-CN58) -> 308 | CO59: 448 | CP59: =CM59*CD59 -> 5866.6667 | CQ59: =CO59*CD59 -> 1792 | CR59: =CQ59/CJ59 -> 117.27749 | CT59: =SUM(K59:W59)*CO59 -> 1792 | CU59: =SUM(X59:AX59)*CO59 -> 0 | CX59: =COUNTA(R59:X59)*$CE59 -> 4.2 | CY59: =COUNTA(R59:X59)*$CF59 -> 6.2 | CZ59: =COUNTA(K59:Q59)*$CG59 -> 7.64 | DA59: =COUNTA(Y59:AE59)*$CE59 -> 0 | DB59: =COUNTA(Y59:AE59)*$CF59 -> 0 | DC59: =COUNTA(R59:X59)*$CG59 -> 7.64 | DD59: =COUNTA(AF59:AL59)*$CE59 -> 0 | DE59: =COUNTA(AF59:AL59)*$CF59 -> 0 | DF59: =COUNTA(Y59:AE59)*$CG59 -> 0 | DG59: =COUNTA(AM59:AS59)*$CE59 -> 0 | DH59: =COUNTA(AM59:AS59)*$CF59 -> 0 | DI59: =COUNTA(AF59:AL59)*$CG59 -> 0 | DJ59: =COUNTA(AT59:AZ59)*$CE59 -> 0 | DK59: =COUNTA(AT59:AZ59)*$CF59 -> 0 | DL59: =COUNTA(AM59:AS59)*$CG59 -> 0 | DM59: =COUNTA(BA59:BG59)*$CE59 -> 0 | DN59: =COUNTA(BA59:BG59)*$CF59 -> 0 | DO59: =COUNTA(AT59:AX59)*$CG59 -> 0 | DP59: =COUNTA(BH59:BN59)*$CE59 -> 0 | DQ59: =COUNTA(BH59:BN59)*$CF59 -> 0 | DR59: =COUNTA(BH59:BN59)*$CG59 -> 0
C60: ENTRE ELLAS | D60: 0.35416667 | E60: MAGAZINE | F60: LMWJV | G60: =IF(D60<=0.541,"DAY",(IF(D60<=0.74930556,"EARLY",(IF(D60<=0.97916667,"PRIME","LATE"))))) -> DAY | H60: AWARENESS | I60: SPOT | J60: 40 | K60: 1 | M60: 1 | S60: 1 | CD60: =SUM(K60:CC60) -> 3 | CE60: 1 | CF60: 2.3 | CG60: 2.16 | CH60: =+CD60*CE60 -> 3 | CI60: =+CD60*CF60 -> 6.9 | CJ60: =CD60*CG60 -> 6.48 | CK60: 900 | CL60: 900 | CM60: =CL60/30*J60 -> 1200 | CN60: =CL60*(1-CN57) -> #VALUE! | CO60: 280 | CP60: =CM60*CD60 -> 3600 | CQ60: =CO60*CD60 -> 840 | CR60: =CQ60/CJ60 -> 129.62963 | CT60: =SUM(K60:W60)*CO60 -> 840 | CU60: =SUM(X60:AX60)*CO60 -> 0 | CX60: =COUNTA(R60:X60)*$CE60 -> 1 | CY60: =COUNTA(R60:X60)*$CF60 -> 2.3 | CZ60: =COUNTA(K60:Q60)*$CG60 -> 4.32 | DA60: =COUNTA(Y60:AE60)*$CE60 -> 0 | DB60: =COUNTA(Y60:AE60)*$CF60 -> 0 | DC60: =COUNTA(R60:X60)*$CG60 -> 2.16 | DD60: =COUNTA(AF60:AL60)*$CE60 -> 0 | DE60: =COUNTA(AF60:AL60)*$CF60 -> 0 | DF60: =COUNTA(Y60:AE60)*$CG60 -> 0 | DG60: =COUNTA(AM60:AS60)*$CE60 -> 0 | DH60: =COUNTA(AM60:AS60)*$CF60 -> 0 | DI60: =COUNTA(AF60:AL60)*$CG60 -> 0 | DJ60: =COUNTA(AT60:AZ60)*$CE60 -> 0 | DK60: =COUNTA(AT60:AZ60)*$CF60 -> 0 | DL60: =COUNTA(AM60:AS60)*$CG60 -> 0 | DM60: =COUNTA(BA60:BG60)*$CE60 -> 0 | DN60: =COUNTA(BA60:BG60)*$CF60 -> 0 | DO60: =COUNTA(AT60:AX60)*$CG60 -> 0
C61: EL NOTICIERO II | D61: 0.52083333 | E61: NOTICIERO | F61: LMWJV | G61: =IF(D61<=0.541,"DAY",(IF(D61<=0.74930556,"EARLY",(IF(D61<=0.97916667,"PRIME","LATE"))))) -> DAY | H61: AWARENESS | I61: SPOT | J61: 40 | L61: 1 | N61: 1 | T61: 1 | CD61: =SUM(K61:CC61) -> 3 | CE61: 0.8 | CF61: 2.3 | CG61: 2.16 | CH61: =+CD61*CE61 -> 2.4 | CI61: =+CD61*CF61 -> 6.9 | CJ61: =CD61*CG61 -> 6.48 | CK61: 900 | CL61: 900 | CM61: =CL61/30*J61 -> 1200 | CN61: =CL61*(1-CN58) -> 252 | CO61: =CN61/30*J61 -> 336 | CP61: =CM61*CD61 -> 3600 | CQ61: =CO61*CD61 -> 1008 | CR61: =CQ61/CJ61 -> 155.55556 | CT61: =SUM(K61:W61)*CO61 -> 1008 | CU61: =SUM(X61:AX61)*CO61 -> 0 | CX61: =COUNTA(R61:X61)*$CE61 -> 0.8 | CY61: =COUNTA(R61:X61)*$CF61 -> 2.3 | CZ61: =COUNTA(K61:Q61)*$CG61 -> 4.32 | DA61: =COUNTA(Y61:AE61)*$CE61 -> 0 | DB61: =COUNTA(Y61:AE61)*$CF61 -> 0 | DC61: =COUNTA(R61:X61)*$CG61 -> 2.16 | DD61: =COUNTA(AF61:AL61)*$CE61 -> 0 | DE61: =COUNTA(AF61:AL61)*$CF61 -> 0 | DF61: =COUNTA(Y61:AE61)*$CG61 -> 0 | DG61: =COUNTA(AM61:AS61)*$CE61 -> 0 | DH61: =COUNTA(AM61:AS61)*$CF61 -> 0 | DI61: =COUNTA(AF61:AL61)*$CG61 -> 0 | DJ61: =COUNTA(AT61:AZ61)*$CE61 -> 0 | DK61: =COUNTA(AT61:AZ61)*$CF61 -> 0 | DL61: =COUNTA(AM61:AS61)*$CG61 -> 0 | DM61: =COUNTA(BA61:BG61)*$CE61 -> 0 | DN61: =COUNTA(BA61:BG61)*$CF61 -> 0 | DO61: =COUNTA(AT61:AX61)*$CG61 -> 0 | DP61: =COUNTA(BH61:BN61)*$CE61 -> 0 | DQ61: =COUNTA(BH61:BN61)*$CF61 -> 0 | DR61: =COUNTA(BH61:BN61)*$CG61 -> 0
C62: DESPUES DEL NOTICIERO | D62: 0.58333333 | E62: NOTICIERO | F62: LMWJV | G62: =IF(D62<=0.541,"DAY",(IF(D62<=0.74930556,"EARLY",(IF(D62<=0.97916667,"PRIME","LATE"))))) -> EARLY | H62: AWARENESS | I62: SPOT | J62: 40 | M62: 1 | S62: 1 | V62: 1 | CD62: =SUM(K62:CC62) -> 3 | CE62: 0.9 | CF62: 2.1 | CG62: 1.68 | CH62: =+CD62*CE62 -> 2.7 | CI62: =+CD62*CF62 -> 6.3 | CJ62: =CD62*CG62 -> 5.04 | CK62: 500 | CL62: 500 | CM62: =CL62/30*J62 -> 666.66667 | CN62: =CL62*(1-CN57) -> #VALUE! | CO62: 373.33 | CP62: =CM62*CD62 -> 2000 | CQ62: =CO62*CD62 -> 1119.99 | CR62: =CQ62/CJ62 -> 222.22024 | CT62: =SUM(K62:W62)*CO62 -> 1119.99 | CU62: =SUM(X62:AX62)*CO62 -> 0 | CX62: =COUNTA(R62:X62)*$CE62 -> 1.8 | CY62: =COUNTA(R62:X62)*$CF62 -> 4.2 | CZ62: =COUNTA(K62:Q62)*$CG62 -> 1.68 | DA62: =COUNTA(Y62:AE62)*$CE62 -> 0 | DB62: =COUNTA(Y62:AE62)*$CF62 -> 0 | DC62: =COUNTA(R62:X62)*$CG62 -> 3.36 | DD62: =COUNTA(AF62:AL62)*$CE62 -> 0 | DE62: =COUNTA(AF62:AL62)*$CF62 -> 0 | DF62: =COUNTA(Y62:AE62)*$CG62 -> 0 | DG62: =COUNTA(AM62:AS62)*$CE62 -> 0 | DH62: =COUNTA(AM62:AS62)*$CF62 -> 0 | DI62: =COUNTA(AF62:AL62)*$CG62 -> 0 | DJ62: =COUNTA(AT62:AZ62)*$CE62 -> 0 | DK62: =COUNTA(AT62:AZ62)*$CF62 -> 0 | DL62: =COUNTA(AM62:AS62)*$CG62 -> 0 | DM62: =COUNTA(BA62:BG62)*$CE62 -> 0 | DN62: =COUNTA(BA62:BG62)*$CF62 -> 0 | DO62: =COUNTA(AT62:AX62)*$CG62 -> 0
C63: TNV. CENNET | D63: 0.6875 | E63: TELENOVELA | F63: LMWJV | G63: =IF(D63<=0.541,"DAY",(IF(D63<=0.74930556,"EARLY",(IF(D63<=0.97916667,"PRIME","LATE"))))) -> EARLY | H63: AWARENESS | I63: SPOT | J63: 40 | L63: 1 | O63: 1 | CD63: =SUM(K63:CC63) -> 2 | CE63: 0.3 | CF63: 1.5 | CG63: 1.68 | CH63: =+CD63*CE63 -> 0.6 | CI63: =+CD63*CF63 -> 3 | CJ63: =CD63*CG63 -> 3.36 | CK63: 500 | CL63: 500 | CM63: =CL63/30*J63 -> 666.66667 | CN63: =CL63*(1-CN58) -> 140 | CO63: 224 | CP63: =CM63*CD63 -> 1333.3333 | CQ63: =CO63*CD63 -> 448 | CR63: =CQ63/CJ63 -> 133.33333 | CT63: =SUM(K63:W63)*CO63 -> 448 | CU63: =SUM(X63:AX63)*CO63 -> 0 | CX63: =COUNTA(R63:X63)*$CE63 -> 0 | CY63: =COUNTA(R63:X63)*$CF63 -> 0 | CZ63: =COUNTA(K63:Q63)*$CG63 -> 3.36 | DA63: =COUNTA(Y63:AE63)*$CE63 -> 0 | DB63: =COUNTA(Y63:AE63)*$CF63 -> 0 | DC63: =COUNTA(R63:X63)*$CG63 -> 0 | DD63: =COUNTA(AF63:AL63)*$CE63 -> 0 | DE63: =COUNTA(AF63:AL63)*$CF63 -> 0 | DF63: =COUNTA(Y63:AE63)*$CG63 -> 0 | DG63: =COUNTA(AM63:AS63)*$CE63 -> 0 | DH63: =COUNTA(AM63:AS63)*$CF63 -> 0 | DI63: =COUNTA(AF63:AL63)*$CG63 -> 0 | DJ63: =COUNTA(AT63:AZ63)*$CE63 -> 0 | DK63: =COUNTA(AT63:AZ63)*$CF63 -> 0 | DL63: =COUNTA(AM63:AS63)*$CG63 -> 0 | DM63: =COUNTA(BA63:BG63)*$CE63 -> 0 | DN63: =COUNTA(BA63:BG63)*$CF63 -> 0 | DO63: =COUNTA(AT63:AX63)*$CG63 -> 0 | DP63: =COUNTA(BH63:BN63)*$CE63 -> 0 | DQ63: =COUNTA(BH63:BN63)*$CF63 -> 0 | DR63: =COUNTA(BH63:BN63)*$CG63 -> 0
C64: MEMORIAS DEL CORAZON | D64: 0.72916667 | E64: TELENOVELA | F64: LMWJV | G64: =IF(D64<=0.541,"DAY",(IF(D64<=0.74930556,"EARLY",(IF(D64<=0.97916667,"PRIME","LATE"))))) -> EARLY | H64: AWARENESS | I64: SPOT | J64: 40 | K64: 1 | S64: 1 | CD64: =SUM(K64:CC64) -> 2 | CE64: 0.3 | CF64: 1.5 | CG64: 2.89 | CH64: =+CD64*CE64 -> 0.6 | CI64: =+CD64*CF64 -> 3 | CJ64: =CD64*CG64 -> 5.78 | CK64: 1000 | CL64: 1000 | CM64: =CL64/30*J64 -> 1333.3333 | CN64: =CL64*(1-CN58) -> 280 | CO64: 224 | CP64: =CM64*CD64 -> 2666.6667 | CQ64: =CO64*CD64 -> 448 | CR64: =CQ64/CJ64 -> 77.508651 | CT64: =SUM(K64:W64)*CO64 -> 448 | CU64: =SUM(X64:AX64)*CO64 -> 0 | CX64: =COUNTA(R64:X64)*$CE64 -> 0.3 | CY64: =COUNTA(R64:X64)*$CF64 -> 1.5 | CZ64: =COUNTA(K64:Q64)*$CG64 -> 2.89 | DA64: =COUNTA(Y64:AE64)*$CE64 -> 0 | DB64: =COUNTA(Y64:AE64)*$CF64 -> 0 | DC64: =COUNTA(R64:X64)*$CG64 -> 2.89 | DD64: =COUNTA(AF64:AL64)*$CE64 -> 0 | DE64: =COUNTA(AF64:AL64)*$CF64 -> 0 | DF64: =COUNTA(Y64:AE64)*$CG64 -> 0 | DG64: =COUNTA(AM64:AS64)*$CE64 -> 0 | DH64: =COUNTA(AM64:AS64)*$CF64 -> 0 | DI64: =COUNTA(AF64:AL64)*$CG64 -> 0 | DJ64: =COUNTA(AT64:AZ64)*$CE64 -> 0 | DK64: =COUNTA(AT64:AZ64)*$CF64 -> 0 | DL64: =COUNTA(AM64:AS64)*$CG64 -> 0 | DM64: =COUNTA(BA64:BG64)*$CE64 -> 0 | DN64: =COUNTA(BA64:BG64)*$CF64 -> 0 | DO64: =COUNTA(AT64:AX64)*$CG64 -> 0 | DP64: =COUNTA(BH64:BN64)*$CE64 -> 0 | DQ64: =COUNTA(BH64:BN64)*$CF64 -> 0 | DR64: =COUNTA(BH64:BN64)*$CG64 -> 0
C65: NOTICIERO DOMINICAL | D65: 0.79166667 | E65: NOTICIERO | F65: D | G65: =IF(D65<=0.541,"DAY",(IF(D65<=0.74930556,"EARLY",(IF(D65<=0.97916667,"PRIME","LATE"))))) -> PRIME | H65: AWARENESS | I65: SPOT | J65: 40 | Q65: 1 | CD65: =SUM(K65:CC65) -> 1 | CE65: 1.4 | CF65: 2.2 | CG65: 5.72 | CH65: =+CD65*CE65 -> 1.4 | CI65: =+CD65*CF65 -> 2.2 | CJ65: =CD65*CG65 -> 5.72 | CK65: 1600 | CL65: 1600 | CM65: =CL65/30*J65 -> 2133.3333 | CN65: =CL65*(1-CN58) -> 448 | CO65: 634.67 | CP65: =CM65*CD65 -> 2133.3333 | CQ65: =CO65*CD65 -> 634.67 | CR65: =CQ65/CJ65 -> 110.95629 | CT65: =SUM(K65:W65)*CO65 -> 634.67 | CU65: =SUM(X65:AX65)*CO65 -> 0 | CX65: =COUNTA(R65:X65)*$CE65 -> 0 | CY65: =COUNTA(R65:X65)*$CF65 -> 0 | CZ65: =COUNTA(K65:Q65)*$CG65 -> 5.72 | DA65: =COUNTA(Y65:AE65)*$CE65 -> 0 | DB65: =COUNTA(Y65:AE65)*$CF65 -> 0 | DC65: =COUNTA(R65:X65)*$CG65 -> 0 | DD65: =COUNTA(AF65:AL65)*$CE65 -> 0 | DE65: =COUNTA(AF65:AL65)*$CF65 -> 0 | DF65: =COUNTA(Y65:AE65)*$CG65 -> 0 | DG65: =COUNTA(AM65:AS65)*$CE65 -> 0 | DH65: =COUNTA(AM65:AS65)*$CF65 -> 0 | DI65: =COUNTA(AF65:AL65)*$CG65 -> 0 | DJ65: =COUNTA(AT65:AZ65)*$CE65 -> 0 | DK65: =COUNTA(AT65:AZ65)*$CF65 -> 0 | DL65: =COUNTA(AM65:AS65)*$CG65 -> 0 | DM65: =COUNTA(BA65:BG65)*$CE65 -> 0 | DN65: =COUNTA(BA65:BG65)*$CF65 -> 0 | DO65: =COUNTA(AT65:AX65)*$CG65 -> 0 | DP65: =COUNTA(BH65:BN65)*$CE65 -> 0 | DQ65: =COUNTA(BH65:BN65)*$CF65 -> 0 | DR65: =COUNTA(BH65:BN65)*$CG65 -> 0
C66: EL NOTICIERO III | D66: 0.79166667 | E66: NOTICIERO | F66: LMWJV | G66: =IF(D66<=0.541,"DAY",(IF(D66<=0.74930556,"EARLY",(IF(D66<=0.97916667,"PRIME","LATE"))))) -> PRIME | H66: AWARENESS | I66: SPOT | J66: 40 | K66: 1 | M66: 1 | R66: 1 | CD66: =SUM(K66:CC66) -> 3 | CE66: 1.3 | CF66: 4.3 | CG66: 5.72 | CH66: =+CD66*CE66 -> 3.9 | CI66: =+CD66*CF66 -> 12.9 | CJ66: =CD66*CG66 -> 17.16 | CK66: 2800 | CL66: 2800 | CM66: =CL66/30*J66 -> 3733.3333 | CN66: =CL66*(1-CO58) -> 840 | CO66: 1000 | CP66: =CM66*CD66 -> 11200 | CQ66: =CO66*CD66 -> 3000 | CR66: =CQ66/CJ66 -> 174.82517 | CT66: =SUM(K66:W66)*CO66 -> 3000 | CU66: =SUM(X66:AX66)*CO66 -> 0 | CX66: =COUNTA(R66:X66)*$CE66 -> 1.3 | CY66: =COUNTA(R66:X66)*$CF66 -> 4.3 | CZ66: =COUNTA(K66:Q66)*$CG66 -> 11.44 | DA66: =COUNTA(Y66:AE66)*$CE66 -> 0 | DB66: =COUNTA(Y66:AE66)*$CF66 -> 0 | DC66: =COUNTA(R66:X66)*$CG66 -> 5.72 | DD66: =COUNTA(AF66:AL66)*$CE66 -> 0 | DE66: =COUNTA(AF66:AL66)*$CF66 -> 0 | DF66: =COUNTA(Y66:AE66)*$CG66 -> 0 | DG66: =COUNTA(AM66:AS66)*$CE66 -> 0 | DH66: =COUNTA(AM66:AS66)*$CF66 -> 0 | DI66: =COUNTA(AF66:AL66)*$CG66 -> 0 | DJ66: =COUNTA(AT66:AZ66)*$CE66 -> 0 | DK66: =COUNTA(AT66:AZ66)*$CF66 -> 0 | DL66: =COUNTA(AM66:AS66)*$CG66 -> 0 | DM66: =COUNTA(BA66:BG66)*$CE66 -> 0 | DN66: =COUNTA(BA66:BG66)*$CF66 -> 0 | DO66: =COUNTA(AT66:AX66)*$CG66 -> 0 | DP66: =COUNTA(BH66:BN66)*$CE66 -> 0 | DQ66: =COUNTA(BH66:BN66)*$CF66 -> 0 | DR66: =COUNTA(BH66:BN66)*$CG66 -> 0
C67: TNV. CORAZON NEGRO | D67: 0.875 | E67: TELENOVELA | F67: LMWJV | G67: =IF(D67<=0.541,"DAY",(IF(D67<=0.74930556,"EARLY",(IF(D67<=0.97916667,"PRIME","LATE"))))) -> PRIME | H67: AWARENESS | I67: SPOT | J67: 40 | L67: 1 | N67: 1 | S67: 1 | CD67: =SUM(K67:CC67) -> 3 | CE67: 0.5 | CF67: 2.7 | CG67: 3.28 | CH67: =+CD67*CE67 -> 1.5 | CI67: =+CD67*CF67 -> 8.1 | CJ67: =CD67*CG67 -> 9.84 | CK67: 1600 | CL67: 1600 | CM67: =CL67/30*J67 -> 2133.3333 | CN67: =CL67*(1-CN58) -> 448 | CO67: 597.33 | CP67: =CM67*CD67 -> 6400 | CQ67: =CO67*CD67 -> 1791.99 | CR67: =CQ67/CJ67 -> 182.1128 | CT67: =SUM(K67:W67)*CO67 -> 1791.99 | CU67: =SUM(X67:AX67)*CO67 -> 0 | CX67: =COUNTA(R67:X67)*$CE67 -> 0.5 | CY67: =COUNTA(R67:X67)*$CF67 -> 2.7 | CZ67: =COUNTA(K67:Q67)*$CG67 -> 6.56 | DA67: =COUNTA(Y67:AE67)*$CE67 -> 0 | DB67: =COUNTA(Y67:AE67)*$CF67 -> 0 | DC67: =COUNTA(R67:X67)*$CG67 -> 3.28 | DD67: =COUNTA(AF67:AL67)*$CE67 -> 0 | DE67: =COUNTA(AF67:AL67)*$CF67 -> 0 | DF67: =COUNTA(Y67:AE67)*$CG67 -> 0 | DG67: =COUNTA(AM67:AS67)*$CE67 -> 0 | DH67: =COUNTA(AM67:AS67)*$CF67 -> 0 | DI67: =COUNTA(AF67:AL67)*$CG67 -> 0 | DJ67: =COUNTA(AT67:AZ67)*$CE67 -> 0 | DK67: =COUNTA(AT67:AZ67)*$CF67 -> 0 | DL67: =COUNTA(AM67:AS67)*$CG67 -> 0 | DM67: =COUNTA(BA67:BG67)*$CE67 -> 0 | DN67: =COUNTA(BA67:BG67)*$CF67 -> 0 | DO67: =COUNTA(AT67:AX67)*$CG67 -> 0 | DP67: =COUNTA(BH67:BN67)*$CE67 -> 0 | DQ67: =COUNTA(BH67:BN67)*$CF67 -> 0 | DR67: =COUNTA(BH67:BN67)*$CG67 -> 0
C68: EL NOTICIERO I | D68: 0.29166667 | E68: NOTICIERO | F68: LMWJV | G68: =IF(D68<=0.541,"DAY",(IF(D68<=0.74930556,"EARLY",(IF(D68<=0.97916667,"PRIME","LATE"))))) -> DAY | H68: AWARENESS | I68: SPOT | J68: 20 | Z68: 1 | AF68: 1 | AI68: 1 | AO68: 1 | AU68: 1 | CD68: =SUM(K68:CC68) -> 5 | CE68: 2.1 | CF68: 3.1 | CG68: 3.82 | CH68: =+CD68*CE68 -> 10.5 | CI68: =+CD68*CF68 -> 15.5 | CJ68: =CD68*CG68 -> 19.1 | CK68: 1100 | CL68: 1100 | CM68: =CL68/30*J68 -> 733.33333 | CN68: =CL68*(1-CN58) -> 308 | CO68: 224 | CP68: =CM68*CD68 -> 3666.6667 | CQ68: =CO68*CD68 -> 1120 | CR68: =CQ68/CJ68 -> 58.638743 | CT68: =SUM(K68:W68)*CO68 -> 0 | CU68: =SUM(X68:AX68)*CO68 -> 1120 | CX68: =COUNTA(R68:X68)*$CE68 -> 0 | CY68: =COUNTA(R68:X68)*$CF68 -> 0 | CZ68: =COUNTA(K68:Q68)*$CG68 -> 0 | DA68: =COUNTA(Y68:AE68)*$CE68 -> 2.1 | DB68: =COUNTA(Y68:AE68)*$CF68 -> 3.1 | DC68: =COUNTA(R68:X68)*$CG68 -> 0 | DD68: =COUNTA(AF68:AL68)*$CE68 -> 4.2 | DE68: =COUNTA(AF68:AL68)*$CF68 -> 6.2 | DF68: =COUNTA(Y68:AE68)*$CG68 -> 3.82 | DG68: =COUNTA(AM68:AS68)*$CE68 -> 2.1 | DH68: =COUNTA(AM68:AS68)*$CF68 -> 3.1 | DI68: =COUNTA(AF68:AL68)*$CG68 -> 7.64 | DJ68: =COUNTA(AT68:AZ68)*$CE68 -> 2.1 | DK68: =COUNTA(AT68:AZ68)*$CF68 -> 3.1 | DL68: =COUNTA(AM68:AS68)*$CG68 -> 3.82 | DM68: =COUNTA(BA68:BG68)*$CE68 -> 0 | DN68: =COUNTA(BA68:BG68)*$CF68 -> 0 | DO68: =COUNTA(AT68:AX68)*$CG68 -> 3.82 | DP68: =COUNTA(BH68:BN68)*$CE68 -> 0 | DQ68: =COUNTA(BH68:BN68)*$CF68 -> 0 | DR68: =COUNTA(BH68:BN68)*$CG68 -> 0
C69: ENTRE ELLAS | D69: 0.35416667 | E69: MAGAZINE | F69: LMWJV | G69: =IF(D69<=0.541,"DAY",(IF(D69<=0.74930556,"EARLY",(IF(D69<=0.97916667,"PRIME","LATE"))))) -> DAY | H69: AWARENESS | I69: SPOT | J69: 20 | AB69: 1 | AH69: 1 | AP69: 1 | CD69: =SUM(K69:CC69) -> 3 | CE69: 1 | CF69: 2.3 | CG69: 1.76 | CH69: =+CD69*CE69 -> 3 | CI69: =+CD69*CF69 -> 6.9 | CJ69: =CD69*CG69 -> 5.28 | CK69: 200 | CL69: 200 | CM69: =CL69 -> 200 | CN69: =CL69*(1-CL58) -> 100 | CO69: 140 | CP69: =CM69*CD69 -> 600 | CQ69: =CO69*CD69 -> 420 | CR69: =CQ69/CJ69 -> 79.545455 | CT69: =SUM(K69:W69)*CO69 -> 0 | CU69: =SUM(X69:AX69)*CO69 -> 420 | CX69: =COUNTA(R69:X69)*$CE69 -> 0 | CY69: =COUNTA(R69:X69)*$CF69 -> 0 | CZ69: =COUNTA(K69:Q69)*$CG69 -> 0 | DA69: =COUNTA(Y69:AE69)*$CE69 -> 1 | DB69: =COUNTA(Y69:AE69)*$CF69 -> 2.3 | DC69: =COUNTA(R69:X69)*$CG69 -> 0 | DD69: =COUNTA(AF69:AL69)*$CE69 -> 1 | DE69: =COUNTA(AF69:AL69)*$CF69 -> 2.3 | DF69: =COUNTA(Y69:AE69)*$CG69 -> 1.76 | DG69: =COUNTA(AM69:AS69)*$CE69 -> 1 | DH69: =COUNTA(AM69:AS69)*$CF69 -> 2.3 | DI69: =COUNTA(AF69:AL69)*$CG69 -> 1.76 | DJ69: =COUNTA(AT69:AZ69)*$CE69 -> 0 | DK69: =COUNTA(AT69:AZ69)*$CF69 -> 0 | DL69: =COUNTA(AM69:AS69)*$CG69 -> 1.76 | DM69: =COUNTA(BA69:BG69)*$CE69 -> 0 | DN69: =COUNTA(BA69:BG69)*$CF69 -> 0 | DO69: =COUNTA(AT69:AX69)*$CG69 -> 0 | DP69: =COUNTA(BH69:BN69)*$CE69 -> 0 | DQ69: =COUNTA(BH69:BN69)*$CF69 -> 0 | DR69: =COUNTA(BH69:BN69)*$CG69 -> 0
C70: EL NOTICIERO II | D70: 0.52083333 | E70: NOTICIERO | F70: LMWJV | G70: =IF(D70<=0.541,"DAY",(IF(D70<=0.74930556,"EARLY",(IF(D70<=0.97916667,"PRIME","LATE"))))) -> DAY | H70: AWARENESS | I70: SPOT | J70: 20 | Y70: 1 | AC70: 1 | AG70: 1 | CD70: =SUM(K70:CC70) -> 3 | CE70: 0.8 | CF70: 2.3 | CG70: 2.16 | CH70: =+CD70*CE70 -> 2.4 | CI70: =+CD70*CF70 -> 6.9 | CJ70: =CD70*CG70 -> 6.48 | CK70: 900 | CL70: 900 | CM70: =CL70/30*J70 -> 600 | CN70: =CL70*(1-CN58) -> 252 | CO70: 168 | CP70: =CM70*CD70 -> 1800 | CQ70: =CO70*CD70 -> 504 | CR70: =CQ70/CJ70 -> 77.777778 | CT70: =SUM(K70:W70)*CO70 -> 0 | CU70: =SUM(X70:AX70)*CO70 -> 504 | CX70: =COUNTA(R70:X70)*$CE70 -> 0 | CY70: =COUNTA(R70:X70)*$CF70 -> 0 | CZ70: =COUNTA(K70:Q70)*$CG70 -> 0 | DA70: =COUNTA(Y70:AE70)*$CE70 -> 1.6 | DB70: =COUNTA(Y70:AE70)*$CF70 -> 4.6 | DC70: =COUNTA(R70:X70)*$CG70 -> 0 | DD70: =COUNTA(AF70:AL70)*$CE70 -> 0.8 | DE70: =COUNTA(AF70:AL70)*$CF70 -> 2.3 | DF70: =COUNTA(Y70:AE70)*$CG70 -> 4.32 | DG70: =COUNTA(AM70:AS70)*$CE70 -> 0 | DH70: =COUNTA(AM70:AS70)*$CF70 -> 0 | DI70: =COUNTA(AF70:AL70)*$CG70 -> 2.16 | DJ70: =COUNTA(AT70:AZ70)*$CE70 -> 0 | DK70: =COUNTA(AT70:AZ70)*$CF70 -> 0 | DL70: =COUNTA(AM70:AS70)*$CG70 -> 0 | DM70: =COUNTA(BA70:BG70)*$CE70 -> 0 | DN70: =COUNTA(BA70:BG70)*$CF70 -> 0 | DO70: =COUNTA(AT70:AX70)*$CG70 -> 0 | DP70: =COUNTA(BH70:BN70)*$CE70 -> 0 | DQ70: =COUNTA(BH70:BN70)*$CF70 -> 0 | DR70: =COUNTA(BH70:BN70)*$CG70 -> 0
C71: DESPUES DEL NOTICIERO | D71: 0.58333333 | E71: NOTICIERO | F71: LMWJV | G71: =IF(D71<=0.541,"DAY",(IF(D71<=0.74930556,"EARLY",(IF(D71<=0.97916667,"PRIME","LATE"))))) -> EARLY | H71: AWARENESS | I71: SPOT | J71: 20 | AA71: 1 | AI71: 1 | AT71: 1 | CD71: =SUM(K71:CC71) -> 3 | CE71: 0.9 | CF71: 2.1 | CG71: 1.82 | CH71: =+CD71*CE71 -> 2.7 | CI71: =+CD71*CF71 -> 6.3 | CJ71: =CD71*CG71 -> 5.46 | CK71: 550 | CL71: 550 | CM71: =CL71/30*J71 -> 366.66667 | CN71: =CL71*(1-CN58) -> 154 | CO71: 186.67 | CP71: =CM71*CD71 -> 1100 | CQ71: =CO71*CD71 -> 560.01 | CR71: =CQ71/CJ71 -> 102.56593 | CT71: =SUM(K71:W71)*CO71 -> 0 | CU71: =SUM(X71:AX71)*CO71 -> 560.01 | CX71: =COUNTA(R71:X71)*$CE71 -> 0 | CY71: =COUNTA(R71:X71)*$CF71 -> 0 | CZ71: =COUNTA(K71:Q71)*$CG71 -> 0 | DA71: =COUNTA(Y71:AE71)*$CE71 -> 0.9 | DB71: =COUNTA(Y71:AE71)*$CF71 -> 2.1 | DC71: =COUNTA(R71:X71)*$CG71 -> 0 | DD71: =COUNTA(AF71:AL71)*$CE71 -> 0.9 | DE71: =COUNTA(AF71:AL71)*$CF71 -> 2.1 | DF71: =COUNTA(Y71:AE71)*$CG71 -> 1.82 | DG71: =COUNTA(AM71:AS71)*$CE71 -> 0 | DH71: =COUNTA(AM71:AS71)*$CF71 -> 0 | DI71: =COUNTA(AF71:AL71)*$CG71 -> 1.82 | DJ71: =COUNTA(AT71:AZ71)*$CE71 -> 0.9 | DK71: =COUNTA(AT71:AZ71)*$CF71 -> 2.1 | DL71: =COUNTA(AM71:AS71)*$CG71 -> 0 | DM71: =COUNTA(BA71:BG71)*$CE71 -> 0 | DN71: =COUNTA(BA71:BG71)*$CF71 -> 0 | DO71: =COUNTA(AT71:AX71)*$CG71 -> 1.82 | DP71: =COUNTA(BH71:BN71)*$CE71 -> 0 | DQ71: =COUNTA(BH71:BN71)*$CF71 -> 0 | DR71: =COUNTA(BH71:BN71)*$CG71 -> 0
C72: TNV. CENNET | D72: 0.6875 | E72: TELENOVELA | F72: LMWJV | G72: =IF(D72<=0.541,"DAY",(IF(D72<=0.74930556,"EARLY",(IF(D72<=0.97916667,"PRIME","LATE"))))) -> EARLY | H72: AWARENESS | I72: SPOT | J72: 20 | Z72: 1 | AF72: 1 | AP72: 1 | AU72: 1 | CD72: =SUM(K72:CC72) -> 4 | CE72: 0.3 | CF72: 1.5 | CG72: 1.68 | CH72: =+CD72*CE72 -> 1.2 | CI72: =+CD72*CF72 -> 6 | CJ72: =CD72*CG72 -> 6.72 | CK72: 350 | CL72: 350 | CM72: =CL72 -> 350 | CN72: =CL72*(1-CL58) -> 175 | CO72: 112 | CP72: =CM72*CD72 -> 1400 | CQ72: =CO72*CD72 -> 448 | CR72: =CQ72/CJ72 -> 66.666667 | CT72: =SUM(K72:W72)*CO72 -> 0 | CU72: =SUM(X72:AX72)*CO72 -> 448 | CX72: =COUNTA(R72:X72)*$CE72 -> 0 | CY72: =COUNTA(R72:X72)*$CF72 -> 0 | CZ72: =COUNTA(K72:Q72)*$CG72 -> 0 | DA72: =COUNTA(Y72:AE72)*$CE72 -> 0.3 | DB72: =COUNTA(Y72:AE72)*$CF72 -> 1.5 | DC72: =COUNTA(R72:X72)*$CG72 -> 0 | DD72: =COUNTA(AF72:AL72)*$CE72 -> 0.3 | DE72: =COUNTA(AF72:AL72)*$CF72 -> 1.5 | DF72: =COUNTA(Y72:AE72)*$CG72 -> 1.68 | DG72: =COUNTA(AM72:AS72)*$CE72 -> 0.3 | DH72: =COUNTA(AM72:AS72)*$CF72 -> 1.5 | DI72: =COUNTA(AF72:AL72)*$CG72 -> 1.68 | DJ72: =COUNTA(AT72:AZ72)*$CE72 -> 0.3 | DK72: =COUNTA(AT72:AZ72)*$CF72 -> 1.5 | DL72: =COUNTA(AM72:AS72)*$CG72 -> 1.68 | DM72: =COUNTA(BA72:BG72)*$CE72 -> 0 | DN72: =COUNTA(BA72:BG72)*$CF72 -> 0 | DO72: =COUNTA(AT72:AX72)*$CG72 -> 1.68 | DP72: =COUNTA(BH72:BN72)*$CE72 -> 0 | DQ72: =COUNTA(BH72:BN72)*$CF72 -> 0 | DR72: =COUNTA(BH72:BN72)*$CG72 -> 0
C73: NOTICIERO DOMINICAL | D73: 0.79166667 | E73: NOTICIERO | F73: D | G73: =IF(D73<=0.541,"DAY",(IF(D73<=0.74930556,"EARLY",(IF(D73<=0.97916667,"PRIME","LATE"))))) -> PRIME | H73: AWARENESS | I73: SPOT | J73: 20 | AE73: 1 | AS73: 1 | CD73: =SUM(K73:CC73) -> 2 | CE73: 0.3 | CF73: 1.5 | CG73: 5.72 | CH73: =+CD73*CE73 -> 0.6 | CI73: =+CD73*CF73 -> 3 | CJ73: =CD73*CG73 -> 11.44 | CK73: 1600 | CL73: 1600 | CM73: =CL73/30*J73 -> 1066.6667 | CN73: =CL73*(1-CN58) -> 448 | CO73: 317.33 | CP73: =CM73*CD73 -> 2133.3333 | CQ73: =CO73*CD73 -> 634.66 | CR73: =CQ73/CJ73 -> 55.477273 | CT73: =SUM(K73:W73)*CO73 -> 0 | CU73: =SUM(X73:AX73)*CO73 -> 634.66 | CX73: =COUNTA(R73:X73)*$CE73 -> 0 | CY73: =COUNTA(R73:X73)*$CF73 -> 0 | CZ73: =COUNTA(K73:Q73)*$CG73 -> 0 | DA73: =COUNTA(Y73:AE73)*$CE73 -> 0.3 | DB73: =COUNTA(Y73:AE73)*$CF73 -> 1.5 | DC73: =COUNTA(R73:X73)*$CG73 -> 0 | DD73: =COUNTA(AF73:AL73)*$CE73 -> 0 | DE73: =COUNTA(AF73:AL73)*$CF73 -> 0 | DF73: =COUNTA(Y73:AE73)*$CG73 -> 5.72 | DG73: =COUNTA(AM73:AS73)*$CE73 -> 0.3 | DH73: =COUNTA(AM73:AS73)*$CF73 -> 1.5 | DI73: =COUNTA(AF73:AL73)*$CG73 -> 0 | DJ73: =COUNTA(AT73:AZ73)*$CE73 -> 0 | DK73: =COUNTA(AT73:AZ73)*$CF73 -> 0 | DL73: =COUNTA(AM73:AS73)*$CG73 -> 5.72 | DM73: =COUNTA(BA73:BG73)*$CE73 -> 0 | DN73: =COUNTA(BA73:BG73)*$CF73 -> 0 | DO73: =COUNTA(AT73:AX73)*$CG73 -> 0 | DP73: =COUNTA(BH73:BN73)*$CE73 -> 0 | DQ73: =COUNTA(BH73:BN73)*$CF73 -> 0 | DR73: =COUNTA(BH73:BN73)*$CG73 -> 0
C74: EL NOTICIERO III | D74: 0.79166667 | E74: NOTICIERO | F74: LMWJV | G74: =IF(D74<=0.541,"DAY",(IF(D74<=0.74930556,"EARLY",(IF(D74<=0.97916667,"PRIME","LATE"))))) -> PRIME | H74: AWARENESS | I74: SPOT | J74: 20 | Y74: 1 | AF74: 1 | AO74: 1 | AV74: 1 | CD74: =SUM(K74:CC74) -> 4 | CE74: 1.4 | CF74: 2.2 | CG74: 5.72 | CH74: =+CD74*CE74 -> 5.6 | CI74: =+CD74*CF74 -> 8.8 | CJ74: =CD74*CG74 -> 22.88 | CK74: 2800 | CL74: 2800 | CM74: =CL74/30*J74 -> 1866.6667 | CN74: =CL74*(1-CO58) -> 840 | CO74: 500 | CP74: =CM74*CD74 -> 7466.6667 | CQ74: =CO74*CD74 -> 2000 | CR74: =CQ74/CJ74 -> 87.412587 | CT74: =SUM(K74:W74)*CO74 -> 0 | CU74: =SUM(X74:AX74)*CO74 -> 2000 | CX74: =COUNTA(R74:X74)*$CE74 -> 0 | CY74: =COUNTA(R74:X74)*$CF74 -> 0 | CZ74: =COUNTA(K74:Q74)*$CG74 -> 0 | DA74: =COUNTA(Y74:AE74)*$CE74 -> 1.4 | DB74: =COUNTA(Y74:AE74)*$CF74 -> 2.2 | DC74: =COUNTA(R74:X74)*$CG74 -> 0 | DD74: =COUNTA(AF74:AL74)*$CE74 -> 1.4 | DE74: =COUNTA(AF74:AL74)*$CF74 -> 2.2 | DF74: =COUNTA(Y74:AE74)*$CG74 -> 5.72 | DG74: =COUNTA(AM74:AS74)*$CE74 -> 1.4 | DH74: =COUNTA(AM74:AS74)*$CF74 -> 2.2 | DI74: =COUNTA(AF74:AL74)*$CG74 -> 5.72 | DJ74: =COUNTA(AT74:AZ74)*$CE74 -> 1.4 | DK74: =COUNTA(AT74:AZ74)*$CF74 -> 2.2 | DL74: =COUNTA(AM74:AS74)*$CG74 -> 5.72 | DM74: =COUNTA(BA74:BG74)*$CE74 -> 0 | DN74: =COUNTA(BA74:BG74)*$CF74 -> 0 | DO74: =COUNTA(AT74:AX74)*$CG74 -> 5.72 | DP74: =COUNTA(BH74:BN74)*$CE74 -> 0 | DQ74: =COUNTA(BH74:BN74)*$CF74 -> 0 | DR74: =COUNTA(BH74:BN74)*$CG74 -> 0
C75: TNV. CORAZON NEGRO | D75: 0.875 | E75: TELENOVELA | F75: LMWJV | G75: =IF(D75<=0.541,"DAY",(IF(D75<=0.74930556,"EARLY",(IF(D75<=0.97916667,"PRIME","LATE"))))) -> PRIME | H75: AWARENESS | I75: SPOT | J75: 20 | AB75: 1 | AH75: 1 | AP75: 1 | AU75: 1 | CD75: =SUM(K75:CC75) -> 4 | CE75: 1.3 | CF75: 4.3 | CG75: 3.28 | CH75: =+CD75*CE75 -> 5.2 | CI75: =+CD75*CF75 -> 17.2 | CJ75: =CD75*CG75 -> 13.12 | CK75: 1600 | CL75: 1600 | CM75: =CL75/30*J75 -> 1066.6667 | CN75: =CL75*(1-CN58) -> 448 | CO75: =CN75/30*J75 -> 298.66667 | CP75: =CM75*CD75 -> 4266.6667 | CQ75: =CO75*CD75 -> 1194.6667 | CR75: =CQ75/CJ75 -> 91.056911 | CT75: =SUM(K75:W75)*CO75 -> 0 | CU75: =SUM(X75:AX75)*CO75 -> 1194.6667 | CX75: =COUNTA(R75:X75)*$CE75 -> 0 | CY75: =COUNTA(R75:X75)*$CF75 -> 0 | CZ75: =COUNTA(K75:Q75)*$CG75 -> 0 | DA75: =COUNTA(Y75:AE75)*$CE75 -> 1.3 | DB75: =COUNTA(Y75:AE75)*$CF75 -> 4.3 | DC75: =COUNTA(R75:X75)*$CG75 -> 0 | DD75: =COUNTA(AF75:AL75)*$CE75 -> 1.3 | DE75: =COUNTA(AF75:AL75)*$CF75 -> 4.3 | DF75: =COUNTA(Y75:AE75)*$CG75 -> 3.28 | DG75: =COUNTA(AM75:AS75)*$CE75 -> 1.3 | DH75: =COUNTA(AM75:AS75)*$CF75 -> 4.3 | DI75: =COUNTA(AF75:AL75)*$CG75 -> 3.28 | DJ75: =COUNTA(AT75:AZ75)*$CE75 -> 1.3 | DK75: =COUNTA(AT75:AZ75)*$CF75 -> 4.3 | DL75: =COUNTA(AM75:AS75)*$CG75 -> 3.28 | DM75: =COUNTA(BA75:BG75)*$CE75 -> 0 | DN75: =COUNTA(BA75:BG75)*$CF75 -> 0 | DO75: =COUNTA(AT75:AX75)*$CG75 -> 3.28 | DP75: =COUNTA(BH75:BN75)*$CE75 -> 0 | DQ75: =COUNTA(BH75:BN75)*$CF75 -> 0 | DR75: =COUNTA(BH75:BN75)*$CG75 -> 0
C76: EL NOTICIERO I | D76: 0.29166667 | E76: NOTICIERO | F76: LMWJV | G76: =IF(D76<=0.541,"DAY",(IF(D76<=0.74930556,"EARLY",(IF(D76<=0.97916667,"PRIME","LATE"))))) -> DAY | H76: MOVILIZACIÓN | I76: BUMPER | J76: 12 | CD76: =SUM(K76:CC76) -> 0 | CE76: 0.5 | CF76: 2.7 | CG76: 3.82 | CH76: =+CD76*CE76 -> 0 | CI76: =+CD76*CF76 -> 0 | CJ76: =CD76*CG76 -> 0 | CK76: 1100 | CL76: 1100 | CM76: =CL76/30*J76 -> 440 | CN76: =CL76*(1-CL58) -> 550 | CO76: =(CN76/30*J76)*(1+10%) -> 242 | CP76: =CM76*CD76 -> 0 | CQ76: =CO76*CD76 -> 0 | CR76: =CQ76/CJ76 -> #DIV/0! | CV76: =SUM(W76:AX76)*CO76 -> 0 | CX76: =COUNTA(R76:X76)*$CE76 -> 0 | CY76: =COUNTA(R76:X76)*$CF76 -> 0 | CZ76: =COUNTA(R76:X76)*$CG76 -> 0 | DA76: =COUNTA(Y76:AE76)*$CE76 -> 0 | DB76: =COUNTA(Y76:AE76)*$CF76 -> 0 | DC76: =COUNTA(Y76:AE76)*$CG76 -> 0 | DD76: =COUNTA(AF76:AL76)*$CE76 -> 0 | DE76: =COUNTA(AF76:AL76)*$CF76 -> 0 | DF76: =COUNTA(AF76:AL76)*$CG76 -> 0 | DG76: =COUNTA(AM76:AS76)*$CE76 -> 0 | DH76: =COUNTA(AM76:AS76)*$CF76 -> 0 | DI76: =COUNTA(AM76:AS76)*$CG76 -> 0 | DJ76: =COUNTA(AT76:AZ76)*$CE76 -> 0 | DK76: =COUNTA(AT76:AZ76)*$CF76 -> 0 | DL76: =COUNTA(AT76:AZ76)*$CG76 -> 0 | DM76: =COUNTA(BA76:BG76)*$CE76 -> 0 | DN76: =COUNTA(BA76:BG76)*$CF76 -> 0 | DO76: =COUNTA(BA76:BG76)*$CG76 -> 0 | DP76: =COUNTA(BH76:BN76)*$CE76 -> 0 | DQ76: =COUNTA(BH76:BN76)*$CF76 -> 0 | DR76: =COUNTA(BH76:BN76)*$CG76 -> 0
C77: DE CASA DE EN CASA | D77: 0.41666667 | E77: MAGAZINE | F77: LMWJV | G77: =IF(D77<=0.541,"DAY",(IF(D77<=0.74930556,"EARLY",(IF(D77<=0.97916667,"PRIME","LATE"))))) -> DAY | H77: MOVILIZACIÓN | I77: BUMPER | J77: 12 | CD77: =SUM(K77:CC77) -> 0 | CE77: 0.4 | CF77: 1.5 | CG77: 1.76 | CH77: =+CD77*CE77 -> 0 | CI77: =+CD77*CF77 -> 0 | CJ77: =CD77*CG77 -> 0 | CK77: 450 | CL77: 450 | CM77: =CL77/30*J77 -> 180 | CN77: =CL77*(1-CL58) -> 225 | CO77: =(CN77/30*J77)*(1+10%) -> 99 | CP77: =CM77*CD77 -> 0 | CQ77: =CO77*CD77 -> 0 | CR77: =CQ77/CJ77 -> #DIV/0! | CV77: =SUM(W77:AX77)*CO77 -> 0 | CX77: =COUNTA(R77:X77)*$CE77 -> 0 | CY77: =COUNTA(R77:X77)*$CF77 -> 0 | CZ77: =COUNTA(R77:X77)*$CG77 -> 0 | DA77: =COUNTA(Y77:AE77)*$CE77 -> 0 | DB77: =COUNTA(Y77:AE77)*$CF77 -> 0 | DC77: =COUNTA(Y77:AE77)*$CG77 -> 0 | DD77: =COUNTA(AF77:AL77)*$CE77 -> 0 | DE77: =COUNTA(AF77:AL77)*$CF77 -> 0 | DF77: =COUNTA(AF77:AL77)*$CG77 -> 0 | DG77: =COUNTA(AM77:AS77)*$CE77 -> 0 | DH77: =COUNTA(AM77:AS77)*$CF77 -> 0 | DI77: =COUNTA(AM77:AS77)*$CG77 -> 0 | DJ77: =COUNTA(AT77:AZ77)*$CE77 -> 0 | DK77: =COUNTA(AT77:AZ77)*$CF77 -> 0 | DL77: =COUNTA(AT77:AZ77)*$CG77 -> 0 | DM77: =COUNTA(BA77:BG77)*$CE77 -> 0 | DN77: =COUNTA(BA77:BG77)*$CF77 -> 0 | DO77: =COUNTA(BA77:BG77)*$CG77 -> 0 | DP77: =COUNTA(BH77:BN77)*$CE77 -> 0 | DQ77: =COUNTA(BH77:BN77)*$CF77 -> 0 | DR77: =COUNTA(BH77:BN77)*$CG77 -> 0
C78: EL NOTICIERO II | D78: 0.52083333 | E78: NOTICIERO | F78: LMWJV | G78: =IF(D78<=0.541,"DAY",(IF(D78<=0.74930556,"EARLY",(IF(D78<=0.97916667,"PRIME","LATE"))))) -> DAY | H78: MOVILIZACIÓN | I78: BUMPER | J78: 12 | CD78: =SUM(K78:CC78) -> 0 | CE78: 1 | CF78: 2 | CG78: 2.16 | CH78: =+CD78*CE78 -> 0 | CI78: =+CD78*CF78 -> 0 | CJ78: =CD78*CG78 -> 0 | CK78: 900 | CL78: 900 | CM78: =CL78/30*J78 -> 360 | CN78: =CL78*(1-CL58) -> 450 | CO78: =(CN78/30*J78)*(1+10%) -> 198 | CP78: =CM78*CD78 -> 0 | CQ78: =CO78*CD78 -> 0 | CR78: =CQ78/CJ78 -> #DIV/0! | CV78: =SUM(W78:AX78)*CO78 -> 0 | CX78: =COUNTA(R78:X78)*$CE78 -> 0 | CY78: =COUNTA(R78:X78)*$CF78 -> 0 | CZ78: =COUNTA(R78:X78)*$CG78 -> 0 | DA78: =COUNTA(Y78:AE78)*$CE78 -> 0 | DB78: =COUNTA(Y78:AE78)*$CF78 -> 0 | DC78: =COUNTA(Y78:AE78)*$CG78 -> 0 | DD78: =COUNTA(AF78:AL78)*$CE78 -> 0 | DE78: =COUNTA(AF78:AL78)*$CF78 -> 0 | DF78: =COUNTA(AF78:AL78)*$CG78 -> 0 | DG78: =COUNTA(AM78:AS78)*$CE78 -> 0 | DH78: =COUNTA(AM78:AS78)*$CF78 -> 0 | DI78: =COUNTA(AM78:AS78)*$CG78 -> 0 | DJ78: =COUNTA(AT78:AZ78)*$CE78 -> 0 | DK78: =COUNTA(AT78:AZ78)*$CF78 -> 0 | DL78: =COUNTA(AT78:AZ78)*$CG78 -> 0 | DM78: =COUNTA(BA78:BG78)*$CE78 -> 0 | DN78: =COUNTA(BA78:BG78)*$CF78 -> 0 | DO78: =COUNTA(BA78:BG78)*$CG78 -> 0 | DP78: =COUNTA(BH78:BN78)*$CE78 -> 0 | DQ78: =COUNTA(BH78:BN78)*$CF78 -> 0 | DR78: =COUNTA(BH78:BN78)*$CG78 -> 0
C79: TNV. HIJO PRÓDIGO | D79: 0.625 | E79: TELENOVELA | F79: LMWJV | G79: =IF(D79<=0.541,"DAY",(IF(D79<=0.74930556,"EARLY",(IF(D79<=0.97916667,"PRIME","LATE"))))) -> EARLY | H79: MOVILIZACIÓN | I79: BUMPER | J79: 12 | CD79: =SUM(K79:CC79) -> 0 | CE79: 1.2 | CF79: 2.1 | CG79: 1.82 | CH79: =+CD79*CE79 -> 0 | CI79: =+CD79*CF79 -> 0 | CJ79: =CD79*CG79 -> 0 | CK79: 550 | CL79: 550 | CM79: =CL79/30*J79 -> 220 | CN79: =CL79*(1-CL58) -> 275 | CO79: =(CN79/30*J79)*(1+10%) -> 121 | CP79: =CM79*CD79 -> 0 | CQ79: =CO79*CD79 -> 0 | CR79: =CQ79/CJ79 -> #DIV/0! | CV79: =SUM(W79:AX79)*CO79 -> 0 | CX79: =COUNTA(R79:X79)*$CE79 -> 0 | CY79: =COUNTA(R79:X79)*$CF79 -> 0 | CZ79: =COUNTA(R79:X79)*$CG79 -> 0 | DA79: =COUNTA(Y79:AE79)*$CE79 -> 0 | DB79: =COUNTA(Y79:AE79)*$CF79 -> 0 | DC79: =COUNTA(Y79:AE79)*$CG79 -> 0 | DD79: =COUNTA(AF79:AL79)*$CE79 -> 0 | DE79: =COUNTA(AF79:AL79)*$CF79 -> 0 | DF79: =COUNTA(AF79:AL79)*$CG79 -> 0 | DG79: =COUNTA(AM79:AS79)*$CE79 -> 0 | DH79: =COUNTA(AM79:AS79)*$CF79 -> 0 | DI79: =COUNTA(AM79:AS79)*$CG79 -> 0 | DJ79: =COUNTA(AT79:AZ79)*$CE79 -> 0 | DK79: =COUNTA(AT79:AZ79)*$CF79 -> 0 | DL79: =COUNTA(AT79:AZ79)*$CG79 -> 0 | DM79: =COUNTA(BA79:BG79)*$CE79 -> 0 | DN79: =COUNTA(BA79:BG79)*$CF79 -> 0 | DO79: =COUNTA(BA79:BG79)*$CG79 -> 0 | DP79: =COUNTA(BH79:BN79)*$CE79 -> 0 | DQ79: =COUNTA(BH79:BN79)*$CF79 -> 0 | DR79: =COUNTA(BH79:BN79)*$CG79 -> 0
C80: TNV. MI DESTINO | D80: 0.6875 | E80: TELENOVELA | F80: LMWJV | G80: =IF(D80<=0.541,"DAY",(IF(D80<=0.74930556,"EARLY",(IF(D80<=0.97916667,"PRIME","LATE"))))) -> EARLY | H80: MOVILIZACIÓN | I80: BUMPER | J80: 12 | CD80: =SUM(K80:CC80) -> 0 | CE80: 0.9 | CF80: 2.1 | CG80: 1.68 | CH80: =+CD80*CE80 -> 0 | CI80: =+CD80*CF80 -> 0 | CJ80: =CD80*CG80 -> 0 | CK80: 500 | CL80: 500 | CM80: =CL80/30*J80 -> 200 | CN80: =CL80*(1-CL58) -> 250 | CO80: =(CN80/30*J80)*(1+10%) -> 110 | CP80: =CM80*CD80 -> 0 | CQ80: =CO80*CD80 -> 0 | CR80: =CQ80/CJ80 -> #DIV/0! | CV80: =SUM(W80:AX80)*CO80 -> 0 | CX80: =COUNTA(R80:X80)*$CE80 -> 0 | CY80: =COUNTA(R80:X80)*$CF80 -> 0 | CZ80: =COUNTA(R80:X80)*$CG80 -> 0 | DA80: =COUNTA(Y80:AE80)*$CE80 -> 0 | DB80: =COUNTA(Y80:AE80)*$CF80 -> 0 | DC80: =COUNTA(Y80:AE80)*$CG80 -> 0 | DD80: =COUNTA(AF80:AL80)*$CE80 -> 0 | DE80: =COUNTA(AF80:AL80)*$CF80 -> 0 | DF80: =COUNTA(AF80:AL80)*$CG80 -> 0 | DG80: =COUNTA(AM80:AS80)*$CE80 -> 0 | DH80: =COUNTA(AM80:AS80)*$CF80 -> 0 | DI80: =COUNTA(AM80:AS80)*$CG80 -> 0 | DJ80: =COUNTA(AT80:AZ80)*$CE80 -> 0 | DK80: =COUNTA(AT80:AZ80)*$CF80 -> 0 | DL80: =COUNTA(AT80:AZ80)*$CG80 -> 0 | DM80: =COUNTA(BA80:BG80)*$CE80 -> 0 | DN80: =COUNTA(BA80:BG80)*$CF80 -> 0 | DO80: =COUNTA(BA80:BG80)*$CG80 -> 0 | DP80: =COUNTA(BH80:BN80)*$CE80 -> 0 | DQ80: =COUNTA(BH80:BN80)*$CF80 -> 0 | DR80: =COUNTA(BH80:BN80)*$CG80 -> 0
C81: SOY EL MEJOR | D81: 0.72916667 | E81: ENTRETENIMIENTO | F81: LMWJV | G81: =IF(D81<=0.541,"DAY",(IF(D81<=0.74930556,"EARLY",(IF(D81<=0.97916667,"PRIME","LATE"))))) -> EARLY | H81: MOVILIZACIÓN | I81: BUMPER | J81: 12 | CD81: =SUM(K81:CC81) -> 0 | CE81: 0.7 | CF81: 2.6 | CG81: 2.89 | CH81: =+CD81*CE81 -> 0 | CI81: =+CD81*CF81 -> 0 | CJ81: =CD81*CG81 -> 0 | CK81: 1000 | CL81: 1000 | CM81: =CL81/30*J81 -> 400 | CN81: =CL81*(1-CL58) -> 500 | CO81: =(CN81/30*J81)*(1+10%) -> 220 | CP81: =CM81*CD81 -> 0 | CQ81: =CO81*CD81 -> 0 | CR81: =CQ81/CJ81 -> #DIV/0! | CV81: =SUM(W81:AX81)*CO81 -> 0 | CX81: =COUNTA(R81:X81)*$CE81 -> 0 | CY81: =COUNTA(R81:X81)*$CF81 -> 0 | CZ81: =COUNTA(R81:X81)*$CG81 -> 0 | DA81: =COUNTA(Y81:AE81)*$CE81 -> 0 | DB81: =COUNTA(Y81:AE81)*$CF81 -> 0 | DC81: =COUNTA(Y81:AE81)*$CG81 -> 0 | DD81: =COUNTA(AF81:AL81)*$CE81 -> 0 | DE81: =COUNTA(AF81:AL81)*$CF81 -> 0 | DF81: =COUNTA(AF81:AL81)*$CG81 -> 0 | DG81: =COUNTA(AM81:AS81)*$CE81 -> 0 | DH81: =COUNTA(AM81:AS81)*$CF81 -> 0 | DI81: =COUNTA(AM81:AS81)*$CG81 -> 0 | DJ81: =COUNTA(AT81:AZ81)*$CE81 -> 0 | DK81: =COUNTA(AT81:AZ81)*$CF81 -> 0 | DL81: =COUNTA(AT81:AZ81)*$CG81 -> 0 | DM81: =COUNTA(BA81:BG81)*$CE81 -> 0 | DN81: =COUNTA(BA81:BG81)*$CF81 -> 0 | DO81: =COUNTA(BA81:BG81)*$CG81 -> 0 | DP81: =COUNTA(BH81:BN81)*$CE81 -> 0 | DQ81: =COUNTA(BH81:BN81)*$CF81 -> 0 | DR81: =COUNTA(BH81:BN81)*$CG81 -> 0
C82: NOTICIERO DOMINICAL | D82: 0.79166667 | E82: NOTICIERO | F82: D | G82: =IF(D82<=0.541,"DAY",(IF(D82<=0.74930556,"EARLY",(IF(D82<=0.97916667,"PRIME","LATE"))))) -> PRIME | H82: MOVILIZACIÓN | I82: BUMPER | J82: 12 | CD82: =SUM(K82:CC82) -> 0 | CE82: 1.7 | CF82: 1.6 | CG82: 5.72 | CH82: =+CD82*CE82 -> 0 | CI82: =+CD82*CF82 -> 0 | CJ82: =CD82*CG82 -> 0 | CK82: 1600 | CL82: 1600 | CM82: =CL82/30*J82 -> 640 | CN82: =CL82*(1-CL58) -> 800 | CO82: =(CN82/30*J82)*(1+10%) -> 352 | CP82: =CM82*CD82 -> 0 | CQ82: =CO82*CD82 -> 0 | CR82: =CQ82/CJ82 -> #DIV/0! | CV82: =SUM(W82:AX82)*CO82 -> 0 | CX82: =COUNTA(R82:X82)*$CE82 -> 0 | CY82: =COUNTA(R82:X82)*$CF82 -> 0 | CZ82: =COUNTA(R82:X82)*$CG82 -> 0 | DA82: =COUNTA(Y82:AE82)*$CE82 -> 0 | DB82: =COUNTA(Y82:AE82)*$CF82 -> 0 | DC82: =COUNTA(Y82:AE82)*$CG82 -> 0 | DD82: =COUNTA(AF82:AL82)*$CE82 -> 0 | DE82: =COUNTA(AF82:AL82)*$CF82 -> 0 | DF82: =COUNTA(AF82:AL82)*$CG82 -> 0 | DG82: =COUNTA(AM82:AS82)*$CE82 -> 0 | DH82: =COUNTA(AM82:AS82)*$CF82 -> 0 | DI82: =COUNTA(AM82:AS82)*$CG82 -> 0 | DJ82: =COUNTA(AT82:AZ82)*$CE82 -> 0 | DK82: =COUNTA(AT82:AZ82)*$CF82 -> 0 | DL82: =COUNTA(AT82:AZ82)*$CG82 -> 0 | DM82: =COUNTA(BA82:BG82)*$CE82 -> 0 | DN82: =COUNTA(BA82:BG82)*$CF82 -> 0 | DO82: =COUNTA(BA82:BG82)*$CG82 -> 0 | DP82: =COUNTA(BH82:BN82)*$CE82 -> 0 | DQ82: =COUNTA(BH82:BN82)*$CF82 -> 0 | DR82: =COUNTA(BH82:BN82)*$CG82 -> 0
C83: EL NOTICIERO III | D83: 0.79166667 | E83: NOTICIERO | F83: LMWJV | G83: =IF(D83<=0.541,"DAY",(IF(D83<=0.74930556,"EARLY",(IF(D83<=0.97916667,"PRIME","LATE"))))) -> PRIME | H83: MOVILIZACIÓN | I83: BUMPER | J83: 12 | CD83: =SUM(K83:CC83) -> 0 | CE83: 1.8 | CF83: 3.9 | CG83: 5.72 | CH83: =+CD83*CE83 -> 0 | CI83: =+CD83*CF83 -> 0 | CJ83: =CD83*CG83 -> 0 | CK83: 2800 | CL83: 2800 | CM83: =CL83/30*J83 -> 1120 | CN83: =CL83*(1-CL58) -> 1400 | CO83: =(CN83/30*J83)*(1+10%) -> 616 | CP83: =CM83*CD83 -> 0 | CQ83: =CO83*CD83 -> 0 | CR83: =CQ83/CJ83 -> #DIV/0! | CV83: =SUM(W83:AX83)*CO83 -> 0 | CX83: =COUNTA(R83:X83)*$CE83 -> 0 | CY83: =COUNTA(R83:X83)*$CF83 -> 0 | CZ83: =COUNTA(R83:X83)*$CG83 -> 0 | DA83: =COUNTA(Y83:AE83)*$CE83 -> 0 | DB83: =COUNTA(Y83:AE83)*$CF83 -> 0 | DC83: =COUNTA(Y83:AE83)*$CG83 -> 0 | DD83: =COUNTA(AF83:AL83)*$CE83 -> 0 | DE83: =COUNTA(AF83:AL83)*$CF83 -> 0 | DF83: =COUNTA(AF83:AL83)*$CG83 -> 0 | DG83: =COUNTA(AM83:AS83)*$CE83 -> 0 | DH83: =COUNTA(AM83:AS83)*$CF83 -> 0 | DI83: =COUNTA(AM83:AS83)*$CG83 -> 0 | DJ83: =COUNTA(AT83:AZ83)*$CE83 -> 0 | DK83: =COUNTA(AT83:AZ83)*$CF83 -> 0 | DL83: =COUNTA(AT83:AZ83)*$CG83 -> 0 | DM83: =COUNTA(BA83:BG83)*$CE83 -> 0 | DN83: =COUNTA(BA83:BG83)*$CF83 -> 0 | DO83: =COUNTA(BA83:BG83)*$CG83 -> 0 | DP83: =COUNTA(BH83:BN83)*$CE83 -> 0 | DQ83: =COUNTA(BH83:BN83)*$CF83 -> 0 | DR83: =COUNTA(BH83:BN83)*$CG83 -> 0
